[
  {
    "question": "伝道の書の冒頭に記されている有名なフレーズは何ですか？",
    "choices": [
      "虚しい、虚しい、虚しい。すべて虚しい。",
      "永遠の輝きはここになし",
      "希望に満ちた新しい朝",
      "光と闇の交錯"
    ],
    "answer": "虚しい、虚しい、虚しい。すべて虚しい。",
    "explanation": "伝道の書1章2節は、人生のはかなさと虚無感を強調するためにこの有名な言葉で始まります。",
    "sources": [
      "伝道の書 1:2"
    ],
    "tags": [
      "旧約聖書",
      "伝道の書"
    ]
  },
  {
    "question": "伝道の書1章9節において『何が新しいか』という問いが示す意味は何ですか？",
    "choices": [
      "世界は常に変化し続ける",
      "過去と同じことの繰り返しである",
      "未来は完全に未知である",
      "新しい発見が日々起こる"
    ],
    "answer": "過去と同じことの繰り返しである",
    "explanation": "伝道の書は、過ぎ去ったものは再び繰り返され、何も新しいものはないと説いています。",
    "sources": [
      "伝道の書 1:9"
    ],
    "tags": [
      "旧約聖書",
      "伝道の書"
    ]
  },
  {
    "question": "伝道の書で『太陽の下』という表現は何を意味していますか？",
    "choices": [
      "天上の理想世界",
      "神の御前の世界",
      "現実の人間生活",
      "未来への希望"
    ],
    "answer": "現実の人間生活",
    "explanation": "『太陽の下』は、地上で営まれる日常生活や現実の世界を象徴する表現です。",
    "sources": [
      "伝道の書 1:3"
    ],
    "tags": [
      "旧約聖書",
      "伝道の書"
    ]
  },
  {
    "question": "伝道の書2章で、快楽や知恵の追求の結果として伝道者が導いた結論は何ですか？",
    "choices": [
      "永遠の幸福を得た",
      "豊かな報いにつながった",
      "すべては結局虚しい",
      "神の啓示に達した"
    ],
    "answer": "すべては結局虚しい",
    "explanation": "伝道書2章では、あらゆる快楽や知恵の追求も、最終的には何もかも虚しく感じられるという結論に至ります。",
    "sources": [
      "伝道の書 2:11"
    ],
    "tags": [
      "旧約聖書",
      "伝道の書"
    ]
  },
  {
    "question": "伝道の書3章1節のテーマは何ですか？",
    "choices": [
      "人間の自由意志",
      "万物には定められた時がある",
      "永遠の生命",
      "神の審判"
    ],
    "answer": "万物には定められた時がある",
    "explanation": "3章1節は『万物にはその時がある』と語り、人生や出来事に定められた時が存在することを示しています。",
    "sources": [
      "伝道の書 3:1"
    ],
    "tags": [
      "旧約聖書",
      "伝道の書"
    ]
  },
  {
    "question": "伝道の書3章では、どのような対比が描かれていますか？",
    "choices": [
      "富と貧困",
      "生と死",
      "光と闇",
      "愛と憎しみ"
    ],
    "answer": "生と死",
    "explanation": "伝道書3章では、誕生と死、始まりと終わりなど、生と死の対比が鮮明に描かれています。",
    "sources": [
      "伝道の書 3:2"
    ],
    "tags": [
      "旧約聖書",
      "伝道の書"
    ]
  },
  {
    "question": "伝道の書3章の『時には泣く時があり、笑う時もある』という記述は何を意味していますか？",
    "choices": [
      "人は常に悲しみに暮れる",
      "人生は正反対の感情が交錯する",
      "喜びだけを追求すべき",
      "感情は表面的なものである"
    ],
    "answer": "人生は正反対の感情が交錯する",
    "explanation": "この詩は人生の様々な感情が入り混じっている現実を象徴しており、喜びと悲しみが同時に存在することを示しています。",
    "sources": [
      "伝道の書 3:4"
    ],
    "tags": [
      "旧約聖書",
      "伝道の書"
    ]
  },
  {
    "question": "伝道の書で人間の労苦や努力が表すものは何とされていますか？",
    "choices": [
      "神からの祝福を受ける",
      "永遠の名誉を得る",
      "最終的には無意味に終わる",
      "社会の発展につながる"
    ],
    "answer": "最終的には無意味に終わる",
    "explanation": "伝道者は、どんなに努力してもその結末は虚しく、報われないことを繰り返し示しています。",
    "sources": [
      "伝道の書 1:3",
      "伝道の書 2:11"
    ],
    "tags": [
      "旧約聖書",
      "伝道の書"
    ]
  },
  {
    "question": "伝道の書で物事の循環性が語られる例として、次のうち正しいものはどれですか？",
    "choices": [
      "日の出と日の入り",
      "季節の移り変わり",
      "月の満ち欠け",
      "星の瞬き"
    ],
    "answer": "季節の移り変わり",
    "explanation": "伝道書は、季節の移り変わりを例に挙げ、万物が一定の周期で繰り返されることを説いています。",
    "sources": [
      "伝道の書 3:1"
    ],
    "tags": [
      "旧約聖書",
      "伝道の書"
    ]
  },
  {
    "question": "伝道の書から導かれる主要な教訓の一つは何ですか？",
    "choices": [
      "人生は常に進歩する",
      "人間は自分の力で運命を変えられる",
      "何も新しいことはなく、虚しさが支配する",
      "努力すれば必ず報われる"
    ],
    "answer": "何も新しいことはなく、虚しさが支配する",
    "explanation": "伝道書は、あらゆる営みや努力が結局は虚しく、永続的な価値を持たないという結論に達します。",
    "sources": [
      "伝道の書 1:2",
      "伝道の書 1:9"
    ],
    "tags": [
      "旧約聖書",
      "伝道の書"
    ]
  },
  {
    "question": "伝道の書で語られる『知恵』の役割は次のうちどれですか？",
    "choices": [
      "全ての謎を解き明かす鍵",
      "人生の矛盾を理解する助け",
      "不滅の生命をもたらす",
      "神の御心を明かす方法"
    ],
    "answer": "人生の矛盾を理解する助け",
    "explanation": "伝道者は、知恵を通して人生の矛盾や無常さについて深く考察しようとしています。",
    "sources": [
      "伝道の書 2:13"
    ],
    "tags": [
      "旧約聖書",
      "伝道の書"
    ]
  },
  {
    "question": "伝道の書で『働くことの虚しさ』が説かれているのはどのような意図からですか？",
    "choices": [
      "労働は常に神の御心に反する",
      "努力しても最終的には報いがない",
      "働けば富と名声が得られる",
      "労働は天からの祝福をもたらす"
    ],
    "answer": "努力しても最終的には報いがない",
    "explanation": "伝道者は、人間のあらゆる労働や努力が、結局は虚しさに終わると述べています。",
    "sources": [
      "伝道の書 2:11"
    ],
    "tags": [
      "旧約聖書",
      "伝道の書"
    ]
  },
  {
    "question": "『無為徒労』という概念は伝道の書のどの部分で強調されていますか？",
    "choices": [
      "1章",
      "2章",
      "3章",
      "5章"
    ],
    "answer": "2章",
    "explanation": "2章で伝道者は、多くの労苦や享楽の追求が、結局は無駄な努力に終わると強調しています。",
    "sources": [
      "伝道の書 2:11"
    ],
    "tags": [
      "旧約聖書",
      "伝道の書"
    ]
  },
  {
    "question": "伝道の書で『運命の定まり』の概念は、どの現象に例えられていますか？",
    "choices": [
      "川の流れ",
      "風の流れ",
      "潮の満ち引き",
      "星の軌道"
    ],
    "answer": "潮の満ち引き",
    "explanation": "潮の満ち引きのように、物事には必然的な周期や運命があることが示されています。",
    "sources": [
      "伝道の書 3:1"
    ],
    "tags": [
      "旧約聖書",
      "伝道の書"
    ]
  },
  {
    "question": "伝道の書で人生の短さはどのように表現されていますか？",
    "choices": [
      "永遠に続く旅として",
      "一瞬の輝きとして",
      "無限の試練として",
      "果てなき成長として"
    ],
    "answer": "一瞬の輝きとして",
    "explanation": "伝道者は、人生の一瞬一瞬がはかなく、つかの間の輝きであることを示しています。",
    "sources": [
      "伝道の書 9:11"
    ],
    "tags": [
      "旧約聖書",
      "伝道の書"
    ]
  },
  {
    "question": "伝道の書で『人間の知識』の限界はどのように示されていますか？",
    "choices": [
      "知識が幸せを保証する",
      "知識を積めば全てが解明される",
      "知識は必ずしも幸福をもたらさない",
      "知識が無ければ救われない"
    ],
    "answer": "知識は必ずしも幸福をもたらさない",
    "explanation": "伝道者は、知恵や知識が増しても、それが必ずしも人生の虚しさを解消するわけではないと述べています。",
    "sources": [
      "伝道の書 1:18"
    ],
    "tags": [
      "旧約聖書",
      "伝道の書"
    ]
  },
  {
    "question": "伝道の書で現世の『快楽』の追求は最終的にどう描かれているか？",
    "choices": [
      "永続する喜びを与える",
      "精神的成長へと導く",
      "虚しさだけを残す",
      "神の恵みと直結する"
    ],
    "answer": "虚しさだけを残す",
    "explanation": "伝道書では、一時的な快楽でも、最終的には心の虚無に帰するものと説かれています。",
    "sources": [
      "伝道の書 2:1-11"
    ],
    "tags": [
      "旧約聖書",
      "伝道の書"
    ]
  },
  {
    "question": "伝道の書3章で『すべての事に時がある』というテーマはどの節に見られますか？",
    "choices": [
      "1章",
      "2章",
      "3章",
      "4章"
    ],
    "answer": "3章",
    "explanation": "3章では、誕生、死、笑い、泣きといったあらゆる出来事に定められた時が存在することが述べられています。",
    "sources": [
      "伝道の書 3:1"
    ],
    "tags": [
      "旧約聖書",
      "伝道の書"
    ]
  },
  {
    "question": "伝道の書は人間の努力についてどのような見解を示していますか？",
    "choices": [
      "努力すれば必ず成功する",
      "どんな努力も最終的には虚しい",
      "働くことは神の啓示である",
      "努力は人間を神に近づける"
    ],
    "answer": "どんな努力も最終的には虚しい",
    "explanation": "伝道の書は、いかに努力し働いても、その結末は虚しさに満ちていると説いています。",
    "sources": [
      "伝道の書 2:11"
    ],
    "tags": [
      "旧約聖書",
      "伝道の書"
    ]
  },
  {
    "question": "伝道の書で『死』の不可避性はどのように表現されていますか？",
    "choices": [
      "死は神の審判として訪れる",
      "死は避けられない自然の摂理である",
      "死は恐れるべき災厄である",
      "死は人の罪の代償である"
    ],
    "answer": "死は避けられない自然の摂理である",
    "explanation": "伝道者は、死がすべての人に共通の避けがたい運命であると強調しています。",
    "sources": [
      "伝道の書 3:19-20"
    ],
    "tags": [
      "旧約聖書",
      "伝道の書"
    ]
  },
  {
    "question": "伝道の書はどのようにして人生の無常さを読者に伝えていますか？",
    "choices": [
      "神秘的な儀式の描写を通して",
      "詩的な表現と繰り返しの中で",
      "歴史的事実の羅列により",
      "哲学的対話の形式を用いて"
    ],
    "answer": "詩的な表現と繰り返しの中で",
    "explanation": "伝道者は、詩的かつ反復する表現を通じて、人生のはかなさや無常を強調しています。",
    "sources": [
      "伝道の書 1:2",
      "伝道の書 3:11"
    ],
    "tags": [
      "旧約聖書",
      "伝道の書"
    ]
  },
  {
    "question": "伝道の書における『労苦』は次のどれとして評価されていますか？",
    "choices": [
      "神の祝福を受ける行為",
      "最終的な虚しさを伴うもの",
      "人間の崇高な使命",
      "永続する報いをもたらす"
    ],
    "answer": "最終的な虚しさを伴うもの",
    "explanation": "伝道書では、人間がどれほど働いても、その労苦が最終的には虚しい結果に終わると説かれています。",
    "sources": [
      "伝道の書 2:11"
    ],
    "tags": [
      "旧約聖書",
      "伝道の書"
    ]
  },
  {
    "question": "伝道の書で『知恵』と『愚かさ』の対比は何を示していますか？",
    "choices": [
      "知恵があれば全て変わる",
      "どちらも必ずしも救いにつながらない",
      "愚かさこそが真の自由",
      "知恵は失敗を回避する万能薬"
    ],
    "answer": "どちらも必ずしも救いにつながらない",
    "explanation": "伝道者は、知恵を追求しても必ずしも幸せや救いが得られるわけではないと述べています。",
    "sources": [
      "伝道の書 7:16-18"
    ],
    "tags": [
      "旧約聖書",
      "伝道の書"
    ]
  },
  {
    "question": "伝道の書における『過去と未来の比較』はどのような意味を持ちますか？",
    "choices": [
      "過去は輝かしく未来は暗い",
      "未来には希望があり、過去は迷いである",
      "過去も未来も変わらず虚しさを含む",
      "未来は完全に新たな創造である"
    ],
    "answer": "過去も未来も変わらず虚しさを含む",
    "explanation": "伝道者は、時が流れても本質は変わらず、どちらも虚しさを帯びると述べています。",
    "sources": [
      "伝道の書 1:4"
    ],
    "tags": [
      "旧約聖書",
      "伝道の書"
    ]
  },
  {
    "question": "伝道の書が語る『運命』の概念にはどのような特徴が見られますか？",
    "choices": [
      "偶然と必然が混在している",
      "全てが人間の意思で決まる",
      "科学的な法則に基づく",
      "予測不可能で完全にランダム"
    ],
    "answer": "偶然と必然が混在している",
    "explanation": "伝道書は、人生の運命や出来事が必然性と偶然性の両面を持つと示しています。",
    "sources": [
      "伝道の書 3:1-8"
    ],
    "tags": [
      "旧約聖書",
      "伝道の書"
    ]
  },
  {
    "question": "伝道の書は生と死の関係についてどのように強調していますか？",
    "choices": [
      "生は死という宿命の前触れである",
      "いかなる生も死の影を免れない",
      "生きることは死を超越する",
      "死は永遠の救済への入り口である"
    ],
    "answer": "いかなる生も死の影を免れない",
    "explanation": "伝道者は、どんなに生き生きとしても最終的には死を迎えるという現実を強く訴えています。",
    "sources": [
      "伝道の書 2:13"
    ],
    "tags": [
      "旧約聖書",
      "伝道の書"
    ]
  },
  {
    "question": "伝道の書で伝道者が労苦を振り返る際の心境はどのように表現されていますか？",
    "choices": [
      "満足と誇りに満ちている",
      "虚無感と絶望に包まれている",
      "未来への希望を抱いている",
      "神の恵みに感謝している"
    ],
    "answer": "虚無感と絶望に包まれている",
    "explanation": "伝道者は、あらゆる労働や追求が結局は空しいものであったと嘆いています。",
    "sources": [
      "伝道の書 2:11"
    ],
    "tags": [
      "旧約聖書",
      "伝道の書"
    ]
  },
  {
    "question": "『日光の下での生き方』という表現は、何を象徴していますか？",
    "choices": [
      "霊的な悟り",
      "神の臨在",
      "人間の現実生活",
      "未来への光明"
    ],
    "answer": "人間の現実生活",
    "explanation": "この表現は、積極的に日常の現実世界で生きることを意味しており、他の超自然的な領域とは対照されます。",
    "sources": [
      "伝道の書 1:3"
    ],
    "tags": [
      "旧約聖書",
      "伝道の書"
    ]
  },
  {
    "question": "伝道の書で『快楽』の追求は最終的にどんな結果をもたらすと語られているか？",
    "choices": [
      "永続する幸福",
      "精神的成長",
      "虚しさ",
      "深い満足感"
    ],
    "answer": "虚しさ",
    "explanation": "書中では、たとえ多くの快楽を追い求めても、結局は心の虚無を埋めることはできないと説かれています。",
    "sources": [
      "伝道の書 2:1-11"
    ],
    "tags": [
      "旧約聖書",
      "伝道の書"
    ]
  },
  {
    "question": "伝道の書において、『死』はどのように位置づけられていますか？",
    "choices": [
      "命の最終章であり、必然の結末",
      "神への試練である",
      "取り返しのつかない罪の結果",
      "新たな始まりとしての再生"
    ],
    "answer": "命の最終章であり、必然の結末",
    "explanation": "伝道者は、死がすべての存在にとって避けることのできない必然の運命であると伝えています。",
    "sources": [
      "伝道の書 3:19-20"
    ],
    "tags": [
      "旧約聖書",
      "伝道の書"
    ]
  },
  {
    "question": "伝道の書において『人の心』はどのように描かれていますか？",
    "choices": [
      "シンプルで無垢である",
      "理解しがたい謎に満ちている",
      "常に神への信仰を持つ",
      "完全に理知的である"
    ],
    "answer": "理解しがたい謎に満ちている",
    "explanation": "伝道者は、人の心が複雑で、その本質を完全には理解できない神秘的な領域と捉えています。",
    "sources": [
      "伝道の書 11:5"
    ],
    "tags": [
      "旧約聖書",
      "伝道の書"
    ]
  },
  {
    "question": "伝道の書で『記憶』はどのような意味を持っていると説かれていますか？",
    "choices": [
      "知恵の源であり、未来への鍵",
      "過去の虚しさを思い出させるもの",
      "神の啓示を記すもの",
      "人間の誇りと結びつくもの"
    ],
    "answer": "過去の虚しさを思い出させるもの",
    "explanation": "伝道書では、記憶が過ぎ去った日々の虚しさや無常感を呼び起こすと解釈されます。",
    "sources": [
      "伝道の書 1:11"
    ],
    "tags": [
      "旧約聖書",
      "伝道の書"
    ]
  },
  {
    "question": "伝道の書における『働くこと』の意義はどのように示されていますか？",
    "choices": [
      "人間の存在を確かなものにする",
      "神への献身の証とする",
      "結局は虚しい結果に終わる",
      "永遠の報いを約束する"
    ],
    "answer": "結局は虚しい結果に終わる",
    "explanation": "書の中で、たとえどんなに働いてもその結末は虚無に帰するという現実が強調されています。",
    "sources": [
      "伝道の書 2:11"
    ],
    "tags": [
      "旧約聖書",
      "伝道の書"
    ]
  },
  {
    "question": "伝道の書で『運命の流れ』はどの感情をも象徴しているか？",
    "choices": [
      "絶え間ない喜び",
      "悲しみと喜びの混在",
      "無条件の平和",
      "純粋な絶望"
    ],
    "answer": "悲しみと喜びの混在",
    "explanation": "書は、人生の運命が悲しみと喜びという対照的な感情とともに流れることを示唆しています。",
    "sources": [
      "伝道の書 3:4"
    ],
    "tags": [
      "旧約聖書",
      "伝道の書"
    ]
  },
  {
    "question": "伝道の書の視点から最も賢明な生き方とされるのは次のうちどれですか？",
    "choices": [
      "過度な快楽追求",
      "慎重に今を楽しむこと",
      "無為に生きること",
      "未来ばかりに心を奪われること"
    ],
    "answer": "慎重に今を楽しむこと",
    "explanation": "伝道者は、すべての努力が虚しさにつながるとしつつも、今この瞬間を大切にすることの意義を説いています。",
    "sources": [
      "伝道の書 3:12-13"
    ],
    "tags": [
      "旧約聖書",
      "伝道の書"
    ]
  },
  {
    "question": "『ほかならぬ日々』という表現は伝道の書で何を意味していますか？",
    "choices": [
      "運命の奇跡",
      "繰り返される平凡な日常",
      "劇的な人生の転機",
      "神の啓示の瞬間"
    ],
    "answer": "繰り返される平凡な日常",
    "explanation": "この表現は、日々が予測可能で反復する、変わらぬ平凡な現実を示しています。",
    "sources": [
      "伝道の書 1:4"
    ],
    "tags": [
      "旧約聖書",
      "伝道の書"
    ]
  },
  {
    "question": "伝道の書でなぜ『虚しい』という言葉が何度も繰り返されるのでしょうか？",
    "choices": [
      "人生の不条理を強調するため",
      "神秘的な儀式を説明するため",
      "神の愛の深さを表現するため",
      "歴史的事実を記録するため"
    ],
    "answer": "人生の不条理を強調するため",
    "explanation": "繰り返される『虚しい』という言葉は、人生の根本的な不条理や無常を読者に印象付けるために用いられています。",
    "sources": [
      "伝道の書 1:2"
    ],
    "tags": [
      "旧約聖書",
      "伝道の書"
    ]
  },
  {
    "question": "伝道の書の文脈で、楽観主義の代わりに強調される感情は何でしょう？",
    "choices": [
      "虚無",
      "希望",
      "情熱",
      "信仰"
    ],
    "answer": "虚無",
    "explanation": "伝道者は、現実の絶え間ない虚しさを通して、楽観だけでは解決できない虚無感を強調しています。",
    "sources": [
      "伝道の書 2:11"
    ],
    "tags": [
      "旧約聖書",
      "伝道の書"
    ]
  },
  {
    "question": "伝道の書によれば、知恵と愚かさの間で何が最も大切だと示唆されていますか？",
    "choices": [
      "完全な知識",
      "極端な無知",
      "適度なバランス",
      "愚かさの放縦"
    ],
    "answer": "適度なバランス",
    "explanation": "知恵があまりにも過剰になると悩みが増すため、知恵と愚かさの間には適度なバランスが求められると説かれています。",
    "sources": [
      "伝道の書 7:16-18"
    ],
    "tags": [
      "旧約聖書",
      "伝道の書"
    ]
  },
  {
    "question": "『過ぎ去る日々』は伝道の書で何を象徴していますか？",
    "choices": [
      "未来への明るい希望",
      "過ぎ去った時間の不可逆性",
      "永遠に続く記憶",
      "神の介入の奇跡"
    ],
    "answer": "過ぎ去った時間の不可逆性",
    "explanation": "一度過ぎた日々は二度と戻らず、その儚さと不可逆性が強調されています。",
    "sources": [
      "伝道の書 1:4"
    ],
    "tags": [
      "旧約聖書",
      "伝道の書"
    ]
  },
  {
    "question": "伝道の書の結論部分で示される最終的な人間への助言は何ですか？",
    "choices": [
      "知恵を究めよ",
      "富を追い求めよ",
      "神を恐れてその戒めを守れ",
      "快楽に生きよ"
    ],
    "answer": "神を恐れてその戒めを守れ",
    "explanation": "伝道書の結びでは、すべての人は神を畏れるべきであるという普遍的な教訓が示されています。",
    "sources": [
      "伝道の書 12:13"
    ],
    "tags": [
      "旧約聖書",
      "伝道の書"
    ]
  },
  {
    "question": "伝道の書において、過去と未来の対比はどのように配置されていますか？",
    "choices": [
      "未来は希望に満ち、過去は苦悩に満ちる",
      "過去と未来のどちらも虚しさを共有する",
      "過去は輝かしく、未来は闇である",
      "未来は約束され、過去は否定される"
    ],
    "answer": "過去と未来のどちらも虚しさを共有する",
    "explanation": "伝道者は、時代が変わっても本質的な虚しさは変わらないと説いています。",
    "sources": [
      "伝道の書 1:9",
      "伝道の書 12:13"
    ],
    "tags": [
      "旧約聖書",
      "伝道の書"
    ]
  },
  {
    "question": "伝道の書で『智慧の重み』はどのように解釈されますか？",
    "choices": [
      "すべての問題を解決する",
      "幸福を保証する",
      "むしろ悩みを増す",
      "無視してよいもの"
    ],
    "answer": "むしろ悩みを増す",
    "explanation": "知恵を得ることは、一方では多くの悩みや苦しみを伴う代償でもあると語られています。",
    "sources": [
      "伝道の書 1:18"
    ],
    "tags": [
      "旧約聖書",
      "伝道の書"
    ]
  },
  {
    "question": "伝道の書が強調する現実の残酷さは主にどの要素に表れていますか？",
    "choices": [
      "人間関係の儚さ",
      "労働の報われなさ",
      "自然災害の猛威",
      "政治の不正"
    ],
    "answer": "労働の報われなさ",
    "explanation": "どれほど努力してもその結果が虚しく報われない現実が、書全体を通して強調されています。",
    "sources": [
      "伝道の書 2:11"
    ],
    "tags": [
      "旧約聖書",
      "伝道の書"
    ]
  },
  {
    "question": "伝道の書における『享楽』の位置づけはどれですか？",
    "choices": [
      "永遠の幸福を保証する",
      "一時の慰めに過ぎない",
      "罪深い行いである",
      "神の祝福の表れである"
    ],
    "answer": "一時の慰めに過ぎない",
    "explanation": "書では、享楽はあくまで一時的な慰めであり、永続する満足や救いには結びつかないと説かれています。",
    "sources": [
      "伝道の書 2:1-11"
    ],
    "tags": [
      "旧約聖書",
      "伝道の書"
    ]
  },
  {
    "question": "伝道の書では、どんな努力も最終的にどのような結果につながると述べられているか？",
    "choices": [
      "大いなる成功",
      "予期せぬ報酬",
      "空虚な終わり",
      "永遠の栄光"
    ],
    "answer": "空虚な終わり",
    "explanation": "伝道者は、いかなる努力も結局は虚しく、全てが無に帰すると結論付けています。",
    "sources": [
      "伝道の書 2:11"
    ],
    "tags": [
      "旧約聖書",
      "伝道の書"
    ]
  },
  {
    "question": "伝道の書の語り口調はどのような雰囲気を持っていると言えるか？",
    "choices": [
      "熱狂的で情熱的",
      "幻想的で夢幻的",
      "冷徹かつ現実的",
      "感傷的で哀愁に満ちた"
    ],
    "answer": "冷徹かつ現実的",
    "explanation": "伝道者は、感情に流されることなく、人間の営みの厳しい現実と虚無を淡々と語っています。",
    "sources": [
      "伝道の書 全体"
    ],
    "tags": [
      "旧約聖書",
      "伝道の書"
    ]
  },
  {
    "question": "伝道の書における『人生』の全体的な評価はどれですか？",
    "choices": [
      "価値ある冒険である",
      "無意味な儚さに満ちている",
      "永続する喜びを約束する",
      "絶え間ない進歩の道である"
    ],
    "answer": "無意味な儚さに満ちている",
    "explanation": "伝道者は、人生そのものが一過性であり、究極的には虚しさだけが残ると評価しています。",
    "sources": [
      "伝道の書 1:2",
      "伝道の書 12:13"
    ],
    "tags": [
      "旧約聖書",
      "伝道の書"
    ]
  },
  {
    "question": "伝道の書における『不変の真理』とは何と表現されているか？",
    "choices": [
      "神の変わらぬ愛",
      "すべては変わらず虚しい",
      "運命の絶対性",
      "人間の情熱の永続"
    ],
    "answer": "すべては変わらず虚しい",
    "explanation": "どんなに時が流れても、人間の営みの根底には常に虚しさが存在するという不変の真理が示されています。",
    "sources": [
      "伝道の書 1:2"
    ],
    "tags": [
      "旧約聖書",
      "伝道の書"
    ]
  },
  {
    "question": "伝道の書は、成功の追求に対して伝道者がどのような警告を発しているか？",
    "choices": [
      "成功は孤独を生む",
      "成功は虚しさにつながる",
      "成功は神の怒りを買う",
      "成功は永続する名誉をもたらす"
    ],
    "answer": "成功は虚しさにつながる",
    "explanation": "書中では、どれほどの成功を収めてもそれが本当の満足へは結びつかず、結局は虚無に帰すると警告しています。",
    "sources": [
      "伝道の書 2:11"
    ],
    "tags": [
      "旧約聖書",
      "伝道の書"
    ]
  },
  {
    "question": "伝道の書に登場する『労働』のイメージはどのように表現されているか？",
    "choices": [
      "創造的な表現である",
      "空回りするエネルギーである",
      "神聖な使命である",
      "理想的な生活の証である"
    ],
    "answer": "空回りするエネルギーである",
    "explanation": "労働がいかに精一杯でも、最終的には無益な努力として終わるという虚しさを伝道者は強調しています。",
    "sources": [
      "伝道の書 2:11"
    ],
    "tags": [
      "旧約聖書",
      "伝道の書"
    ]
  },
  {
    "question": "伝道の書のメッセージを総括すると、最も象徴する言葉は何でしょうか？",
    "choices": [
      "永遠",
      "虚無",
      "栄光",
      "平和"
    ],
    "answer": "虚無",
    "explanation": "書全体を通じて、あらゆる努力や人間の営みは最終的に虚しく、すべては虚無に帰するというメッセージが伝えられています。",
    "sources": [
      "伝道の書 1:2"
    ],
    "tags": [
      "旧約聖書",
      "伝道の書"
    ]
  }
]