[
  {
    "question": "【エゼキエル書1章-1】エゼキエル書1章に登場する、四つの顔を持つ生き物は神の何を象徴していると考えられていますか？",
    "choices": ["全能性と知恵", "国の繁栄", "罪の深さ", "裁きの日"],
    "answer": "全能性と知恵",
    "explanation": "この質問はエゼキエル書1章の幻の中で、生き物の四つの顔が神の全能性と知恵を象徴していると解釈される点に着目しています。参考：新解約2017版 エゼキエル書1章",
    "sources": [
      "エゼキエル書 1:4-28"
    ],
    "tags": ["旧約聖書 / エゼキエル書"]
  },
  {
    "question": "【エゼキエル書1章-2】エゼキエル書1章において、神の栄光がどのような視覚的要素で表現されていますか？",
    "choices": ["四つの顔、翼、動く輪", "大河、月、星", "山、谷、川", "木々、果実、花"],
    "answer": "四つの顔、翼、動く輪",
    "explanation": "エゼキエル書1章の幻には、四つの顔や動く輪といった視覚的要素が含まれており、神の栄光を象徴しています。参考：新解約2017版 エゼキエル書1章",
    "sources": [
      "エゼキエル書 1:4-28"
    ],
    "tags": ["旧約聖書 / エゼキエル書"]
  },
  {
    "question": "【エゼキエル書1章-3】エゼキエル書1章の幻に見られる輝く光は、何を示しているとされているか？",
    "choices": ["神の栄光", "民の罪", "終末の日", "預言者の夢"],
    "answer": "神の栄光",
    "explanation": "輝く光は神の栄光そのものを象徴するとされ、エゼキエルに神の偉大さが啓示されたことを示しています。参考：新解約2017版 エゼキエル書1章",
    "sources": [
      "エゼキエル書 1:4-28"
    ],
    "tags": ["旧約聖書 / エゼキエル書"]
  },
  {
    "question": "【エゼキエル書1章-4】エゼキエル書1章では、霊的な現実がどのように表現されていますか？",
    "choices": ["異なる顔と動く輪による幻", "黄金の像", "静かな泉", "武装した戦士たち"],
    "answer": "異なる顔と動く輪による幻",
    "explanation": "幻の中の異なる顔と動く輪は、神の多面的な性格と動的な権威を象徴していると解釈されます。参考：新解約2017版 エゼキエル書1章",
    "sources": [
      "エゼキエル書 1:4-28"
    ],
    "tags": ["旧約聖書 / エゼキエル書"]
  },
  {
    "question": "【エゼキエル書1章-5】エゼキエル書1章に登場する動く輪は何を象徴していますか？",
    "choices": ["神の絶え間ない存在と導き", "戦争の乗り物", "王国の繁栄", "自然の法則"],
    "answer": "神の絶え間ない存在と導き",
    "explanation": "動く輪は、神が常に動いておられること、そしてその導きが変わらないことを象徴しています。参考：新解約2017版 エゼキエル書1章",
    "sources": [
      "エゼキエル書 1:4-28"
    ],
    "tags": ["旧約聖書 / エゼキエル書"]
  },
  {
    "question": "【エゼキエル書1章-6】エゼキエル書1章に現れる生き物たちは何を象徴していると解釈されるか？",
    "choices": ["神の全能性と統治", "預言者自身の内面", "イスラエルの民", "未来の軍勢"],
    "answer": "神の全能性と統治",
    "explanation": "生き物たちは神の全能性、統治権を表し、神の御声とお告げが伝えられる背景を成しています。参考：新解約2017版 エゼキエル書1章",
    "sources": [
      "エゼキエル書 1:4-28"
    ],
    "tags": ["旧約聖書 / エゼキエル書"]
  },
  {
    "question": "【エゼキエル書1章-7】エゼキエル書1章の幻に含まれる要素として正しいものはどれか？",
    "choices": ["四つの顔、翼、動く輪", "大河、月、星", "山々、谷、川", "木々、果実、花"],
    "answer": "四つの顔、翼、動く輪",
    "explanation": "幻の中には、神の栄光を象徴する複数の視覚要素が散りばめられており、その中核として四つの顔、翼、そして輪が描かれています。参考：新解約2017版 エゼキエル書1章",
    "sources": [
      "エゼキエル書 1:4-28"
    ],
    "tags": ["旧約聖書 / エゼキエル書"]
  },
  {
    "question": "【エゼキエル書1章-8】エゼキエル書1章の幻によってエゼキエルに何が啓示されたとされているか？",
    "choices": ["神の栄光とその計画", "イスラエルの歴史", "終末の予言", "異邦への警告"],
    "answer": "神の栄光とその計画",
    "explanation": "幻は、エゼキエルに神の栄光および、神が計画される出来事の一端を啓示するものとされています。参考：新解約2017版 エゼキエル書1章",
    "sources": [
      "エゼキエル書 1:4-28"
    ],
    "tags": ["旧約聖書 / エゼキエル書"]
  },
  {
    "question": "【エゼキエル書2章-1】エゼキエル書2章で神がエゼキエルに与えた象徴的な媒体は何ですか？",
    "choices": ["巻物", "剣", "指輪", "杯"],
    "answer": "巻物",
    "explanation": "神はエゼキエルに巻物を与え、それを通して神の啓示とメッセージを伝える使命を帯びさせました。参考：新解約2017版 エゼキエル書2章",
    "sources": [
      "エゼキエル書 2章"
    ],
    "tags": ["旧約聖書 / エゼキエル書"]
  },
  {
    "question": "【エゼキエル書2章-2】エゼキエル書2章における彼の使命は、主に何に向けられているか？",
    "choices": ["イスラエルの民への警告", "敵国との交渉", "農耕の指示", "祭司の儀式"],
    "answer": "イスラエルの民への警告",
    "explanation": "エゼキエルは、イスラエルの民に向けて、背信と罪の道から転ぶことへの警告を伝える使命を授かりました。参考：新解約2017版 エゼキエル書2章",
    "sources": [
      "エゼキエル書 2章"
    ],
    "tags": ["旧約聖書 / エゼキエル書"]
  },
  {
    "question": "【エゼキエル書2章-3】エゼキエル書2章において、神はエゼキエルにどのように言葉を伝えるよう命じたか？",
    "choices": ["口によって宣言", "筆記して記録", "音楽を奏で", "祭壇で奉仕"],
    "answer": "口によって宣言",
    "explanation": "エゼキエルは、神の言葉を口に出して伝えることにより、その啓示を民に広めるよう召命されました。参考：新解約2017版 エゼキエル書2章",
    "sources": [
      "エゼキエル書 2章"
    ],
    "tags": ["旧約聖書 / エゼキエル書"]
  },
  {
    "question": "【エゼキエル書2章-4】エゼキエル書2章に記された巻物は、象徴的に何を意味しているか？",
    "choices": ["神の啓示と未来の計画", "物質的な富", "戦略的な秘密", "宗教儀式の規定"],
    "answer": "神の啓示と未来の計画",
    "explanation": "巻物は、神の啓示と、それに基づく未来の計画や警告を象徴する重要な媒体です。参考：新解約2017版 エゼキエル書2章",
    "sources": [
      "エゼキエル書 2章"
    ],
    "tags": ["旧約聖書 / エゼキエル書"]
  },
  {
    "question": "【エゼキエル書2章-5】エゼキエル書2章における使命は、彼にどのような姿勢を求めたか？",
    "choices": ["従順と覚悟", "富の追求", "独裁的支配", "懐疑と躊躇"],
    "answer": "従順と覚悟",
    "explanation": "神はエゼキエルに、恐れることなく従順にその使命を果たすよう求めています。参考：新解約2017版 エゼキエル書2章",
    "sources": [
      "エゼキエル書 2章"
    ],
    "tags": ["旧約聖書 / エゼキエル書"]
  },
  {
    "question": "【エゼキエル書2章-6】エゼキエル書2章の巻物は、どのような味わいを象徴的に表現されていたか？",
    "choices": ["苦い味", "甘い香り", "塩味", "酸っぱい感覚"],
    "answer": "苦い味",
    "explanation": "巻物は、神の言葉が時に苦いものであることを示すため、苦い味として象徴的に表現されています。参考：新解約2017版 エゼキエル書2章",
    "sources": [
      "エゼキエル書 2章"
    ],
    "tags": ["旧約聖書 / エゼキエル書"]
  },
  {
    "question": "【エゼキエル書2章-7】エゼキエル書2章で神がエゼキエルに与えたメッセージの媒体は何か？",
    "choices": ["巻物", "石板", "黄金の杯", "鉄の鍵"],
    "answer": "巻物",
    "explanation": "神は、啓示の媒体として再び巻物を用い、エゼキエルにその言葉を伝えるよう命じました。参考：新解約2017版 エゼキエル書2章",
    "sources": [
      "エゼキエル書 2章"
    ],
    "tags": ["旧約聖書 / エゼキエル書"]
  },
  {
    "question": "【エゼキエル書2章-8】エゼキエル書2章において、エゼキエルの使命は主にどこに向けられていたか？",
    "choices": ["反逆するイスラエルの民", "異邦との同盟", "祭司たちへの指示", "神殿の建設"],
    "answer": "反逆するイスラエルの民",
    "explanation": "エゼキエルは、反逆と背信に陥ったイスラエルの民に対して、神の警告のメッセージを伝える使命を担っています。参考：新解約2017版 エゼキエル書2章",
    "sources": [
      "エゼキエル書 2章"
    ],
    "tags": ["旧約聖書 / エゼキエル書"]
  },
  {
    "question": "【エゼキエル書3章-1】エゼキエル書3章でエゼキエルは、どの役割を与えられたとされているか？",
    "choices": ["見張り人", "軍の指揮官", "祭司", "裁判官"],
    "answer": "見張り人",
    "explanation": "エゼキエルは、イスラエルの民に対して神の警告を伝える見張り人としての役割を負うよう命じられました。参考：新解約2017版 エゼキエル書3章",
    "sources": [
      "エゼキエル書 3章"
    ],
    "tags": ["旧約聖書 / エゼキエル書"]
  },
  {
    "question": "【エゼキエル書3章-2】エゼキエル書3章において、彼の使命の目的は何か？",
    "choices": ["民の罪を警告すること", "戦争を指揮すること", "宝を守ること", "預言を否定すること"],
    "answer": "民の罪を警告すること",
    "explanation": "エゼキエルは、イスラエルの民に対して神の裁きが迫っていることを警告する使命を授かりました。参考：新解約2017版 エゼキエル書3章",
    "sources": [
      "エゼキエル書 3章"
    ],
    "tags": ["旧約聖書 / エゼキエル書"]
  },
  {
    "question": "【エゼキエル書3章-3】エゼキエル書3章で彼に課せられた責務は主に何か？",
    "choices": ["民の霊的な見張り", "経済の監督", "軍事行動の計画", "祭典の運営"],
    "answer": "民の霊的な見張り",
    "explanation": "エゼキエルは、民が陥る霊的な堕落に対して警鐘を鳴らす見張り人として召命されています。参考：新解約2017版 エゼキエル書3章",
    "sources": [
      "エゼキエル書 3章"
    ],
    "tags": ["旧約聖書 / エゼキエル書"]
  },
  {
    "question": "【エゼキエル書3章-4】エゼキエル書3章に基づき、彼は象徴的に何を担うようになったか？",
    "choices": ["神の警告の使者", "国家の建築家", "戦の英雄", "農業の指導者"],
    "answer": "神の警告の使者",
    "explanation": "エゼキエルは、神からの厳しい警告を民に伝えるための使者、すなわち警告の使者としての責務を帯びています。参考：新解約2017版 エゼキエル書3章",
    "sources": [
      "エゼキエル書 3章"
    ],
    "tags": ["旧約聖書 / エゼキエル書"]
  },
  {
    "question": "【エゼキエル書3章-5】エゼキエル書3章において、彼の役割は何のために存在しているか？",
    "choices": ["イスラエルの民への警鐘", "税の徴収", "国家の統治", "預言者間の競争"],
    "answer": "イスラエルの民への警鐘",
    "explanation": "見張り人としてのエゼキエルの役割は、悪しき行いに対する警鐘として民を戒めるためのものです。参考：新解約2017版 エゼキエル書3章",
    "sources": [
      "エゼキエル書 3章"
    ],
    "tags": ["旧約聖書 / エゼキエル書"]
  },
  {
    "question": "【エゼキエル書3章-6】エゼキエル書3章で、彼に課せられた責務は主に何に関するものか？",
    "choices": ["罪の告発と警告", "富の蓄積", "権力の維持", "国際交渉"],
    "answer": "罪の告発と警告",
    "explanation": "エゼキエルは、罪深い行いを見過ごさず、神の裁きが迫っていることを告発し警告する責務を担っています。参考：新解約2017版 エゼキエル書3章",
    "sources": [
      "エゼキエル書 3章"
    ],
    "tags": ["旧約聖書 / エゼキエル書"]
  },
  {
    "question": "【エゼキエル書3章-7】エゼキエル書3章において、『見張り人』の役割は具体的に何を意味しているか？",
    "choices": ["民への神の警告を伝えること", "戦闘の指揮", "宗教儀式の管理", "祭典の主催"],
    "answer": "民への神の警告を伝えること",
    "explanation": "『見張り人』としての役割は、罪に陥った民に対し神の警告を逃さず伝えることを意味します。参考：新解約2017版 エゼキエル書3章",
    "sources": [
      "エゼキエル書 3章"
    ],
    "tags": ["旧約聖書 / エゼキエル書"]
  },
  {
    "question": "【エゼキエル書3章-8】エゼキエル書3章では、彼の説教的使命は何として表現されているか？",
    "choices": ["神の言葉の伝達者", "政治の改革者", "建築の設計者", "農業の助言者"],
    "answer": "神の言葉の伝達者",
    "explanation": "エゼキエルは、神の言葉そのものを民に伝える伝達者としての使命が強調されています。参考：新解約2017版 エゼキエル書3章",
    "sources": [
      "エゼキエル書 3章"
    ],
    "tags": ["旧約聖書 / エゼキエル書"]
  },
  {
    "question": "【エゼキエル書4章-1】エゼキエル書4章で預言者が行った象徴的行為は、何の象徴とされているか？",
    "choices": ["エルサレム包囲の象徴", "国の繁栄", "異邦国との同盟", "潤いの象徴"],
    "answer": "エルサレム包囲の象徴",
    "explanation": "4章でエゼキエルが取った行為は、エルサレムへの包囲戦の現実と、それに伴う絶望を象徴しています。参考：新解約2017版 エゼキエル書4章",
    "sources": [
      "エゼキエル書 4章"
    ],
    "tags": ["旧約聖書 / エゼキエル書"]
  },
  {
    "question": "【エゼキエル書4章-2】エゼキエル書4章で預言者が用いた模型は、何を表現しているか？",
    "choices": ["包囲戦の様相", "平和の宴", "豊作の祈り", "祭りの饗宴"],
    "answer": "包囲戦の様相",
    "explanation": "預言者が用いた模型は、エルサレムが包囲される様子を象徴的に示し、民に迫る破滅を表しています。参考：新解約2017版 エゼキエル書4章",
    "sources": [
      "エゼキエル書 4章"
    ],
    "tags": ["旧約聖書 / エゼキエル書"]
  },
  {
    "question": "【エゼキエル書4章-3】エゼキエル書4章の象徴行為は、どの都市の運命を暗示しているか？",
    "choices": ["堕落したエルサレム", "新しい国の誕生", "隣国との和解", "楽園への旅"],
    "answer": "堕落したエルサレム",
    "explanation": "この行為は、エルサレムの堕落と絶望的な未来を直接示唆するために用いられています。参考：新解約2017版 エゼキエル書4章",
    "sources": [
      "エゼキエル書 4章"
    ],
    "tags": ["旧約聖書 / エゼキエル書"]
  },
  {
    "question": "【エゼキエル書4章-4】エゼキエル書4章の預言行為により、彼は象徴的に何を示そうとしたか？",
    "choices": ["厳しい裁きと封鎖", "救済と再生", "豊穣と繁栄", "祝福と拡大"],
    "answer": "厳しい裁きと封鎖",
    "explanation": "預言行為は、エルサレムに対する神の厳しい裁きと、その結果による封鎖状態を象徴しています。参考：新解約2017版 エゼキエル書4章",
    "sources": [
      "エゼキエル書 4章"
    ],
    "tags": ["旧約聖書 / エゼキエル書"]
  },
  {
    "question": "【エゼキエル書4章-5】エゼキエル書4章における象徴行為は、何を体現していると言えるか？",
    "choices": ["エルサレムの包囲と絶望", "新たな契約の成立", "異邦国へのいたずら", "祝祭の始まり"],
    "answer": "エルサレムの包囲と絶望",
    "explanation": "この象徴的な行為は、エルサレムが包囲され、その結果絶望的な事態が訪れることを示しています。参考：新解約2017版 エゼキエル書4章",
    "sources": [
      "エゼキエル書 4章"
    ],
    "tags": ["旧約聖書 / エゼキエル書"]
  },
  {
    "question": "【エゼキエル書4章-6】エゼキエル書4章の行為は、どのような歴史的現象を象徴しているか？",
    "choices": ["エルサレムの包囲状態", "国際的な交易", "宗教改革", "王権の確立"],
    "answer": "エルサレムの包囲状態",
    "explanation": "この預言行為は、エルサレムが包囲されて孤立し、破滅へ向かう歴史的現象を象徴しています。参考：新解約2017版 エゼキエル書4章",
    "sources": [
      "エゼキエル書 4章"
    ],
    "tags": ["旧約聖書 / エゼキエル書"]
  },
  {
    "question": "【エゼキエル書4章-7】エゼキエル書4章に記された預言者の行動は、何に対する警告とされているか？",
    "choices": ["迫り来る裁きと破壊", "未来の繁栄", "祭司の栄誉", "季節の変動"],
    "answer": "迫り来る裁きと破壊",
    "explanation": "行動は、民に迫る神の裁きと、エルサレムの破壊の兆しを強く警告しています。参考：新解約2017版 エゼキエル書4章",
    "sources": [
      "エゼキエル書 4章"
    ],
    "tags": ["旧約聖書 / エゼキエル書"]
  },
  {
    "question": "【エゼキエル書4章-8】エゼキエル書4章の象徴行為は、最終的に何を反映しているとされるか？",
    "choices": ["エルサレムへの神の裁き", "新しい祝祭の開始", "異邦への伝道", "平和な統治"],
    "answer": "エルサレムへの神の裁き",
    "explanation": "この象徴行為は、最終的にエルサレムに対する神の裁きの到来を予告しています。参考：新解約2017版 エゼキエル書4章",
    "sources": [
      "エゼキエル書 4章"
    ],
    "tags": ["旧約聖書 / エゼキエル書"]
  },
  {
    "question": "【エゼキエル書5章-1】エゼキエル書5章において、剃髪の行為は何を象徴しているとされるか？",
    "choices": ["イスラエルの滅亡と散在", "国家の繁栄", "異邦人への包容", "宗教的純化"],
    "answer": "イスラエルの滅亡と散在",
    "explanation": "剃髪の行為は、エルサレムの民が散らばり、滅びることを象徴する厳しい警告として理解されます。参考：新解約2017版 エゼキエル書5章",
    "sources": [
      "エゼキエル書 5章"
    ],
    "tags": ["旧約聖書 / エゼキエル書"]
  },
  {
    "question": "【エゼキエル書5章-2】エゼキエル書5章で預言者が行った剃髪は、何の警告として用いられたか？",
    "choices": ["都市の裁きと分散", "新しい契約の成立", "祝福の兆し", "富の増大"],
    "answer": "都市の裁きと分散",
    "explanation": "剃髪の行為は、エルサレムが裁かれ、国民が分散することを警告する象徴的なメッセージです。参考：新解約2017版 エゼキエル書5章",
    "sources": [
      "エゼキエル書 5章"
    ],
    "tags": ["旧約聖書 / エゼキエル書"]
  },
  {
    "question": "【エゼキエル書5章-3】エゼキエル書5章において、剃髪の象徴的行為はどのような運命を示唆しているか？",
    "choices": ["破壊と逃亡", "豊作と繁栄", "団結と平和", "革新と進歩"],
    "answer": "破壊と逃亡",
    "explanation": "剃髪は、都市の破壊と国民の逃亡を象徴し、極めて悲惨な未来を予告しています。参考：新解約2017版 エゼキエル書5章",
    "sources": [
      "エゼキエル書 5章"
    ],
    "tags": ["旧約聖書 / エゼキエル書"]
  },
  {
    "question": "【エゼキエル書5章-4】エゼキエル書5章において、剃髪の行為は何に対する警告と解釈されるか？",
    "choices": ["民の散逸と滅亡", "異邦人との同盟", "農業の成功", "商業の発展"],
    "answer": "民の散逸と滅亡",
    "explanation": "この象徴行為は、エルサレムの民が散らばり、滅びるという悲惨な結果を暗示しています。参考：新解約2017版 エゼキエル書5章",
    "sources": [
      "エゼキエル書 5章"
    ],
    "tags": ["旧約聖書 / エゼキエル書"]
  },
  {
    "question": "【エゼキエル書5章-5】エゼキエル書5章での髪の処理は、一般的に何を象徴していると言われているか？",
    "choices": ["統治の終焉と分裂", "新政府の樹立", "宗教改革", "自然の再生"],
    "answer": "統治の終焉と分裂",
    "explanation": "髪の処理は、かつての統治体制が終わりを迎え、国が分裂することを象徴的に表しています。参考：新解約2017版 エゼキエル書5章",
    "sources": [
      "エゼキエル書 5章"
    ],
    "tags": ["旧約聖書 / エゼキエル書"]
  },
  {
    "question": "【エゼキエル書5章-6】エゼキエル書5章の象徴行為は、エルサレムのどの側面を表現しているか？",
    "choices": ["没落と散逸", "豊かさと繁栄", "神聖な守護", "政治的統一"],
    "answer": "没落と散逸",
    "explanation": "象徴的な剃髪や髪の処理の行為は、エルサレムの没落と民の散逸を示しています。参考：新解約2017版 エゼキエル書5章",
    "sources": [
      "エゼキエル書 5章"
    ],
    "tags": ["旧約聖書 / エゼキエル書"]
  },
  {
    "question": "【エゼキエル書5章-7】エゼキエル書5章において、剃髪は何を警告する行為とされているか？",
    "choices": ["厳しい神の裁き", "慈悲と救済", "勝利と繁栄", "聖なる祝福"],
    "answer": "厳しい神の裁き",
    "explanation": "剃髪という象徴行為は、神の裁きが確実に下ることを警告する強烈なメッセージです。参考：新解約2017版 エゼキエル書5章",
    "sources": [
      "エゼキエル書 5章"
    ],
    "tags": ["旧約聖書 / エゼキエル書"]
  },
  {
    "question": "【エゼキエル書5章-8】エゼキエル書5章の預言行為は、最終的にどのような歴史的結果を示唆しているか？",
    "choices": ["エルサレムの解体と追放", "国家の再興", "平和な統一", "宗教的復興"],
    "answer": "エルサレムの解体と追放",
    "explanation": "この行為は、エルサレムが破壊され、民が追放されるという歴史的悲劇を暗示しています。参考：新解約2017版 エゼキエル書5章",
    "sources": [
      "エゼキエル書 5章"
    ],
    "tags": ["旧約聖書 / エゼキエル書"]
  },
  {
    "question": "【エゼキエル書6章-1】エゼキエル書6章では、預言が主に何に対する警告として伝えられているか？",
    "choices": ["偶像崇拝", "農業の失敗", "異邦人への布教", "経済的腐敗"],
    "answer": "偶像崇拝",
    "explanation": "6章では、偶像崇拝が重大な罪とされ、それに対する神の裁きが宣告されています。参考：新解約2017版 エゼキエル書6章",
    "sources": [
      "エゼキエル書 6章"
    ],
    "tags": ["旧約聖書 / エゼキエル書"]
  },
  {
    "question": "【エゼキエル書6章-2】エゼキエル書6章の預言は、どの不信仰の行為に対する裁きを告げているか？",
    "choices": ["偶像の礼拝", "預言者の拒絶", "戦争の挑発", "税の増徴"],
    "answer": "偶像の礼拝",
    "explanation": "預言は、偶像の礼拝を行うことが神に対する不信仰とみなされ、そのため厳しい裁きが下される旨を述べています。参考：新解約2017版 エゼキエル書6章",
    "sources": [
      "エゼキエル書 6章"
    ],
    "tags": ["旧約聖書 / エゼキエル書"]
  },
  {
    "question": "【エゼキエル書6章-3】エゼキエル書6章で述べられている裁きは、主にどの行為に対して行われるとされるか？",
    "choices": ["偶像崇拝", "正義の追求", "家族の絆", "祭りの準備"],
    "answer": "偶像崇拝",
    "explanation": "神は、民が偶像を拝むことに対して厳しい裁きを行い、その罪深さを強調しています。参考：新解約2017版 エゼキエル書6章",
    "sources": [
      "エゼキエル書 6章"
    ],
    "tags": ["旧約聖書 / エゼキエル書"]
  },
  {
    "question": "【エゼキエル書6章-4】なぜエゼキエル書6章では、山々に対しても裁きが宣告されたのか？",
    "choices": ["偶像が置かれていたから", "山の資源独占", "神に捧げられた祭壇", "民の集会場だったから"],
    "answer": "偶像が置かれていたから",
    "explanation": "山はしばしば偶像の置かれる場所として使用され、そのため神は山々にも裁きを下すと宣言しています。参考：新解約2017版 エゼキエル書6章",
    "sources": [
      "エゼキエル書 6章"
    ],
    "tags": ["旧約聖書 / エゼキエル書"]
  },
  {
    "question": "【エゼキエル書6章-5】エゼキエル書6章において、山々への裁きは何の象徴とされているか？",
    "choices": ["偶像崇拝の中心地", "神聖な避難所", "豊かな実り", "霊的再生の場"],
    "answer": "偶像崇拝の中心地",
    "explanation": "山々はかつて偶像崇拝の中心地として崇められたため、その場所にも神の裁きが及ぶとされています。参考：新解約2017版 エゼキエル書6章",
    "sources": [
      "エゼキエル書 6章"
    ],
    "tags": ["旧約聖書 / エゼキエル書"]
  },
  {
    "question": "【エゼキエル書6章-6】エゼキエル書6章の預言の主な対象は何か？",
    "choices": ["イスラエルの偶像礼拝", "隣国の王", "財宝の隠匿", "祭司の逸脱"],
    "answer": "イスラエルの偶像礼拝",
    "explanation": "この章は、イスラエルの民が行う偶像礼拝に対して神の裁きを宣言するものです。参考：新解約2017版 エゼキエル書6章",
    "sources": [
      "エゼキエル書 6章"
    ],
    "tags": ["旧約聖書 / エゼキエル書"]
  },
  {
    "question": "【エゼキエル書6章-7】エゼキエル書6章に示された警告は、何に対する戒めを目的としているか？",
    "choices": ["偶像に対する不信仰", "戦争の準備", "楽器の使用", "伝統の保存"],
    "answer": "偶像に対する不信仰",
    "explanation": "警告は、民が偶像に依拠する信仰に対して注意を促すためのもので、その結果としての裁きを予告しています。参考：新解約2017版 エゼキエル書6章",
    "sources": [
      "エゼキエル書 6章"
    ],
    "tags": ["旧約聖書 / エゼキエル書"]
  },
  {
    "question": "【エゼキエル書6章-8】エゼキエル書6章における裁きの預言は、何の行為への懲罰を示しているか？",
    "choices": ["偶像を拝む行為", "正しい礼拝の実践", "慈善事業", "家族の儀式"],
    "answer": "偶像を拝む行為",
    "explanation": "神は、偶像に対する不忠実な礼拝行為に対して、激しい裁きと懲罰を下すと宣言しています。参考：新解約2017版 エゼキエル書6章",
    "sources": [
      "エゼキエル書 6章"
    ],
    "tags": ["旧約聖書 / エゼキエル書"]
  },
  {
    "question": "【エゼキエル書7章-1】エゼキエル書7章は主に何についての預言か？",
    "choices": ["近づく破滅と裁き", "国家の繁栄", "宗教改革", "平和な同盟"],
    "answer": "近づく破滅と裁き",
    "explanation": "7章は、神の裁きが差し迫った破滅の時をもたらすという厳しい警告として描かれています。参考：新解約2017版 エゼキエル書7章",
    "sources": [
      "エゼキエル書 7章"
    ],
    "tags": ["旧約聖書 / エゼキエル書"]
  },
  {
    "question": "【エゼキエル書7章-2】エゼキエル書7章の預言は、どの時代の終わりを告げているか？",
    "choices": ["大いなる破滅の時", "繁栄の時代", "宗教的覚醒", "平和の新時代"],
    "answer": "大いなる破滅の時",
    "explanation": "7章は、避けがたい破滅の時代が到来することを力強く告げる預言です。参考：新解約2017版 エゼキエル書7章",
    "sources": [
      "エゼキエル書 7章"
    ],
    "tags": ["旧約聖書 / エゼキエル書"]
  },
  {
    "question": "【エゼキエル書7章-3】エゼキエル書7章における裁きの宣告は、何を強調しているか？",
    "choices": ["逃れられない神の裁き", "人間の努力による救済", "祝福の連続", "新たな契約の成立"],
    "answer": "逃れられない神の裁き",
    "explanation": "この章は、どんな手段を尽くしても避けられない神の裁きが下されることを強調しています。参考：新解約2017版 エゼキエル書7章",
    "sources": [
      "エゼキエル書 7章"
    ],
    "tags": ["旧約聖書 / エゼキエル書"]
  },
  {
    "question": "【エゼキエル書7章-4】エゼキエル書7章から、エゼキエルが伝えたかったメッセージは何か？",
    "choices": ["滅びの予告と警告", "新たな希望", "経済の発展", "文化の祭典"],
    "answer": "滅びの予告と警告",
    "explanation": "預言者は、ただ単に未来の滅亡を告げるだけでなく、民に警告するための厳しいメッセージを伝えています。参考：新解約2017版 エゼキエル書7章",
    "sources": [
      "エゼキエル書 7章"
    ],
    "tags": ["旧約聖書 / エゼキエル書"]
  },
  {
    "question": "【エゼキエル書7章-5】エゼキエル書7章において、民に対する告知は何を意味しているか？",
    "choices": ["終末の裁き", "本当の救済", "富の増大", "宗教的刷新"],
    "answer": "終末の裁き",
    "explanation": "告知は、民が迎える終末の裁きを意味しており、その厳しさを警告するものです。参考：新解約2017版 エゼキエル書7章",
    "sources": [
      "エゼキエル書 7章"
    ],
    "tags": ["旧約聖書 / エゼキエル書"]
  },
  {
    "question": "【エゼキエル書7章-6】エゼキエル書7章は、どのような未来の出来事を予告しているか？",
    "choices": ["破滅と混乱", "繁栄と統一", "平和な統治", "文化の黄金時代"],
    "answer": "破滅と混乱",
    "explanation": "預言は、未来における破滅と混乱の時代がやってくることを強く示唆しています。参考：新解約2017版 エゼキエル書7章",
    "sources": [
      "エゼキエル書 7章"
    ],
    "tags": ["旧約聖書 / エゼキエル書"]
  },
  {
    "question": "【エゼキエル書7章-7】エゼキエル書7章は、信仰の放棄に対してどのような結果を示唆しているか？",
    "choices": ["惨劇的な破滅", "神の恵み", "経済的な成功", "政治的安定"],
    "answer": "惨劇的な破滅",
    "explanation": "信仰を放棄した結果、民は惨劇的な破滅に直面することが預言されています。参考：新解約2017版 エゼキエル書7章",
    "sources": [
      "エゼキエル書 7章"
    ],
    "tags": ["旧約聖書 / エゼキエル書"]
  },
  {
    "question": "【エゼキエル書7章-8】エゼキエル書7章に描かれる裁きは、どのような性質を帯びているか？",
    "choices": ["避けられない激しい審判", "穏やかな救済", "祝福の宴", "官僚的な手続き"],
    "answer": "避けられない激しい審判",
    "explanation": "この章の裁きは、激しく厳しい審判として描かれており、避けることができないとされています。参考：新解約2017版 エゼキエル書7章",
    "sources": [
      "エゼキエル書 7章"
    ],
    "tags": ["旧約聖書 / エゼキエル書"]
  },
  {
    "question": "【エゼキエル書8章-1】エゼキエル書8章でエゼキエルが目撃した不当な行為は何か？",
    "choices": ["神殿での偶像崇拝", "祭壇での供物", "民の礼拝", "神の讃美"],
    "answer": "神殿での偶像崇拝",
    "explanation": "エゼキエルは、神殿内で隠された偶像崇拝の光景を目撃し、それが重大な罪として告発されます。参考：新解約2017版 エゼキエル書8章",
    "sources": [
      "エゼキエル書 8章"
    ],
    "tags": ["旧約聖書 / エゼキエル書"]
  },
  {
    "question": "【エゼキエル書8章-2】エゼキエル書8章の幻は、どこで不正な礼拝行為が行われていることを示しているか？",
    "choices": ["エルサレムの神殿内部", "異邦の宮殿", "戦場の前線", "市場の中央"],
    "answer": "エルサレムの神殿内部",
    "explanation": "幻は、神殿内部という聖域で、偶像崇拝という不正な行為が行われていることを強調しています。参考：新解約2017版 エゼキエル書8章",
    "sources": [
      "エゼキエル書 8章"
    ],
    "tags": ["旧約聖書 / エゼキエル書"]
  },
  {
    "question": "【エゼキエル書8章-3】エゼキエル書8章の幻は、何が原因で神の怒りを招いたとされているか？",
    "choices": ["偶像への熱狂", "正当な礼拝", "宗教儀式の改善", "預言者への服従"],
    "answer": "偶像への熱狂",
    "explanation": "エゼキエルが幻の中で目撃した行為は、偶像崇拝に対する人々の熱狂が神の怒りを招いたと解釈されています。参考：新解約2017版 エゼキエル書8章",
    "sources": [
      "エゼキエル書 8章"
    ],
    "tags": ["旧約聖書 / エゼキエル書"]
  },
  {
    "question": "【エゼキエル書8章-4】エゼキエル書8章に描かれる光景は、何に対する象徴的な批判か？",
    "choices": ["堕落した宗教慣行", "政治の分裂", "経済の失敗", "自然の災害"],
    "answer": "堕落した宗教慣行",
    "explanation": "幻は、神殿内で行われる堕落した宗教慣行を象徴的に批判するためのものです。参考：新解約2017版 エゼキエル書8章",
    "sources": [
      "エゼキエル書 8章"
    ],
    "tags": ["旧約聖書 / エゼキエル書"]
  },
  {
    "question": "【エゼキエル書8章-5】エゼキエル書8章の幻において、不正な行為は主にどこで行われていたか？",
    "choices": ["神殿内", "城壁の外", "市場で", "田畑で"],
    "answer": "神殿内",
    "explanation": "幻の中で不正な行為が行われていた場所は、聖なる神殿内部であり、そこに偶像崇拝が蔓延していました。参考：新解約2017版 エゼキエル書8章",
    "sources": [
      "エゼキエル書 8章"
    ],
    "tags": ["旧約聖書 / エゼキエル書"]
  },
  {
    "question": "【エゼキエル書8章-6】エゼキエル書8章の幻は何を強調するために用いられているか？",
    "choices": ["内在する偶像崇拝の罪", "経済の繁栄", "軍事の勝利", "農業の成功"],
    "answer": "内在する偶像崇拝の罪",
    "explanation": "幻は、神殿という本来聖なる場所に潜む、内在する偶像崇拝の罪を強調する目的で描かれています。参考：新解約2017版 エゼキエル書8章",
    "sources": [
      "エゼキエル書 8章"
    ],
    "tags": ["旧約聖書 / エゼキエル書"]
  },
  {
    "question": "【エゼキエル書8章-7】エゼキエル書8章において、神の裁きを促す要因は何だったか？",
    "choices": ["偶像に対する不忠実な礼拝", "戦争の失敗", "預言者の無言", "自然災害"],
    "answer": "偶像に対する不忠実な礼拝",
    "explanation": "神の怒りを引き起こす要因は、不忠実な礼拝や偶像崇拝にあったとされています。参考：新解約2017版 エゼキエル書8章",
    "sources": [
      "エゼキエル書 8章"
    ],
    "tags": ["旧約聖書 / エゼキエル書"]
  },
  {
    "question": "【エゼキエル書8章-8】エゼキエル書8章は、何が神からの罰を引き起こしたと伝えているか？",
    "choices": ["偶像崇拝と偽りの礼拝法", "商業の繁栄", "政治的安定", "正しい祭儀"],
    "answer": "偶像崇拝と偽りの礼拝法",
    "explanation": "幻は、偶像崇拝や偽りの礼拝法が原因で神の罰が下ることを強く警告しています。参考：新解約2017版 エゼキエル書8章",
    "sources": [
      "エゼキエル書 8章"
    ],
    "tags": ["旧約聖書 / エゼキエル書"]
  },
  {
    "question": "【エゼキエル書9章-1】エゼキエル書9章で神は、選ばれた者たちに何を施したか？",
    "choices": ["印を与えた", "豊かな遺産", "神聖な衣服", "鉄の剣"],
    "answer": "印を与えた",
    "explanation": "神は、悔い改め深い者たちを区別するために印を与え、裁きから守ろうとしました。参考：新解約2017版 エゼキエル書9章",
    "sources": [
      "エゼキエル書 9章"
    ],
    "tags": ["旧約聖書 / エゼキエル書"]
  },
  {
    "question": "【エゼキエル書9章-2】エゼキエル書9章において、特に印された者たちは何を免れたとされているか？",
    "choices": ["神の裁き", "商業の衰退", "国の崩壊", "異邦への攻撃"],
    "answer": "神の裁き",
    "explanation": "印を受けた者たちは、神の激しい裁きから保護される存在とされています。参考：新解約2017版 エゼキエル書9章",
    "sources": [
      "エゼキエル書 9章"
    ],
    "tags": ["旧約聖書 / エゼキエル書"]
  },
  {
    "question": "【エゼキエル書9章-3】エゼキエル書9章の印は、何を示すために用いられたか？",
    "choices": ["信仰深い者への保護", "政治的な権力", "金銭的成功", "社会的地位"],
    "answer": "信仰深い者への保護",
    "explanation": "印は、神が守るべき信仰深い者たちを他と区別するための象徴として使われました。参考：新解約2017版 エゼキエル書9章",
    "sources": [
      "エゼキエル書 9章"
    ],
    "tags": ["旧約聖書 / エゼキエル書"]
  },
  {
    "question": "【エゼキエル書9章-4】エゼキエル書9章における印の役割は何か？",
    "choices": ["選ばれた者を区別するため", "富の象徴", "軍事的勝利", "国家の統治"],
    "answer": "選ばれた者を区別するため",
    "explanation": "印は、神に従う信仰深い者とそうでない者を区別するための象徴として与えられました。参考：新解約2017版 エゼキエル書9章",
    "sources": [
      "エゼキエル書 9章"
    ],
    "tags": ["旧約聖書 / エゼキエル書"]
  },
  {
    "question": "【エゼキエル書9章-5】エゼキエル書9章の印が意味するものは何か？",
    "choices": ["神の慈悲と識別", "戦の準備", "商業の恩恵", "偶像の保護"],
    "answer": "神の慈悲と識別",
    "explanation": "印は、神の慈悲深さを示すと同時に、真に救われるべき者を識別するために与えられました。参考：新解約2017版 エゼキエル書9章",
    "sources": [
      "エゼキエル書 9章"
    ],
    "tags": ["旧約聖書 / エゼキエル書"]
  },
  {
    "question": "【エゼキエル書9章-6】エゼキエル書9章で印を受けた者は、どのような恩恵を得たとされるか？",
    "choices": ["守られた命", "富の蓄積", "政治的特権", "宗教的昇進"],
    "answer": "守られた命",
    "explanation": "印を受けた者は、神の裁きから逃れ、命が守られるという恩恵を与えられました。参考：新解約2017版 エゼキエル書9章",
    "sources": [
      "エゼキエル書 9章"
    ],
    "tags": ["旧約聖書 / エゼキエル書"]
  },
  {
    "question": "【エゼキエル書9章-7】エゼキエル書9章の印は、何の象徴として理解されるか？",
    "choices": ["神の選びと保護", "戦争の準備", "偶像崇拝の開始", "国家の再建"],
    "answer": "神の選びと保護",
    "explanation": "印は、神が特に選んだ者たちを示し、彼らが裁きから守られることを象徴しています。参考：新解約2017版 エゼキエル書9章",
    "sources": [
      "エゼキエル書 9章"
    ],
    "tags": ["旧約聖書 / エゼキエル書"]
  },
  {
    "question": "【エゼキエル書9章-8】エゼキエル書9章は、印を受けた者にどのような未来を約束しているか？",
    "choices": ["神の救いと免罪", "永遠の戦い", "物質的繁栄", "異邦との同盟"],
    "answer": "神の救いと免罪",
    "explanation": "印を受けた者たちには、神の救いと罪が赦される未来が約束されていると預言されています。参考：新解約2017版 エゼキエル書9章",
    "sources": [
      "エゼキエル書 9章"
    ],
    "tags": ["旧約聖書 / エゼキエル書"]
  },
  {
    "question": "【エゼキエル書10章-1】エゼキエル書10章において、エゼキエルは何を目撃したか？",
    "choices": ["神の栄光の一部が取り去られる幻", "民の祝宴", "異邦の罰", "豊作の証"],
    "answer": "神の栄光の一部が取り去られる幻",
    "explanation": "10章では、エゼキエルが神殿から神の栄光が部分的に取り去られる、厳粛な幻を目撃します。参考：新解約2017版 エゼキエル書10章",
    "sources": [
      "エゼキエル書 10章"
    ],
    "tags": ["旧約聖書 / エゼキエル書"]
  },
  {
    "question": "【エゼキエル書10章-2】エゼキエル書10章に登場する生き物の中で、特筆すべき現象は何か？",
    "choices": ["神の栄光の離脱", "天使の降臨", "預言者の昇天", "戦士の勝利"],
    "answer": "神の栄光の離脱",
    "explanation": "この章は、神の栄光が神殿から離れていく現象を強調し、神の怒りが現れていることを示唆しています。参考：新解約2017版 エゼキエル書10章",
    "sources": [
      "エゼキエル書 10章"
    ],
    "tags": ["旧約聖書 / エゼキエル書"]
  },
  {
    "question": "【エゼキエル書10章-3】エゼキエル書10章は、神のどの性質を強調しているか？",
    "choices": ["裁きの厳しさと潔さ", "慈悲深さ", "平和な導き", "富の恵み"],
    "answer": "裁きの厳しさと潔さ",
    "explanation": "幻は、神が裁きを下す際の厳しさと、それに伴う潔さを強調するために描かれています。参考：新解約2017版 エゼキエル書10章",
    "sources": [
      "エゼキエル書 10章"
    ],
    "tags": ["旧約聖書 / エゼキエル書"]
  },
  {
    "question": "【エゼキエル書10章-4】エゼキエル書10章の幻は、何を象徴するものとして解釈されるか？",
    "choices": ["神の栄光の一時的失われ", "永遠の救済", "国家の誕生", "農業の豊穣"],
    "answer": "神の栄光の一時的失われ",
    "explanation": "幻は、神殿から一時的に神の栄光が退く現象を示しており、裁きの段階を予告しています。参考：新解約2017版 エゼキエル書10章",
    "sources": [
      "エゼキエル書 10章"
    ],
    "tags": ["旧約聖書 / エゼキエル書"]
  },
  {
    "question": "【エゼキエル書10章-5】エゼキエル書10章の幻は、どのような変化を示しているか？",
    "choices": ["神殿から栄光が退く現象", "民の歓喜", "宴の開催", "祭司の昇進"],
    "answer": "神殿から栄光が退く現象",
    "explanation": "幻は、神殿から栄光が退く、つまり神の臨在が一時的に失われる変化を描いています。参考：新解約2017版 エゼキエル書10章",
    "sources": [
      "エゼキエル書 10章"
    ],
    "tags": ["旧約聖書 / エゼキエル書"]
  },
  {
    "question": "【エゼキエル書10章-6】エゼキエル書10章に描かれる預言は、何の始まりを告げているか？",
    "choices": ["神の裁きの段階", "新しい同盟", "豊かな祝福", "政治の改革"],
    "answer": "神の裁きの段階",
    "explanation": "幻は、神の裁きが次第に具体化し始める段階に入ったことを示唆しています。参考：新解約2017版 エゼキエル書10章",
    "sources": [
      "エゼキエル書 10章"
    ],
    "tags": ["旧約聖書 / エゼキエル書"]
  },
  {
    "question": "【エゼキエル書10章-7】エゼキエル書10章で見られる現象は、神の何を示唆しているか？",
    "choices": ["神の怒りと厳正な裁き", "民への優しさ", "預言者の称賛", "国家の再建"],
    "answer": "神の怒りと厳正な裁き",
    "explanation": "現象は、神が怒りに満ちた厳正な裁きを下そうとしていることを示しています。参考：新解約2017版 エゼキエル書10章",
    "sources": [
      "エゼキエル書 10章"
    ],
    "tags": ["旧約聖書 / エゼキエル書"]
  },
  {
    "question": "【エゼキエル書10章-8】エゼキエル書10章における幻の意義は何か？",
    "choices": ["神殿の聖域からの栄光喪失", "祭典の始まり", "豊穣祭の予兆", "民の勝利"],
    "answer": "神殿の聖域からの栄光喪失",
    "explanation": "幻は、神殿という聖域から神の栄光が失われることを象徴し、裁きの到来を告げています。参考：新解約2017版 エゼキエル書10章",
    "sources": [
      "エゼキエル書 10章"
    ],
    "tags": ["旧約聖書 / エゼキエル書"]
  },
  {
    "question": "【エゼキエル書11章-1】エゼキエル書11章は、どの層に対する神の裁きを預言しているか？",
    "choices": ["不正な指導者たち", "農民", "異邦の商人", "祭司以外の市民"],
    "answer": "不正な指導者たち",
    "explanation": "11章は、指導者層の不正行為に対し、神が厳しい裁きを下すと預言しています。参考：新解約2017版 エゼキエル書11章",
    "sources": [
      "エゼキエル書 11章"
    ],
    "tags": ["旧約聖書 / エゼキエル書"]
  },
  {
    "question": "【エゼキエル書11章-2】エゼキエル書11章において、エゼキエルは何を通して神の怒りを伝えたか？",
    "choices": ["偽りの指導層への警告", "軍の行動", "異邦との同盟", "農作物の収穫"],
    "answer": "偽りの指導層への警告",
    "explanation": "エゼキエルは、偽りの指導者たちに対する神の怒りを伝えるための警告の使者として描かれています。参考：新解約2017版 エゼキエル書11章",
    "sources": [
      "エゼキエル書 11章"
    ],
    "tags": ["旧約聖書 / エゼキエル書"]
  },
  {
    "question": "【エゼキエル書11章-3】エゼキエル書11章の預言は、何に対する懲罰として描かれているか？",
    "choices": ["不正な政治と裏切り", "宗教儀式の改革", "預言者の無視", "自然の災害"],
    "answer": "不正な政治と裏切り",
    "explanation": "この章は、不正な政治行為と指導者の裏切りが神の懲罰の対象とされると預言しています。参考：新解約2017版 エゼキエル書11章",
    "sources": [
      "エゼキエル書 11章"
    ],
    "tags": ["旧約聖書 / エゼキエル書"]
  },
  {
    "question": "【エゼキエル書11章-4】エゼキエル書11章に示される裁きは、誰に対して行われるか？",
    "choices": ["悪徳なリーダー達", "一般市民", "異邦の王", "祭司ではない者"],
    "answer": "悪徳なリーダー達",
    "explanation": "預言は、特に堕落したリーダーたちに対する神の裁きを強調しています。参考：新解約2017版 エゼキエル書11章",
    "sources": [
      "エゼキエル書 11章"
    ],
    "tags": ["旧約聖書 / エゼキエル書"]
  },
  {
    "question": "【エゼキエル書11章-5】エゼキエル書11章の預言的メッセージは、どのような状況を対象としているか？",
    "choices": ["神に背いた統治者の失墜", "繁栄する共同体", "新たな宗教運動", "農業の発達"],
    "answer": "神に背いた統治者の失墜",
    "explanation": "預言は、神に背いた指導者たちが失墜する運命にあることを述べ、民に警告を与えています。参考：新解約2017版 エゼキエル書11章",
    "sources": [
      "エゼキエル書 11章"
    ],
    "tags": ["旧約聖書 / エゼキエル書"]
  },
  {
    "question": "【エゼキエル書11章-6】エゼキエル書11章における神の裁きは、何に基づいているとされるか？",
    "choices": ["汚された心と行動", "富の操作", "祭りの失敗", "文書の偽造"],
    "answer": "汚された心と行動",
    "explanation": "神の裁きは、指導者たちの心の汚れや不正な行動に根ざしているとされています。参考：新解約2017版 エゼキエル書11章",
    "sources": [
      "エゼキエル書 11章"
    ],
    "tags": ["旧約聖書 / エゼキエル書"]
  },
  {
    "question": "【エゼキエル書11章-7】エゼキエル書11章は、どのような社会的リーダーの行動を批判しているか？",
    "choices": ["不正行為に走る指導者", "正直な農民", "礼儀正しい商人", "真面目な学者"],
    "answer": "不正行為に走る指導者",
    "explanation": "この章は、不正な行為に走る指導者たちに対して、神の裁きが下されると厳しく批判しています。参考：新解約2017版 エゼキエル書11章",
    "sources": [
      "エゼキエル書 11章"
    ],
    "tags": ["旧約聖書 / エゼキエル書"]
  },
  {
    "question": "【エゼキエル書11章-8】エゼキエル書11章は、どのような世代に向けられた警告として描かれているか？",
    "choices": ["堕落した指導層を含むすべての世代", "若者だけ", "高齢者だけ", "異邦人の世代"],
    "answer": "堕落した指導層を含むすべての世代",
    "explanation": "預言は、特定の世代に限らず、堕落した指導層が存在する全ての世代に向けた警告として解釈されます。参考：新解約2017版 エゼキエル書11章",
    "sources": [
      "エゼキエル書 11章"
    ],
    "tags": ["旧約聖書 / エゼキエル書"]
  },
  {
    "question": "【エゼキエル書12章-1】エゼキエル書12章における預言者の行動は、何を象徴していると解釈されるか？",
    "choices": ["迫り来る捕囚の兆候", "新たな祝祭の開始", "豊作の暗示", "異邦との和解"],
    "answer": "迫り来る捕囚の兆候",
    "explanation": "エゼキエルの象徴的な行動は、民が捕囚に向かうことを予告するもので、激しい警告となっています。参考：新解約2017版 エゼキエル書12章",
    "sources": [
      "エゼキエル書 12章"
    ],
    "tags": ["旧約聖書 / エゼキエル書"]
  },
  {
    "question": "【エゼキエル書12章-2】エゼキエル書12章の象徴的な行動は、何を示しているか？",
    "choices": ["イスラエルの追放", "国の拡大", "政治的繁栄", "宗教的結束"],
    "answer": "イスラエルの追放",
    "explanation": "この象徴的行動は、イスラエルの民が神の裁きにより追放される未来を示すものです。参考：新解約2017版 エゼキエル書12章",
    "sources": [
      "エゼキエル書 12章"
    ],
    "tags": ["旧約聖書 / エゼキエル書"]
  },
  {
    "question": "【エゼキエル書12章-3】エゼキエル書12章に描かれた象徴行為は、どのような歴史的出来事を予告しているか？",
    "choices": ["捕囚と亡命", "戦争の勝利", "国家の独立", "経済の発展"],
    "answer": "捕囚と亡命",
    "explanation": "象徴行為は、捕囚状態と民の亡命という、悲劇的な歴史的出来事を予告しています。参考：新解約2017版 エゼキエル書12章",
    "sources": [
      "エゼキエル書 12章"
    ],
    "tags": ["旧約聖書 / エゼキエル書"]
  },
  {
    "question": "【エゼキエル書12章-4】エゼキエル書12章は、どのような未来を暗示していると言われているか？",
    "choices": ["追放と流浪の時代", "黄金時代", "平和な統治", "宗教的改革"],
    "answer": "追放と流浪の時代",
    "explanation": "預言は、民が捕囚され、異国で流浪する時代が到来することを強く暗示しています。参考：新解約2017版 エゼキエル書12章",
    "sources": [
      "エゼキエル書 12章"
    ],
    "tags": ["旧約聖書 / エゼキエル書"]
  },
  {
    "question": "【エゼキエル書12章-5】エゼキエル書12章における、異国行きの象徴は何を意味しているか？",
    "choices": ["神の裁きによる放逐", "異邦への貿易", "文化の交流", "平和な移住"],
    "answer": "神の裁きによる放逐",
    "explanation": "この象徴は、民が神の裁きにより、異国へと放逐されることを意味しています。参考：新解約2017版 エゼキエル書12章",
    "sources": [
      "エゼキエル書 12章"
    ],
    "tags": ["旧約聖書 / エゼキエル書"]
  },
  {
    "question": "【エゼキエル書12章-6】エゼキエル書12章の預言行為は、何に対する象徴的な警告であったか？",
    "choices": ["国への裏切りと罰", "経済の成功", "宗教儀式の刷新", "新たな盟約"],
    "answer": "国への裏切りと罰",
    "explanation": "預言行為は、国が神に裏切られた結果として、厳しい罰が下ることを警告するものです。参考：新解約2017版 エゼキエル書12章",
    "sources": [
      "エゼキエル書 12章"
    ],
    "tags": ["旧約聖書 / エゼキエル書"]
  },
  {
    "question": "【エゼキエル書12章-7】エゼキエル書12章の描写は、どのような物語の一端を示しているか？",
    "choices": ["捕囚に向かう民の運命", "国際貿易の繁栄", "異邦文化の受容", "祭司の昇進"],
    "answer": "捕囚に向かう民の運命",
    "explanation": "描写は、民が捕囚へと向かう悲劇的な運命を物語の一端として示しています。参考：新解約2017版 エゼキエル書12章",
    "sources": [
      "エゼキエル書 12章"
    ],
    "tags": ["旧約聖書 / エゼキエル書"]
  },
  {
    "question": "【エゼキエル書12章-8】エゼキエル書12章の象徴的な行動は、最終的に何を予告しているとされるか？",
    "choices": ["民の散逸と捕囚", "国家の再興", "新たな連帯", "宗教的再生"],
    "answer": "民の散逸と捕囚",
    "explanation": "象徴行動は、民が散逸し捕囚されるという厳しい未来を予告しています。参考：新解約2017版 エゼキエル書12章",
    "sources": [
      "エゼキエル書 12章"
    ],
    "tags": ["旧約聖書 / エゼキエル書"]
  },
  {
    "question": "【エゼキエル書13章-1】エゼキエル書13章は主に何に対する警告か？",
    "choices": ["偽預言者の欺瞞", "正しい指導者の栄光", "豊かな収穫", "平和な政権"],
    "answer": "偽預言者の欺瞞",
    "explanation": "13章は、偽りの預言者が民を誤った道に導くことに対し、厳しい警告を発しています。参考：新解約2017版 エゼキエル書13章",
    "sources": [
      "エゼキエル書 13章"
    ],
    "tags": ["旧約聖書 / エゼキエル書"]
  },
  {
    "question": "【エゼキエル書13章-2】エゼキエル書13章で批判されている人物は誰か？",
    "choices": ["偽預言者", "正直な預言者", "勇敢な戦士", "勤勉な農民"],
    "answer": "偽預言者",
    "explanation": "預言者たちの中でも、真実を伴わない偽預言者が特に非難の対象とされています。参考：新解約2017版 エゼキエル書13章",
    "sources": [
      "エゼキエル書 13章"
    ],
    "tags": ["旧約聖書 / エゼキエル書"]
  },
  {
    "question": "【エゼキエル書13章-3】エゼキエル書13章の偽預言者の行為は、何をもたらすとされるか？",
    "choices": ["民の混乱と誤導", "経済の発展", "宗教的統一", "国家の繁栄"],
    "answer": "民の混乱と誤導",
    "explanation": "偽預言者の虚偽の語りは、民に大きな混乱と誤った信仰をもたらすとされています。参考：新解約2017版 エゼキエル書13章",
    "sources": [
      "エゼキエル書 13章"
    ],
    "tags": ["旧約聖書 / エゼキエル書"]
  },
  {
    "question": "【エゼキエル書13章-4】エゼキエル書13章の預言は、どの指導者層への警告か？",
    "choices": ["虚偽を伝える預言者たち", "正義を貫く者たち", "民を支える教師たち", "聖なる祭司"],
    "answer": "虚偽を伝える預言者たち",
    "explanation": "預言は、神の名をあやふやにする虚偽の預言者たちに対する警告として描かれています。参考：新解約2017版 エゼキエル書13章",
    "sources": [
      "エゼキエル書 13章"
    ],
    "tags": ["旧約聖書 / エゼキエル書"]
  },
  {
    "question": "【エゼキエル書13章-5】エゼキエル書13章で非難される偽預言者たちは、何を誤用しているとされたか？",
    "choices": ["神の名", "民の財産", "国家の権力", "伝統の知恵"],
    "answer": "神の名",
    "explanation": "偽預言者たちは、神の聖なる名を自らの利益のために誤用することで、民を惑わせています。参考：新解約2017版 エゼキエル書13章",
    "sources": [
      "エゼキエル書 13章"
    ],
    "tags": ["旧約聖書 / エゼキエル書"]
  },
  {
    "question": "【エゼキエル書13章-6】エゼキエル書13章において、偽預言者の予言はどのような結果を招くと描かれているか？",
    "choices": ["民の裏切りと混乱", "宗教の統一", "平和な繁栄", "預言の真実"],
    "answer": "民の裏切りと混乱",
    "explanation": "偽預言は、民に誤った指導を与え、最終的には裏切りと混乱を招くとされています。参考：新解約2017版 エゼキエル書13章",
    "sources": [
      "エゼキエル書 13章"
    ],
    "tags": ["旧約聖書 / エゼキエル書"]
  },
  {
    "question": "【エゼキエル書13章-7】エゼキエル書13章の批判は、何を正そうとするものか？",
    "choices": ["真理に基づかない預言行為", "経済的不正", "戦争の野望", "文化の衰退"],
    "answer": "真理に基づかない預言行為",
    "explanation": "批判は、神の真理に基づかない虚偽の預言行為を正そうとするものです。参考：新解約2017版 エゼキエル書13章",
    "sources": [
      "エゼキエル書 13章"
    ],
    "tags": ["旧約聖書 / エゼキエル書"]
  },
  {
    "question": "【エゼキエル書13章-8】エゼキエル書13章は、どのような虚偽の行為に対して警鐘を鳴らしているか？",
    "choices": ["偽りの啓示の伝達", "正統な啓示の拒否", "宗教儀式の充実", "政治的改革"],
    "answer": "偽りの啓示の伝達",
    "explanation": "預言は、偽りの啓示を伝える偽預言者の行為に対して、厳しく警鐘を鳴らしています。参考：新解約2017版 エゼキエル書13章",
    "sources": [
      "エゼキエル書 13章"
    ],
    "tags": ["旧約聖書 / エゼキエル書"]
  },
  {
    "question": "【エゼキエル書14章-1】エゼキエル書14章は、主に何に対する神の裁きについて述べているか？",
    "choices": ["偶像崇拝", "正しい礼拝", "経済的繁栄", "国際的同盟"],
    "answer": "偶像崇拝",
    "explanation": "14章は、偶像崇拝が神に背く重大な罪であるとして、厳しい裁きを予告しています。参考：新解約2017版 エゼキエル書14章",
    "sources": [
      "エゼキエル書 14章"
    ],
    "tags": ["旧約聖書 / エゼキエル書"]
  },
  {
    "question": "【エゼキエル書14章-2】エゼキエル書14章における裁きの預言は、何の行為に焦点を当てているか？",
    "choices": ["偶像への信仰", "正統な祭儀", "社会的結束", "農業の成功"],
    "answer": "偶像への信仰",
    "explanation": "この章は、民が偶像に頼る信仰そのものが、神の裁きの対象であると強調しています。参考：新解約2017版 エゼキエル書14章",
    "sources": [
      "エゼキエル書 14章"
    ],
    "tags": ["旧約聖書 / エゼキエル書"]
  },
  {
    "question": "【エゼキエル書14章-3】エゼキエル書14章は、どのような人々に対して厳しい裁きを予告しているか？",
    "choices": ["偶像に頼る者", "慈悲深い者", "賢明な者", "正義を行う者"],
    "answer": "偶像に頼る者",
    "explanation": "偶像を頼る者は、神に逆らう行為として、厳しい罰の対象とされています。参考：新解約2017版 エゼキエル書14章",
    "sources": [
      "エゼキエル書 14章"
    ],
    "tags": ["旧約聖書 / エゼキエル書"]
  },
  {
    "question": "【エゼキエル書14章-4】エゼキエル書14章に描かれた裁きは、何の結果として示されているか？",
    "choices": ["信仰の誤りと堕落", "経済の発展", "文化の興隆", "政治の安定"],
    "answer": "信仰の誤りと堕落",
    "explanation": "裁きは、偶像崇拝による信仰の歪みと堕落の結果として示されています。参考：新解約2017版 エゼキエル書14章",
    "sources": [
      "エゼキエル書 14章"
    ],
    "tags": ["旧約聖書 / エゼキエル書"]
  },
  {
    "question": "【エゼキエル書14章-5】エゼキエル書14章は、偶像崇拝がもたらす何を強調しているか？",
    "choices": ["破滅の結果", "繁栄の兆し", "新たな連帯", "宗教的覚醒"],
    "answer": "破滅の結果",
    "explanation": "偶像崇拝が生むのは、信仰の誤りによる破滅的な結末であると預言されています。参考：新解約2017版 エゼキエル書14章",
    "sources": [
      "エゼキエル書 14章"
    ],
    "tags": ["旧約聖書 / エゼキエル書"]
  },
  {
    "question": "【エゼキエル書14章-6】エゼキエル書14章において、偶像崇拝はどのような道徳的問題と関連付けられているか？",
    "choices": ["信仰の裏切り", "慈善の欠如", "商業倫理の問題", "家庭の崩壊"],
    "answer": "信仰の裏切り",
    "explanation": "偶像崇拝は、真の神への信頼を裏切る行為とみなされ、道徳的な問題と結びつけられています。参考：新解約2017版 エゼキエル書14章",
    "sources": [
      "エゼキエル書 14章"
    ],
    "tags": ["旧約聖書 / エゼキエル書"]
  },
  {
    "question": "【エゼキエル書14章-7】エゼキエル書14章の預言は、どのような信仰の在り方を否定しているか？",
    "choices": ["偶像に依存する信仰", "神への全幅の信頼", "正統な礼拝", "共同体の団結"],
    "answer": "偶像に依存する信仰",
    "explanation": "預言は、偶像に頼り自らの意思で信仰を築くことを否定し、真の神信仰を求めています。参考：新解約2017版 エゼキエル書14章",
    "sources": [
      "エゼキエル書 14章"
    ],
    "tags": ["旧約聖書 / エゼキエル書"]
  },
  {
    "question": "【エゼキエル書14章-8】エゼキエル書14章は、何に対する警告として裁きを伝えているか？",
    "choices": ["偶像崇拝による堕落", "正義を貫く行為", "経済的繁栄", "宗教儀式の刷新"],
    "answer": "偶像崇拝による堕落",
    "explanation": "偶像に頼る信仰は、信仰の裏切りと堕落を招くとされ、神の裁きを受ける原因となります。参考：新解約2017版 エゼキエル書14章",
    "sources": [
      "エゼキエル書 14章"
    ],
    "tags": ["旧約聖書 / エゼキエル書"]
  },
  {
    "question": "【エゼキエル書15章-1】エゼキエル書15章で、エゼキエルは何をぶどうの木に例えて表現しているか？",
    "choices": ["無用な木、腐敗した都", "豊かな生命", "神の祝福", "正しい指導者"],
    "answer": "無用な木、腐敗した都",
    "explanation": "たとえ話は、エルサレムの腐敗と無用な存在状態を、枯れた木に例えて表現しています。参考：新解約2017版 エゼキエル書15章",
    "sources": [
      "エゼキエル書 15章"
    ],
    "tags": ["旧約聖書 / エゼキエル書"]
  },
  {
    "question": "【エゼキエル書15章-2】エゼキエル書15章のたとえ話は何の象徴として用いられているか？",
    "choices": ["堕落したエルサレム", "新たな始まり", "平和な繁栄", "神の救済"],
    "answer": "堕落したエルサレム",
    "explanation": "このたとえは、堕落して無価値になったエルサレムの運命を象徴する比喩として用いられています。参考：新解約2017版 エゼキエル書15章",
    "sources": [
      "エゼキエル書 15章"
    ],
    "tags": ["旧約聖書 / エゼキエル書"]
  },
  {
    "question": "【エゼキエル書15章-3】エゼキエル書15章において、木が焼かれる象徴は何を意味しているか？",
    "choices": ["無価値と滅亡", "再生と復興", "聖なる試練", "内面的な変革"],
    "answer": "無価値と滅亡",
    "explanation": "木が焼かれる様子は、もはや使い物にならない、すなわち滅亡する運命を象徴しています。参考：新解約2017版 エゼキエル書15章",
    "sources": [
      "エゼキエル書 15章"
    ],
    "tags": ["旧約聖書 / エゼキエル書"]
  },
  {
    "question": "【エゼキエル書15章-4】エゼキエル書15章は、エルサレムの運命をどのようにたとえているか？",
    "choices": ["燃え尽きる枯れ木", "生い茂る庭", "果実を実らせる葡萄", "聖なる樹"],
    "answer": "燃え尽きる枯れ木",
    "explanation": "エルサレムの運命は、枯れて燃え尽きる木に例えられ、その無用さと破壊を象徴しています。参考：新解約2017版 エゼキエル書15章",
    "sources": [
      "エゼキエル書 15章"
    ],
    "tags": ["旧約聖書 / エゼキエル書"]
  },
  {
    "question": "【エゼキエル書15章-5】エゼキエル書15章のたとえにおける木の運命は、何を示唆しているか？",
    "choices": ["都市の完全な崩壊", "自然のサイクル", "豊かな実り", "新たな生命の芽吹き"],
    "answer": "都市の完全な崩壊",
    "explanation": "木の燃え尽きる様は、エルサレムが完全に崩壊する運命を象徴しています。参考：新解約2017版 エゼキエル書15章",
    "sources": [
      "エゼキエル書 15章"
    ],
    "tags": ["旧約聖書 / エゼキエル書"]
  },
  {
    "question": "【エゼキエル書15章-6】エゼキエル書15章において、たとえ話が警告しているのは何か？",
    "choices": ["堕落と滅亡", "神の慈愛", "共同体の結束", "経済の発展"],
    "answer": "堕落と滅亡",
    "explanation": "たとえは、都市の無価値な状態や堕落、そしてそれに続く滅亡を警告しています。参考：新解約2017版 エゼキエル書15章",
    "sources": [
      "エゼキエル書 15章"
    ],
    "tags": ["旧約聖書 / エゼキエル書"]
  },
  {
    "question": "【エゼキエル書15章-7】エゼキエル書15章の比喩は、どのような運命を象徴しているか？",
    "choices": ["無益な滅び", "栄光の復活", "繁栄の兆し", "知恵の伝承"],
    "answer": "無益な滅び",
    "explanation": "比喩は、エルサレムの状態が、何の役にも立たず、ただ滅び去る運命にあることを象徴しています。参考：新解約2017版 エゼキエル書15章",
    "sources": [
      "エゼキエル書 15章"
    ],
    "tags": ["旧約聖書 / エゼキエル書"]
  },
  {
    "question": "【エゼキエル書15章-8】エゼキエル書15章は、何をもって都市の無価値さを示しているとされるか？",
    "choices": ["燃え尽きた枯れ木", "満開の花々", "堅固な城壁", "豊かな実り"],
    "answer": "燃え尽きた枯れ木",
    "explanation": "燃え尽きた枯れ木というたとえは、都市がもはや生命力を失い、無価値である様を鋭く表現しています。参考：新解約2017版 エゼキエル書15章",
    "sources": [
      "エゼキエル書 15章"
    ],
    "tags": ["旧約聖書 / エゼキエル書"]
  },
  {
    "question": "【エゼキエル書16章-1】エゼキエル書16章では、エルサレムはどのようにたとえられているか？",
    "choices": ["不実な女性", "賢い母", "勇敢な戦士", "慈悲深い預言者"],
    "answer": "不実な女性",
    "explanation": "たとえ話では、エルサレムの不忠実さと堕落が、不実な女性に例えられています。参考：新解約2017版 エゼキエル書16章",
    "sources": [
      "エゼキエル書 16章"
    ],
    "tags": ["旧約聖書 / エゼキエル書"]
  },
  {
    "question": "【エゼキエル書16章-2】エゼキエル書16章において、エルサレムの行いは何の象徴として描かれているか？",
    "choices": ["神への背信", "豊かな祝福", "宗教的献身", "国家の繁栄"],
    "answer": "神への背信",
    "explanation": "エルサレムの行いは、神への信頼を裏切る背信行為として象徴的に描かれています。参考：新解約2017版 エゼキエル書16章",
    "sources": [
      "エゼキエル書 16章"
    ],
    "tags": ["旧約聖書 / エゼキエル書"]
  },
  {
    "question": "【エゼキエル書16章-3】エゼキエル書16章に見られるたとえは、何を非難しているか？",
    "choices": ["宗教的不貞行為", "経済的無関心", "政治的冷静", "文化の多様性"],
    "answer": "宗教的不貞行為",
    "explanation": "たとえは、エルサレムの背信と不貞、すなわち神との関係における不忠実さを非難するものです。参考：新解約2017版 エゼキエル書16章",
    "sources": [
      "エゼキエル書 16章"
    ],
    "tags": ["旧約聖書 / エゼキエル書"]
  },
  {
    "question": "【エゼキエル書16章-4】エゼキエル書16章は、エルサレムの過去と現在をどのように対比しているか？",
    "choices": ["無垢から堕落への変化", "豊かさから貧困への移行", "勇気から恐怖への変容", "平和から戦争への発展"],
    "answer": "無垢から堕落への変化",
    "explanation": "エルサレムのかつての無垢な状態と、現在の背信状態が対比され、その変貌が厳しく非難されています。参考：新解約2017版 エゼキエル書16章",
    "sources": [
      "エゼキエル書 16章"
    ],
    "tags": ["旧約聖書 / エゼキエル書"]
  },
  {
    "question": "【エゼキエル書16章-5】エゼキエル書16章における象徴表現は、何を批判するために用いられているか？",
    "choices": ["不忠実な行い", "経済的混乱", "農業の不作", "国家の境界"],
    "answer": "不忠実な行い",
    "explanation": "象徴は、民が神に対して不忠実である点を厳しく批判するために用いられています。参考：新解約2017版 エゼキエル書16章",
    "sources": [
      "エゼキエル書 16章"
    ],
    "tags": ["旧約聖書 / エゼキエル書"]
  },
  {
    "question": "【エゼキエル書16章-6】エゼキエル書16章は、どのような行為に対して神の怒りを預言しているか？",
    "choices": ["背信と不貞", "正直な取引", "勤勉な努力", "愛に満ちた行動"],
    "answer": "背信と不貞",
    "explanation": "神は、背信と不貞に対して激しい怒りを持って、罰が下ることを預言しています。参考：新解約2017版 エゼキエル書16章",
    "sources": [
      "エゼキエル書 16章"
    ],
    "tags": ["旧約聖書 / エゼキエル書"]
  },
  {
    "question": "【エゼキエル書16章-7】エゼキエル書16章でたとえられるエルサレムの姿は、何を象徴しているか？",
    "choices": ["不実さと堕落", "信仰の純粋さ", "正義の堅守", "民の団結"],
    "answer": "不実さと堕落",
    "explanation": "不実な行為により堕落したエルサレムの姿が、不実さと堕落を象徴していると預言されています。参考：新解約2017版 エゼキエル書16章",
    "sources": [
      "エゼキエル書 16章"
    ],
    "tags": ["旧約聖書 / エゼキエル書"]
  },
  {
    "question": "【エゼキエル書16章-8】エゼキエル書16章は、エルサレムの姿をどのような警告として描いているか？",
    "choices": ["神の激しい怒りを招く行い", "繁栄の到来", "国際的な称賛", "文化的復興"],
    "answer": "神の激しい怒りを招く行い",
    "explanation": "預言は、エルサレムの不実な行為が神の激しい怒りを招く危険性を強調し、警告を与えています。参考：新解約2017版 エゼキエル書16章",
    "sources": [
      "エゼキエル書 16章"
    ],
    "tags": ["旧約聖書 / エゼキエル書"]
  },
  {
    "question": "【エゼキエル書17章-1】エゼキエル書17章のたとえ話に登場する主要な登場人物は誰か？",
    "choices": ["二羽の鷲", "二人の預言者", "二つの山", "二匹の獣"],
    "answer": "二羽の鷲",
    "explanation": "たとえ話では、二羽の鷲が主要な役割を果たし、これが政治的状況の象徴として用いられています。参考：新解約2017版 エゼキエル書17章",
    "sources": [
      "エゼキエル書 17章"
    ],
    "tags": ["旧約聖書 / エゼキエル書"]
  },
  {
    "question": "【エゼキエル書17章-2】エゼキエル書17章のたとえは、主に何を象徴しているか？",
    "choices": ["国際的な同盟の破綻", "宗教儀式の刷新", "科学の進展", "農業の繁栄"],
    "answer": "国際的な同盟の破綻",
    "explanation": "たとえ話は、異邦国間の同盟関係が破綻し、その結果互いに不信が募る現実を象徴しています。参考：新解約2017版 エゼキエル書17章",
    "sources": [
      "エゼキエル書 17章"
    ],
    "tags": ["旧約聖書 / エゼキエル書"]
  },
  {
    "question": "【エゼキエル書17章-3】エゼキエル書17章において、たとえ話の中の葡萄は何を象徴しているか？",
    "choices": ["王国の運命", "理想の秩序", "民の繁栄", "聖なる血統"],
    "answer": "王国の運命",
    "explanation": "葡萄は、王国の存続や滅亡といった運命を象徴する比喩として使われています。参考：新解約2017版 エゼキエル書17章",
    "sources": [
      "エゼキエル書 17章"
    ],
    "tags": ["旧約聖書 / エゼキエル書"]
  },
  {
    "question": "【エゼキエル書17章-4】エゼキエル書17章は、どのような国家間の関係をたとえているとされているか？",
    "choices": ["裏切りと不信の政治", "平和的共存", "経済的協力", "文化交流"],
    "answer": "裏切りと不信の政治",
    "explanation": "このたとえ話は、国際政治における裏切りや不信がもたらす混乱を象徴しています。参考：新解約2017版 エゼキエル書17章",
    "sources": [
      "エゼキエル書 17章"
    ],
    "tags": ["旧約聖書 / エゼキエル書"]
  },
  {
    "question": "【エゼキエル書17章-5】エゼキエル書17章のたとえ話は、どのようなメッセージを伝えているか？",
    "choices": ["王国の没落と混乱", "新しい王国の誕生", "繁栄の連鎖", "宗教の再興"],
    "answer": "王国の没落と混乱",
    "explanation": "たとえは、国家の権勢が一度失墜し、混乱に陥る可能性を警告するものです。参考：新解約2017版 エゼキエル書17章",
    "sources": [
      "エゼキエル書 17章"
    ],
    "tags": ["旧約聖書 / エゼキエル書"]
  },
  {
    "question": "【エゼキエル書17章-6】エゼキエル書17章において、たとえ話は何を警告しているか？",
    "choices": ["不信と裏切りの危険", "自然災害の予告", "経済の成熟", "交通の発展"],
    "answer": "不信と裏切りの危険",
    "explanation": "たとえ話は、国家間の不信が裏切りにつながる危険性を示しています。参考：新解約2017版 エゼキエル書17章",
    "sources": [
      "エゼキエル書 17章"
    ],
    "tags": ["旧約聖書 / エゼキエル書"]
  },
  {
    "question": "【エゼキエル書17章-7】エゼキエル書17章における象徴的な鷲は、どの力を示しているか？",
    "choices": ["強大な支配力", "芸術の美しさ", "宗教の温かさ", "平和の象徴"],
    "answer": "強大な支配力",
    "explanation": "鷲は、国や勢力の持つ強大な支配力を象徴する象徴的な存在として描かれています。参考：新解約2017版 エゼキエル書17章", 
    "sources": [
      "エゼキエル書 17章"
    ],
    "tags": ["旧約聖書 / エゼキエル書"]
  },
  {
    "question": "【エゼキエル書17章-8】エゼキエル書17章のたとえ話は、最終的に何を予告しているか？",
    "choices": ["王国の崩壊と混乱", "民の救済", "宗教の革新", "文化の復興"],
    "answer": "王国の崩壊と混乱",
    "explanation": "たとえは、国家の不信から起こる最終的な崩壊と、それに伴う混乱を予告しています。参考：新解約2017版 エゼキエル書17章",
    "sources": [
      "エゼキエル書 17章"
    ],
    "tags": ["旧約聖書 / エゼキエル書"]
  },
  {
    "question": "【エゼキエル書18章-1】エゼキエル書18章の預言は、主に何の原則を強調しているか？",
    "choices": ["個人の責任", "共同体の罪", "預言者の権威", "国家の過失"],
    "answer": "個人の責任",
    "explanation": "18章は、各人の行いに応じた評価が行われるという、個々の責任の原則を強調しています。参考：新解約2017版 エゼキエル書18章",
    "sources": [
      "エゼキエル書 18章"
    ],
    "tags": ["旧約聖書 / エゼキエル書"]
  },
  {
    "question": "【エゼキエル書18章-2】エゼキエル書18章の罪と罰の関係は、何に基づいて評価されるか？",
    "choices": ["各個人の行い", "家族の名誉", "民族の伝統", "部族の習慣"],
    "answer": "各個人の行い",
    "explanation": "罪と罰は、その人自身の行動に基づいて評価されるという点が、この章の核心です。参考：新解約2017版 エゼキエル書18章",
    "sources": [
      "エゼキエル書 18章"
    ],
    "tags": ["旧約聖書 / エゼキエル書"]
  },
  {
    "question": "【エゼキエル書18章-3】エゼキエル書18章のメッセージは、どのような倫理観を反映しているか？",
    "choices": ["因果応報", "集団責任", "運命論", "外交関係"],
    "answer": "因果応報",
    "explanation": "この章は、各人の行いに応じた結果が生じるという因果応報の倫理観を強調しています。参考：新解約2017版 エゼキエル書18章",
    "sources": [
      "エゼキエル書 18章"
    ],
    "tags": ["旧約聖書 / エゼキエル書"]
  },
  {
    "question": "【エゼキエル書18章-4】エゼキエル書18章は、罪の責任を誰に帰するかを明確にしているか？",
    "choices": ["本人に", "祖先に", "預言者に", "国家に"],
    "answer": "本人に",
    "explanation": "罪は、各個人に帰属するものであるという考えが、この章の教えの中心となっています。参考：新解約2017版 エゼキエル書18章",
    "sources": [
      "エゼキエル書 18章"
    ],
    "tags": ["旧約聖書 / エゼキエル書"]
  },
  {
    "question": "【エゼキエル書18章-5】エゼキエル書18章で語られる救いは、何に基づいているか？",
    "choices": ["個人の改心と行い", "血統", "宗教儀式", "社会的地位"],
    "answer": "個人の改心と行い",
    "explanation": "救いは、個々人が真摯に悔い改め、正しい行いをすることに基づいて与えられます。参考：新解約2017版 エゼキエル書18章",
    "sources": [
      "エゼキエル書 18章"
    ],
    "tags": ["旧約聖書 / エゼキエル書"]
  },
  {
    "question": "【エゼキエル書18章-6】エゼキエル書18章における罪の評価は、何を重視しているか？",
    "choices": ["本人の行動", "家族の功績", "先祖の罪", "同胞の信仰"],
    "answer": "本人の行動",
    "explanation": "評価は、本人が実際に行った行いに基づいて行われ、他者の責任は問われません。参考：新解約2017版 エゼキエル書18章",
    "sources": [
      "エゼキエル書 18章"
    ],
    "tags": ["旧約聖書 / エゼキエル書"]
  },
  {
    "question": "【エゼキエル書18章-7】エゼキエル書18章の預言は、どのような行動変容を促しているか？",
    "choices": ["真摯な悔い改め", "経済の繁栄", "政治的革命", "文化の模倣"],
    "answer": "真摯な悔い改め",
    "explanation": "個々人に対して、罪に対する真摯な悔い改めと行動の変化が求められることが、この章の教えです。参考：新解約2017版 エゼキエル書18章",
    "sources": [
      "エゼキエル書 18章"
    ],
    "tags": ["旧約聖書 / エゼキエル書"]
  },
  {
    "question": "【エゼキエル書18章-8】エゼキエル書18章は、集団的な罪の考え方に対して何を訴えているか？",
    "choices": ["個々人の責任を問う", "共同体の連帯責任", "文化の継承", "民族の伝統"],
    "answer": "個々人の責任を問う",
    "explanation": "この章は、集団としてではなく、各人個別の行いに対して神が責任を問うという立場を取っています。参考：新解約2017版 エゼキエル書18章",
    "sources": [
      "エゼキエル書 18章"
    ],
    "tags": ["旧約聖書 / エゼキエル書"]
  },
  {
    "question": "【エゼキエル書19章-1】エゼキエル書19章は、主に何について嘆いているか？",
    "choices": ["イスラエルの王子たちの堕落", "豊かな実り", "神の恵み", "宗教の統一"],
    "answer": "イスラエルの王子たちの堕落",
    "explanation": "嘆きは、指導者である王子たちの堕落した行動と、その結果としての悲劇を嘆く内容です。参考：新解約2017版 エゼキエル書19章",
    "sources": [
      "エゼキエル書 19章"
    ],
    "tags": ["旧約聖書 / エゼキエル書"]
  },
  {
    "question": "【エゼキエル書19章-2】エゼキエル書19章の嘆きは、どのような悲哀を表現しているか？",
    "choices": ["指導者の失墜と悲劇", "民の歓喜", "国家の富", "平和な同盟"],
    "answer": "指導者の失墜と悲劇",
    "explanation": "嘆きは、指導者の堕落とそれに伴う悲劇的な結果を深く嘆く内容です。参考：新解約2017版 エゼキエル書19章",
    "sources": [
      "エゼキエル書 19章"
    ],
    "tags": ["旧約聖書 / エゼキエル書"]
  },
  {
    "question": "【エゼキエル書19章-3】エゼキエル書19章は、誰の失敗について嘆いているか？",
    "choices": ["王子たちの堕落", "預言者の無視", "農民の不作", "異邦人の反乱"],
    "answer": "王子たちの堕落",
    "explanation": "預言は、特に王子たちの堕落と、その不祥事について嘆きを捧げています。参考：新解約2017版 エゼキエル書19章",
    "sources": [
      "エゼキエル書 19章"
    ],
    "tags": ["旧約聖書 / エゼキエル書"]
  },
  {
    "question": "【エゼキエル書19章-4】エゼキエル書19章に見られる嘆きの歌は、何を象徴しているか？",
    "choices": ["指導者の悲哀と裏切り", "国家の繁栄", "宗教の祝福", "自然の恵み"],
    "answer": "指導者の悲哀と裏切り",
    "explanation": "嘆きの歌は、指導者たちの裏切りと悲哀を象徴し、その堕落に対する深い失望を表現しています。参考：新解約2017版 エゼキエル書19章",
    "sources": [
      "エゼキエル書 19章"
    ],
    "tags": ["旧約聖書 / エゼキエル書"]
  },
  {
    "question": "【エゼキエル書19章-5】エゼキエル書19章は、どのような指導者の素行を批判しているか？",
    "choices": ["無責任な王子たち", "勤勉な民", "正直な商人", "優れた学者"],
    "answer": "無責任な王子たち",
    "explanation": "堕落した王子たちの無責任な行動が、神の裁きの対象となると強調されています。参考：新解約2017版 エゼキエル書19章",
    "sources": [
      "エゼキエル書 19章"
    ],
    "tags": ["旧約聖書 / エゼキエル書"]
  },
  {
    "question": "【エゼキエル書19章-6】エゼキエル書19章における嘆きは、何から生じたものか？",
    "choices": ["信頼の裏切り", "豊かな収穫", "文化の発展", "宗教の革新"],
    "answer": "信頼の裏切り",
    "explanation": "嘆きは、指導者たちが国民の信頼を裏切った結果として生じる悲劇を表現しています。参考：新解約2017版 エゼキエル書19章",
    "sources": [
      "エゼキエル書 19章"
    ],
    "tags": ["旧約聖書 / エゼキエル書"]
  },
  {
    "question": "【エゼキエル書19章-7】エゼキエル書19章の悲嘆の声は、将来にどのような警告を示しているか？",
    "choices": ["指導者の没落がもたらす悲劇", "経済の繁栄", "新たな政策", "平和な同盟"],
    "answer": "指導者の没落がもたらす悲劇",
    "explanation": "預言は、堕落した指導者の結果として、国全体に悲劇が起こることを警告しています。参考：新解約2017版 エゼキエル書19章",
    "sources": [
      "エゼキエル書 19章"
    ],
    "tags": ["旧約聖書 / エゼキエル書"]
  },
  {
    "question": "【エゼキエル書19章-8】エゼキエル書19章は、誰のために哀歌を捧げていると描かれているか？",
    "choices": ["堕落した指導者たちのため", "勇敢な戦士のため", "偉大な預言者のため", "正しい民のため"],
    "answer": "堕落した指導者たちのため",
    "explanation": "預言は、堕落した指導者たちに対して、国民が抱く失望と悲しみを象徴する哀歌を捧げています。参考：新解約2017版 エゼキエル書19章",
    "sources": [
      "エゼキエル書 19章"
    ],
    "tags": ["旧約聖書 / エゼキエル書"]
  },
  {
    "question": "【エゼキエル書20章-1】エゼキエル書20章は、主に何について語られているか？",
    "choices": ["イスラエルの反逆", "国家の繁栄", "異邦との同盟", "農業の豊穣"],
    "answer": "イスラエルの反逆",
    "explanation": "この章は、過去から続くイスラエルの反逆の歴史と、その罪に対する神の怒りを語っています。参考：新解約2017版 エゼキエル書20章",
    "sources": [
      "エゼキエル書 20章"
    ],
    "tags": ["旧約聖書 / エゼキエル書"]
  },
  {
    "question": "【エゼキエル書20章-2】エゼキエル書20章において、民の行いはどのように評価されているか？",
    "choices": ["神への背信", "正直さと忠誠", "信仰の献身", "道徳的高潔さ"],
    "answer": "神への背信",
    "explanation": "民が繰り返す反逆は、神に対する明確な背信行為とみなされ、厳しい裁きが告げられます。参考：新解約2017版 エゼキエル書20章",
    "sources": [
      "エゼキエル書 20章"
    ],
    "tags": ["旧約聖書 / エゼキエル書"]
  },
  {
    "question": "【エゼキエル書20章-3】エゼキエル書20章の預言は、何に対する神の怒りを示しているか？",
    "choices": ["絶え間ない反逆", "経済の発展", "宗教の繁栄", "平和な統治"],
    "answer": "絶え間ない反逆",
    "explanation": "預言は、イスラエルの民が絶えず神に背く反逆を続けた結果として、怒りが募っている状況を示しています。参考：新解約2017版 エゼキエル書20章",
    "sources": [
      "エゼキエル書 20章"
    ],
    "tags": ["旧約聖書 / エゼキエル書"]
  },
  {
    "question": "【エゼキエル書20章-4】エゼキエル書20章は、イスラエルの歴史においてどのような出来事を再評価しているか？",
    "choices": ["反逆とその罰", "豊かな実り", "文化の黄金時代", "民族の統一"],
    "answer": "反逆とその罰",
    "explanation": "歴史の記述は、民の継続的な反逆とそれに伴う厳しい罰を再評価するものです。参考：新解約2017版 エゼキエル書20章",
    "sources": [
      "エゼキエル書 20章"
    ],
    "tags": ["旧約聖書 / エゼキエル書"]
  },
  {
    "question": "【エゼキエル書20章-5】エゼキエル書20章における民への警告は、どのような態度を求めているか？",
    "choices": ["悔い改めと忠誠", "さらにの反逆", "経済の追求", "戦争の宣言"],
    "answer": "悔い改めと忠誠",
    "explanation": "預言は、民に対して悔い改め、神に忠実に従う態度を求めるよう促しています。参考：新解約2017版 エゼキエル書20章",
    "sources": [
      "エゼキエル書 20章"
    ],
    "tags": ["旧約聖書 / エゼキエル書"]
  },
  {
    "question": "【エゼキエル書20章-6】エゼキエル書20章のメッセージは、何を促すために語られているか？",
    "choices": ["神への誠実な戻り", "政治的野心", "文化の模倣", "経済の繁栄"],
    "answer": "神への誠実な戻り",
    "explanation": "預言は、民が神に誠実に戻ることの重要性を強調するメッセージです。参考：新解約2017版 エゼキエル書20章",
    "sources": [
      "エゼキエル書 20章"
    ],
    "tags": ["旧約聖書 / エゼキエル書"]
  },
  {
    "question": "【エゼキエル書20章-7】エゼキエル書20章は、何がイスラエルにもたらす災いと示唆しているか？",
    "choices": ["不従順な反逆", "宗教の献身", "富の泉", "共同体の団結"],
    "answer": "不従順な反逆",
    "explanation": "預言は、民が従わないことがさらなる災いを呼び起こすと警告しています。参考：新解約2017版 エゼキエル書20章",
    "sources": [
      "エゼキエル書 20章"
    ],
    "tags": ["旧約聖書 / エゼキエル書"]
  },
  {
    "question": "【エゼキエル書20章-8】エゼキエル書20章は、歴史的出来事を通してどのような教訓を伝えているとされるか？",
    "choices": ["背信には必ず罰がある", "富は永遠の幸福の鍵", "権力は無敵である", "繁栄は実力主義である"],
    "answer": "背信には必ず罰がある",
    "explanation": "この章は、背信行為が必ず神の裁きを招くという厳しい教訓を伝えています。参考：新解約2017版 エゼキエル書20章",
    "sources": [
      "エゼキエル書 20章"
    ],
    "tags": ["旧約聖書 / エゼキエル書"]
  },
  {
    "question": "【エゼキエル書21章-1】エゼキエル書21章は、主に何についての預言か？",
    "choices": ["近い将来の破滅", "新たな契約", "経済の繁栄", "宗教的復興"],
    "answer": "近い将来の破滅",
    "explanation": "21章は、迫り来る破滅の予兆を预言し、神の怒りが具体的に現れる時期を示唆しています。参考：新解約2017版 エゼキエル書21章",
    "sources": [
      "エゼキエル書 21章"
    ],
    "tags": ["旧約聖書 / エゼキエル書"]
  },
  {
    "question": "【エゼキエル書21章-2】エゼキエル書21章における裁きの預告は、何に対するものか？",
    "choices": ["民の罪と不義", "異邦人への祝福", "知恵の伝承", "国家の拡大"],
    "answer": "民の罪と不義",
    "explanation": "神の裁きは、民が犯した罪深い行為と不義に対する報いとして下されると預言されています。参考：新解約2017版 エゼキエル書21章",
    "sources": [
      "エゼキエル書 21章"
    ],
    "tags": ["旧約聖書 / エゼキエル書"]
  },
  {
    "question": "【エゼキエル書21章-3】エゼキエル書21章において、神の声は何を確約しているか？",
    "choices": ["容赦ない裁き", "平和な再生", "経済的繁栄", "宗教の更新"],
    "answer": "容赦ない裁き",
    "explanation": "神の声は、どんな弁解も許さない容赦のない裁きが下ると断言しています。参考：新解約2017版 エゼキエル書21章",
    "sources": [
      "エゼキエル書 21章"
    ],
    "tags": ["旧約聖書 / エゼキエル書"]
  },
  {
    "question": "【エゼキエル書21章-4】エゼキエル書21章の預言は、どのような未来を示唆しているか？",
    "choices": ["破壊と混乱の時代", "黄金の時代", "政治の安定", "精神的覚醒"],
    "answer": "破壊と混乱の時代",
    "explanation": "預言は、未来において破壊と混乱が支配する時代が訪れると強く示しています。参考：新解約2017版 エゼキエル書21章",
    "sources": [
      "エゼキエル書 21章"
    ],
    "tags": ["旧約聖書 / エゼキエル書"]
  },
  {
    "question": "【エゼキエル書21章-5】エゼキエル書21章において、神の警告は、何の結果としての破滅を予告しているか？",
    "choices": ["罪深い行いへの報い", "成功への道", "繁栄の連鎖", "神の慈悲"],
    "answer": "罪深い行いへの報い",
    "explanation": "民の罪深い行いに対する報いとして、破滅という結果が必然的に下されるとされます。参考：新解約2017版 エゼキエル書21章",
    "sources": [
      "エゼキエル書 21章"
    ],
    "tags": ["旧約聖書 / エゼキエル書"]
  },
  {
    "question": "【エゼキエル書21章-6】エゼキエル書21章における裁きは、何の象徴と解釈されるか？",
    "choices": ["避けられない神の怒り", "預言者の栄光", "民の幸運", "偽りの救済"],
    "answer": "避けられない神の怒り",
    "explanation": "裁きは、神の怒りが如何にして回避不能であるかを象徴的に示しています。参考：新解約2017版 エゼキエル書21章",
    "sources": [
      "エゼキエル書 21章"
    ],
    "tags": ["旧約聖書 / エゼキエル書"]
  },
  {
    "question": "【エゼキエル書21章-7】エゼキエル書21章に預言された出来事は、どのようにして文明に影響を与えるとされるか？",
    "choices": ["全滅と混沌", "技術の発展", "文化の統一", "経済の拡大"],
    "answer": "全滅と混沌",
    "explanation": "預言は、全体としての社会が全滅し、混沌状態に陥る未来を予告しています。参考：新解約2017版 エゼキエル書21章",
    "sources": [
      "エゼキエル書 21章"
    ],
    "tags": ["旧約聖書 / エゼキエル書"]
  },
  {
    "question": "【エゼキエル書21章-8】エゼキエル書21章は、最終的に人々に何を警告しているか？",
    "choices": ["罪の代償は必ず払われる", "富は永遠の幸福", "権力は神聖", "成功は保証される"],
    "answer": "罪の代償は必ず払われる",
    "explanation": "この章は、いかなる罪も最終的には神の裁きの下で代償を払わなければならないと警告しています。参考：新解約2017版 エゼキエル書21章",
    "sources": [
      "エゼキエル書 21章"
    ],
    "tags": ["旧約聖書 / エゼキエル書"]
  },
  {
    "question": "【エゼキエル書22章-1】エゼキエル書22章では、エルサレムのどの罪が特に糾弾されているか？",
    "choices": ["社会的不正と堕落", "経済の発展", "宗教の統一", "農業の繁栄"],
    "answer": "社会的不正と堕落",
    "explanation": "エルサレムが陥った社会的不正と道徳の堕落が、神の裁きの根拠として厳しく非難されています。参考：新解約2017版 エゼキエル書22章",
    "sources": [
      "エゼキエル書 22章"
    ],
    "tags": ["旧約聖書 / エゼキエル書"]
  },
  {
    "question": "【エゼキエル書22章-2】エゼキエル書22章の預言は、何に対する罰を含意しているか？",
    "choices": ["道徳の退廃", "文化の多様性", "国家の統一", "豊かな自然"],
    "answer": "道徳の退廃",
    "explanation": "預言は、道徳的に退廃した状態が、神の罰の対象となることを明示しています。参考：新解約2017版 エゼキエル書22章",
    "sources": [
      "エゼキエル書 22章"
    ],
    "tags": ["旧約聖書 / エゼキエル書"]
  },
  {
    "question": "【エゼキエル書22章-3】エゼキエル書22章において、都市の堕落は何の象徴とされているか？",
    "choices": ["罪深い行いの結果", "社会の革新", "民の繁栄", "宗教の栄光"],
    "answer": "罪深い行いの結果",
    "explanation": "エルサレムの堕落は、民が犯した罪の結果としての象徴とされています。参考：新解約2017版 エゼキエル書22章",
    "sources": [
      "エゼキエル書 22章"
    ],
    "tags": ["旧約聖書 / エゼキエル書"]
  },
  {
    "question": "【エゼキエル書22章-4】エゼキエル書22章は、エルサレムを裁く理由として何を挙げているか？",
    "choices": ["不正行為と偶像崇拝", "経済的成功", "戦の勝利", "文化的交流"],
    "answer": "不正行為と偶像崇拝",
    "explanation": "エルサレムの罪深さ、特に不正行為と偶像崇拝が神の裁きを招く主な理由とされています。参考：新解約2017版 エゼキエル書22章",
    "sources": [
      "エゼキエル書 22章"
    ],
    "tags": ["旧約聖書 / エゼキエル書"]
  },
  {
    "question": "【エゼキエル書22章-5】エゼキエル書22章における裁きは、何を戒めるために行われるか？",
    "choices": ["道徳的敗北", "技術の進化", "宗教の刷新", "国際的協力"],
    "answer": "道徳的敗北",
    "explanation": "裁きは、神に背いた結果としての道徳的敗北を戒め、回復を促すために述べられています。参考：新解約2017版 エゼキエル書22章",
    "sources": [
      "エゼキエル書 22章"
    ],
    "tags": ["旧約聖書 / エゼキエル書"]
  },
  {
    "question": "【エゼキエル書22章-6】エゼキエル書22章が描くエルサレムの現状は、どのような悲劇を象徴しているか？",
    "choices": ["民の罪の蓄積", "自然の災害", "経済の崩壊", "政治の混乱"],
    "answer": "民の罪の蓄積",
    "explanation": "民の罪が長く蓄積された結果として、エルサレムは悲劇的な状態にあると描かれています。参考：新解約2017版 エゼキエル書22章",
    "sources": [
      "エゼキエル書 22章"
    ],
    "tags": ["旧約聖書 / エゼキエル書"]
  },
  {
    "question": "【エゼキエル書22章-7】エゼキエル書22章の神の裁きは、何に対する怒りの表現か？",
    "choices": ["堕落した行為", "正義の憎悪", "知識の追求", "文化の進歩"],
    "answer": "堕落した行為",
    "explanation": "神の怒りは、特に堕落した行為に向けられ、その結果として裁きが下されるとされています。参考：新解約2017版 エゼキエル書22章",
    "sources": [
      "エゼキエル書 22章"
    ],
    "tags": ["旧約聖書 / エゼキエル書"]
  },
  {
    "question": "【エゼキエル書22章-8】エゼキエル書22章において、エルサレムの滅びの予兆として示されるものは何か？",
    "choices": ["道徳的破綻", "国の繁栄", "宗教的刷新", "経済の成功"],
    "answer": "道徳的破綻",
    "explanation": "道徳の破綻は、エルサレムの滅びの予兆として、不可避の悲劇を示唆しています。参考：新解約2017版 エゼキエル書22章",
    "sources": [
      "エゼキエル書 22章"
    ],
    "tags": ["旧約聖書 / エゼキエル書"]
  },
  {
    "question": "【エゼキエル書23章-1】エゼキエル書23章では、二人の女性のたとえは何を象徴しているか？",
    "choices": ["エルサレムとシオンの不実", "異邦の祝祭", "繁栄する都市", "伝統の美徳"],
    "answer": "エルサレムとシオンの不実",
    "explanation": "たとえ話では、二人の女性がエルサレムとシオンの不実を象徴し、神への背信を批判しています。参考：新解約2017版 エゼキエル書23章",
    "sources": [
      "エゼキエル書 23章"
    ],
    "tags": ["旧約聖書 / エゼキエル書"]
  },
  {
    "question": "【エゼキエル書23章-2】エゼキエル書23章のたとえは、主に何を批判しているか？",
    "choices": ["宗教的な背信", "正しい礼拝", "文化的誇り", "善良な行い"],
    "answer": "宗教的な背信",
    "explanation": "たとえは、神に対する宗教的な忠誠が失われている現状を厳しく批判するものです。参考：新解約2017版 エゼキエル書23章",
    "sources": [
      "エゼキエル書 23章"
    ],
    "tags": ["旧約聖書 / エゼキエル書"]
  },
  {
    "question": "【エゼキエル書23章-3】エゼキエル書23章において、たとえ話は何に対する警告とされているか？",
    "choices": ["不義な愛慕行為", "献身的な愛", "家族の絆", "国家の結束"],
    "answer": "不義な愛慕行為",
    "explanation": "たとえは、神に逆らうような不義な情熱を持った愛慕行為に対する警告として用いられています。参考：新解約2017版 エゼキエル書23章",
    "sources": [
      "エゼキエル書 23章"
    ],
    "tags": ["旧約聖書 / エゼキエル書"]
  },
  {
    "question": "【エゼキエル書23章-4】エゼキエル書23章は、どのような行為を非難しているか？",
    "choices": ["神への不忠実な交わり", "正しい儀式", "民への愛情", "伝統の維持"],
    "answer": "神への不忠実な交わり",
    "explanation": "預言は、神への忠実さを欠いた不正な交わりを非難し、民に警告を発しています。参考：新解約2017版 エゼキエル書23章",
    "sources": [
      "エゼキエル書 23章"
    ],
    "tags": ["旧約聖書 / エゼキエル書"]
  },
  {
    "question": "【エゼキエル書23章-5】エゼキエル書23章に描かれる女性たちは何を象徴しているか？",
    "choices": ["偽りの情熱と堕落", "聖なる美徳", "慈悲深い心", "勇敢な精神"],
    "answer": "偽りの情熱と堕落",
    "explanation": "寓話で描かれる女性たちは、神への不忠実さとそれに伴う堕落を象徴しています。参考：新解約2017版 エゼキエル書23章",
    "sources": [
      "エゼキエル書 23章"
    ],
    "tags": ["旧約聖書 / エゼキエル書"]
  },
  {
    "question": "【エゼキエル書23章-6】エゼキエル書23章のたとえ話は、どのような国家の道徳状態を暗示しているか？",
    "choices": ["堕落と裏切り", "繁栄と統合", "文化の再興", "宗教の改革"],
    "answer": "堕落と裏切り",
    "explanation": "たとえは、国家全体が堕落し、互いに裏切りあう状態を象徴的に表現しています。参考：新解約2017版 エゼキエル書23章",
    "sources": [
      "エゼキエル書 23章"
    ],
    "tags": ["旧約聖書 / エゼキエル書"]
  },
  {
    "question": "【エゼキエル書23章-7】エゼキエル書23章のたとえは、何を戒めるためのものであったか？",
    "choices": ["神に対する不誠実な態度", "経済の怠惰", "政治の無関心", "伝統の厳守"],
    "answer": "神に対する不誠実な態度",
    "explanation": "預言は、神に対して不誠実である行為を戒め、正しい信仰に立ち返ることを促しています。参考：新解約2017版 エゼキエル書23章",
    "sources": [
      "エゼキエル書 23章"
    ],
    "tags": ["旧約聖書 / エゼキエル書"]
  },
  {
    "question": "【エゼキエル書23章-8】エゼキエル書23章は、最終的に何を予告しているか？",
    "choices": ["神の激しい裁きと破壊", "国家の再建", "文化の刷新", "祝福の復活"],
    "answer": "神の激しい裁きと破壊",
    "explanation": "預言は、神の激しい裁きが差し迫っていること、そして破壊が避けられない運命であると警告しています。参考：新解約2017版 エゼキエル書23章",
    "sources": [
      "エゼキエル書 23章"
    ],
    "tags": ["旧約聖書 / エゼキエル書"]
  },
  {
    "question": "【エゼキエル書24章-1】エゼキエル書24章では、預言者の身近な出来事が象徴的に描かれているが、それは何を示しているか？",
    "choices": ["迫り来る破局の予兆", "新たな繁栄", "楽園の再現", "宗教の刷新"],
    "answer": "迫り来る破局の予兆",
    "explanation": "預言者の愛する者の死が象徴的に描かれ、迫りくる全体的な破局の予兆とされています。参考：新解約2017版 エゼキエル書24章",
    "sources": [
      "エゼキエル書 24章"
    ],
    "tags": ["旧約聖書 / エゼキエル書"]
  },
  {
    "question": "【エゼキエル書24章-2】エゼキエル書24章で象徴的に用いられた沸騰する器は、何を意味しているか？",
    "choices": ["絶え間ない苦難と怒り", "豊かな恵み", "平和な調和", "希望の光"],
    "answer": "絶え間ない苦難と怒り",
    "explanation": "沸騰する器は、神の怒りと、それに伴う絶え間ない苦難を象徴する表現です。参考：新解約2017版 エゼキエル書24章",
    "sources": [
      "エゼキエル書 24章"
    ],
    "tags": ["旧約聖書 / エゼキエル書"]
  },
  {
    "question": "【エゼキエル書24章-3】エゼキエル書24章における愛する者の死は、何を暗示しているとされているか？",
    "choices": ["神の裁きの到来", "個人的悲哀のみ", "自然の摂理", "新たな始まり"],
    "answer": "神の裁きの到来",
    "explanation": "愛する者の死は、神の裁きが個人的にも国全体にも訪れる前兆とされています。参考：新解約2017版 エゼキエル書24章",
    "sources": [
      "エゼキエル書 24章"
    ],
    "tags": ["旧約聖書 / エゼキエル書"]
  },
  {
    "question": "【エゼキエル書24章-4】エゼキエル書24章は、個人的悲劇を通して何を伝えようとしているか？",
    "choices": ["国家全体の破滅", "家族の温かさ", "個人の勝利", "自然の美しさ"],
    "answer": "国家全体の破滅",
    "explanation": "個人の悲劇は、国家全体が破滅するという神の警告の象徴とされています。参考：新解約2017版 エゼキエル書24章",
    "sources": [
      "エゼキエル書 24章"
    ],
    "tags": ["旧約聖書 / エゼキエル書"]
  },
  {
    "question": "【エゼキエル書24章-5】エゼキエル書24章に見られる象徴的表現は、何の前触れとされているか？",
    "choices": ["総体的な神の裁き", "政治改革", "経済の繁栄", "宗教的統一"],
    "answer": "総体的な神の裁き",
    "explanation": "象徴的表現は、全体に及ぶ神の裁きが間近に迫っていることを告げる前触れです。参考：新解約2017版 エゼキエル書24章",
    "sources": [
      "エゼキエル書 24章"
    ],
    "tags": ["旧約聖書 / エゼキエル書"]
  },
  {
    "question": "【エゼキエル書24章-6】エゼキエル書24章の預言は、どのような悲劇的結果を示唆しているか？",
    "choices": ["全体の滅亡と苦難", "軽微な変動", "短期的な混乱", "個人の変革"],
    "answer": "全体の滅亡と苦難",
    "explanation": "預言は、国家全体が滅び、苦難に満ちる結果を迎えることを示唆しています。参考：新解約2017版 エゼキエル書24章",
    "sources": [
      "エゼキエル書 24章"
    ],
    "tags": ["旧約聖書 / エゼキエル書"]
  },
  {
    "question": "【エゼキエル書24章-7】エゼキエル書24章における熱い器は、どのような感情を象徴しているか？",
    "choices": ["神の激しい怒り", "優しさ", "慈悲", "希望"],
    "answer": "神の激しい怒り",
    "explanation": "熱い器は、神が怒りを燃やす様子を象徴し、その強烈な感情を表現しています。参考：新解約2017版 エゼキエル書24章",
    "sources": [
      "エゼキエル書 24章"
    ],
    "tags": ["旧約聖書 / エゼキエル書"]
  },
  {
    "question": "【エゼキエル書24章-8】エゼキエル書24章で表現される預言は、何を避けられない未来として預言しているか？",
    "choices": ["全体的な破滅と悲劇", "経済の成功", "新たな繁栄", "宗教的喜び"],
    "answer": "全体的な破滅と悲劇",
    "explanation": "預言は、経済や政治ではなく、神の裁きによる全ての破滅が避けられない未来であることを警告しています。参考：新解約2017版 エゼキエル書24章",
    "sources": [
      "エゼキエル書 24章"
    ],
    "tags": ["旧約聖書 / エゼキエル書"]
  },
  {
    "question": "【エゼキエル書25章-1】エゼキエル書25章は、どの国々に対する預言を含んでいるか？",
    "choices": ["隣国諸国（アモン、モアブ、エドムなど）", "エジプトとメソポタミア", "ローマとギリシャ", "中国とインド"],
    "answer": "隣国諸国（アモン、モアブ、エドムなど）",
    "explanation": "この章は、イスラエルの隣国とされる国々に対する神の裁きと罰を預言しています。参考：新解約2017版 エゼキエル書25章",
    "sources": [
      "エゼキエル書 25章"
    ],
    "tags": ["旧約聖書 / エゼキエル書"]
  },
  {
    "question": "【エゼキエル書25章-2】エゼキエル書25章の預言は、外国に対してどのような裁きを示唆しているか？",
    "choices": ["神の怒りによる破滅", "政治的提携", "経済的繁栄", "文化的交流"],
    "answer": "神の怒りによる破滅",
    "explanation": "預言は、これらの国々が神の怒りに触れ、破滅へと導かれると示唆しています。参考：新解約2017版 エゼキエル書25章",
    "sources": [
      "エゼキエル書 25章"
    ],
    "tags": ["旧約聖書 / エゼキエル書"]
  },
  {
    "question": "【エゼキエル書25章-3】エゼキエル書25章において、神の裁きは、民のどの性質への報いとして描かれているか？",
    "choices": ["民の傲慢", "宗教の忠誠", "経済の博愛", "人道的行為"],
    "answer": "民の傲慢",
    "explanation": "預言は、傲慢な態度が神の怒りを買い、厳しい裁きの対象となると述べています。参考：新解約2017版 エゼキエル書25章",
    "sources": [
      "エゼキエル書 25章"
    ],
    "tags": ["旧約聖書 / エゼキエル書"]
  },
  {
    "question": "【エゼキエル書25章-4】エゼキエル書25章は、どのような行動に対して神の怒りを宣告しているか？",
    "choices": ["敵対的で不敬な態度", "外交的交渉", "友好的交流", "平和の追求"],
    "answer": "敵対的で不敬な態度",
    "explanation": "預言は、敵対的かつ不敬な態度が神の裁きを引き起こすと断じています。参考：新解約2017版 エゼキエル書25章",
    "sources": [
      "エゼキエル書 25章"
    ],
    "tags": ["旧約聖書 / エゼキエル書"]
  },
  {
    "question": "【エゼキエル書25章-5】エゼキエル書25章における外国諸国への預言は、彼らの何を非難しているか？",
    "choices": ["高慢と暴虐", "文化の多様性", "経済の活性化", "宗教の寛容"],
    "answer": "高慢と暴虐",
    "explanation": "預言は、外国の国々が持つ高慢さと暴虐な行動を激しく非難しています。参考：新解約2017版 エゼキエル書25章",
    "sources": [
      "エゼキエル書 25章"
    ],
    "tags": ["旧約聖書 / エゼキエル書"]
  },
  {
    "question": "【エゼキエル書25章-6】エゼキエル書25章は、どのような態度が神の裁きに繋がると示しているか？",
    "choices": ["傲慢な心", "謙虚な心", "慈悲深い行動", "知恵の追求"],
    "answer": "傲慢な心",
    "explanation": "傲慢さが神の怒りを引き起こし、予期せぬ厳しい罰を招くと預言されています。参考：新解約2017版 エゼキエル書25章",
    "sources": [
      "エゼキエル書 25章"
    ],
    "tags": ["旧約聖書 / エゼキエル書"]
  },
  {
    "question": "【エゼキエル書25章-7】エゼキエル書25章で宣告される罰は、何を通じて現れるとされるか？",
    "choices": ["戦争と破壊", "平和な協定", "豊かな収穫", "文化の交流"],
    "answer": "戦争と破壊",
    "explanation": "預言は、罰が戦争と破壊という形で現れることを強調しています。参考：新解約2017版 エゼキエル書25章",
    "sources": [
      "エゼキエル書 25章"
    ],
    "tags": ["旧約聖書 / エゼキエル書"]
  },
  {
    "question": "【エゼキエル書25章-8】エゼキエル書25章は、外国諸国に対する神の裁きを何と定義しているか？",
    "choices": ["永続的な罰", "一時的な懲罰", "経済的制裁のみ", "道徳的励まし"],
    "answer": "永続的な罰",
    "explanation": "預言は、外国国に対する裁きが継続的かつ永続的なものであると定めています。参考：新解約2017版 エゼキエル書25章",
    "sources": [
      "エゼキエル書 25章"
    ],
    "tags": ["旧約聖書 / エゼキエル書"]
  },
  {
    "question": "【エゼキエル書26章-1】エゼキエル書26章は、主にどの都市に対する預言か？",
    "choices": ["ティルス", "エルサレム", "バビロン", "アレクサンドリア"],
    "answer": "ティルス",
    "explanation": "26章は、特に商業都市ティルスに対する神の裁きを預言しています。参考：新解約2017版 エゼキエル書26章",
    "sources": [
      "エゼキエル書 26章"
    ],
    "tags": ["旧約聖書 / エゼキエル書"]
  },
  {
    "question": "【エゼキエル書26章-2】エゼキエル書26章では、ティルスに対して預言された災いは何か？",
    "choices": ["海による破壊", "大地震", "火災", "疫病"],
    "answer": "海による破壊",
    "explanation": "預言において、ティルスは海の暴力によって破壊されるとされています。参考：新解約2017版 エゼキエル書26章",
    "sources": [
      "エゼキエル書 26章"
    ],
    "tags": ["旧約聖書 / エゼキエル書"]
  },
  {
    "question": "【エゼキエル書26章-3】エゼキエル書26章の預言は、ティルスの何を批判しているか？",
    "choices": ["傲慢な繁栄", "宗教的謙虚さ", "文化の多様性", "経済の衰退"],
    "answer": "傲慢な繁栄",
    "explanation": "預言は、ティルスが過度な繁栄に溺れ、傲慢になったことを厳しく批判しています。参考：新解約2017版 エゼキエル書26章",
    "sources": [
      "エゼキエル書 26章"
    ],
    "tags": ["旧約聖書 / エゼキエル書"]
  },
  {
    "question": "【エゼキエル書26章-4】エゼキエル書26章における裁きは、どのような性質を帯びているか？",
    "choices": ["完全な破壊", "限定的な制裁", "一時的な混乱", "象徴的な罰"],
    "answer": "完全な破壊",
    "explanation": "裁きは、ティルスに対して、完全で容赦なき破壊が下るとされたものです。参考：新解約2017版 エゼキエル書26章",
    "sources": [
      "エゼキエル書 26章"
    ],
    "tags": ["旧約聖書 / エゼキエル書"]
  },
  {
    "question": "【エゼキエル書26章-5】エゼキエル書26章は、ティルスの未来についてどのような結末を予告しているか？",
    "choices": ["廃墟と荒廃", "栄光の復活", "文化の革新", "経済の繁栄"],
    "answer": "廃墟と荒廃",
    "explanation": "預言は、ティルスが廃墟と荒廃に包まれる最終的な結末を迎えることを示しています。参考：新解約2017版 エゼキエル書26章",
    "sources": [
      "エゼキエル書 26章"
    ],
    "tags": ["旧約聖書 / エゼキエル書"]
  },
  {
    "question": "【エゼキエル書26章-6】エゼキエル書26章に描かれるティルスは、何により滅ぼされるとされるか？",
    "choices": ["大波と海の暴力", "火と硫黄", "雷と嵐", "疫病と飢饉"],
    "answer": "大波と海の暴力",
    "explanation": "赦しき破壊は、特に大波や海の暴力によってもたらされると命じられています。参考：新解約2017版 エゼキエル書26章",
    "sources": [
      "エゼキエル書 26章"
    ],
    "tags": ["旧約聖書 / エゼキエル書"]
  },
  {
    "question": "【エゼキエル書26章-7】エゼキエル書26章での預言の主な目的は何か？",
    "choices": ["ティルスの高慢に対する罰", "民の祝福", "新たな同盟", "文化の振興"],
    "answer": "ティルスの高慢に対する罰",
    "explanation": "預言は、ティルスがその高慢さゆえに神の罰を受ける運命にあることを明示しています。参考：新解約2017版 エゼキエル書26章",
    "sources": [
      "エゼキエル書 26章"
    ],
    "tags": ["旧約聖書 / エゼキエル書"]
  },
  {
    "question": "【エゼキエル書26章-8】エゼキエル書26章は、ティルスに対してどのような結末を約束しているか？",
    "choices": ["永続的な荒廃", "短期の混乱", "繁栄の回復", "経済の成長"],
    "answer": "永続的な荒廃",
    "explanation": "預言は、ティルスが永続的に荒廃し、再生の兆しが見えない状態に陥ることを示唆しています。参考：新解約2017版 エゼキエル書26章",
    "sources": [
      "エゼキエル書 26章"
    ],
    "tags": ["旧約聖書 / エゼキエル書"]
  },
  {
    "question": "【エゼキエル書27章-1】エゼキエル書27章は、どの都市に捧げられた哀歌か？",
    "choices": ["ティルス", "エルサレム", "バビロン", "ペルシャ"],
    "answer": "ティルス",
    "explanation": "27章は、繁栄していたティルスの没落と、その栄光の衰退を哀悼するために詠まれたものです。参考：新解約2017版 エゼキエル書27章",
    "sources": [
      "エゼキエル書 27章"
    ],
    "tags": ["旧約聖書 / エゼキエル書"]
  },
  {
    "question": "【エゼキエル書27章-2】エゼキエル書27章における哀歌は、何を象徴しているか？",
    "choices": ["滅びゆく栄華", "神の慈悲", "民の繁栄", "戦争の勝利"],
    "answer": "滅びゆく栄華",
    "explanation": "詩的な哀歌は、かつての栄光が失われる悲劇を象徴し、ティルスの滅びを嘆いています。参考：新解約2017版 エゼキエル書27章",
    "sources": [
      "エゼキエル書 27章"
    ],
    "tags": ["旧約聖書 / エゼキエル書"]
  },
  {
    "question": "【エゼキエル書27章-3】エゼキエル書27章では、どのような要素を盛り込んだ詩的表現が特徴とされているか？",
    "choices": ["豊かな交易と港の栄光", "平和な農村風景", "軍事の華麗", "宗教儀式の厳粛さ"],
    "answer": "豊かな交易と港の栄光",
    "explanation": "詩は、ティルスがかつて繁栄した交易と港を中心とした栄光を讃えていますが、同時にその没落が描かれます。参考：新解約2017版 エゼキエル書27章",
    "sources": [
      "エゼキエル書 27章"
    ],
    "tags": ["旧約聖書 / エゼキエル書"]
  },
  {
    "question": "【エゼキエル書27章-4】エゼキエル書27章に見られる哀歌は、何を悔やむために詠まれているか？",
    "choices": ["ティルスの没落", "国家の拡大", "宗教の統一", "文化の融合"],
    "answer": "ティルスの没落",
    "explanation": "哀歌は、かつて輝いていたティルスが没落し、その栄誉を失ったことを深く悔やんでいます。参考：新解約2017版 エゼキエル書27章",
    "sources": [
      "エゼキエル書 27章"
    ],
    "tags": ["旧約聖書 / エゼキエル書"]
  },
  {
    "question": "【エゼキエル書27章-5】エゼキエル書27章での都市の運命は、どのように描かれているか？",
    "choices": ["栄光の消滅と荒廃", "永遠の繁栄", "宗教的栄光", "民の祝祭"],
    "answer": "栄光の消滅と荒廃",
    "explanation": "預言は、ティルスのかつての栄光が完全に消え、荒廃する運命にあることを嘆くものです。参考：新解約2017版 エゼキエル書27章",
    "sources": [
      "エゼキエル書 27章"
    ],
    "tags": ["旧約聖書 / エゼキエル書"]
  },
  {
    "question": "【エゼキエル書27章-6】エゼキエル書27章において、ティルスの栄誉が失われる原因は何か？",
    "choices": ["傲慢と不義", "正義の追求", "謙虚な外交", "文化の進歩"],
    "answer": "傲慢と不義",
    "explanation": "ティルスは、その傲慢さと不義により、かつての栄誉を失い、没落の道を辿るとされています。参考：新解約2017版 エゼキエル書27章",
    "sources": [
      "エゼキエル書 27章"
    ],
    "tags": ["旧約聖書 / エゼキエル書"]
  },
  {
    "question": "【エゼキエル書27章-7】エゼキエル書27章の詩的な哀歌は、何に対する警告としての役割を果たしているか？",
    "choices": ["高慢な繁栄の終焉", "技術の進展", "宗教の隆盛", "文学の革新"],
    "answer": "高慢な繁栄の終焉",
    "explanation": "哀歌は、かつての高慢な栄光が終焉し、警告としての意味を帯びるものです。参考：新解約2017版 エゼキエル書27章",
    "sources": [
      "エゼキエル書 27章"
    ],
    "tags": ["旧約聖書 / エゼキエル書"]
  },
  {
    "question": "【エゼキエル書27章-8】エゼキエル書27章は、ティルスに対するどのような感情を表現しているか？",
    "choices": ["深い悲哀と失望", "喜びと祝福", "期待と興奮", "冷静な分析"],
    "answer": "深い悲哀と失望",
    "explanation": "詩は、かつての栄光が没したティルスに対する、深い悲哀と失望の感情を表現します。参考：新解約2017版 エゼキエル書27章",
    "sources": [
      "エゼキエル書 27章"
    ],
    "tags": ["旧約聖書 / エゼキエル書"]
  },
  {
    "question": "【エゼキエル書28章-1】エゼキエル書28章は、主にどの人物に対する預言か？",
    "choices": ["ティルスの王", "エルサレムの指導者", "バビロンの侍従", "モアブの預言者"],
    "answer": "ティルスの王",
    "explanation": "28章は、ティルスの王に対する預言として、その誇大な性質と傲慢さが問題視されています。参考：新解約2017版 エゼキエル書28章",
    "sources": [
      "エゼキエル書 28章"
    ],
    "tags": ["旧約聖書 / エゼキエル書"]
  },
  {
    "question": "【エゼキエル書28章-2】エゼキエル書28章において、ティルスの王は何で象徴的に描かれているか？",
    "choices": ["美しく誇大な存在", "謙虚な農民", "正直な商人", "勇敢な戦士"],
    "answer": "美しく誇大な存在",
    "explanation": "預言は、ティルスの王がその容姿や力を誇示するあまり、誇大であることを非難するものです。参考：新解約2017版 エゼキエル書28章",
    "sources": [
      "エゼキエル書 28章"
    ],
    "tags": ["旧約聖書 / エゼキエル書"]
  },
  {
    "question": "【エゼキエル書28章-3】エゼキエル書28章は、ティルスの王のどの性質を批判しているか？",
    "choices": ["高慢と自己陶酔", "謙虚さ", "慈悲深さ", "知識の追求"],
    "answer": "高慢と自己陶酔",
    "explanation": "ティルスの王は、自己陶酔と高慢な態度が目立ち、これが神の裁きの対象とされています。参考：新解約2017版 エゼキエル書28章",
    "sources": [
      "エゼキエル書 28章"
    ],
    "tags": ["旧約聖書 / エゼキエル書"]
  },
  {
    "question": "【エゼキエル書28章-4】エゼキエル書28章における預言は、ティルスの王にどのような結末を提示しているか？",
    "choices": ["滅びと屈辱", "栄光の再興", "平和な統治", "宗教的栄誉"],
    "answer": "滅びと屈辱",
    "explanation": "預言は、誇り高いティルスの王が最終的に滅び、屈辱を味わう運命にあると断じています。参考：新解約2017版 エゼキエル書28章",
    "sources": [
      "エゼキエル書 28章"
    ],
    "tags": ["旧約聖書 / エゼキエル書"]
  },
  {
    "question": "【エゼキエル書28章-5】エゼキエル書28章は、ティルスの王の権勢をどのように評価しているか？",
    "choices": ["過度な誇示", "慎ましさ", "公正な判断", "協調性"],
    "answer": "過度な誇示",
    "explanation": "権勢は、過度な誇示と自己陶酔によって、神の前で恥をかくものと評価されています。参考：新解約2017版 エゼキエル書28章",
    "sources": [
      "エゼキエル書 28章"
    ],
    "tags": ["旧約聖書 / エゼキエル書"]
  },
  {
    "question": "【エゼキエル書28章-6】エゼキエル書28章において、誇大な自己評価は何を招くとされるか？",
    "choices": ["神の激しい裁き", "国際的な称賛", "民の尊敬", "豊かな祝福"],
    "answer": "神の激しい裁き",
    "explanation": "過度の誇示は、最終的に神の激しい裁きという形で報いを受けると預言されています。参考：新解約2017版 エゼキエル書28章",
    "sources": [
      "エゼキエル書 28章"
    ],
    "tags": ["旧約聖書 / エゼキエル書"]
  },
  {
    "question": "【エゼキエル書28章-7】エゼキエル書28章の預言は、どのような道徳的メッセージを伝えているか？",
    "choices": ["謙虚であるべき", "権力の追求", "富の蓄積", "軍事の栄光"],
    "answer": "謙虚であるべき",
    "explanation": "預言は、謙虚さの重要性を説き、誇大な自己評価がもたらす悲劇への警告として伝えられています。参考：新解約2017版 エゼキエル書28章",
    "sources": [
      "エゼキエル書 28章"
    ],
    "tags": ["旧約聖書 / エゼキエル書"]
  },
  {
    "question": "【エゼキエル書28章-8】エゼキエル書28章は、ティルスの王の失墜を通して何を警告しているか？",
    "choices": ["高慢は必ず滅びを招く", "努力は報われる", "富は永続する", "権力は守られる"],
    "answer": "高慢は必ず滅びを招く",
    "explanation": "預言は、自己の誇り高い態度が必ず破滅に至るという警告を送っています。参考：新解約2017版 エゼキエル書28章",
    "sources": [
      "エゼキエル書 28章"
    ],
    "tags": ["旧約聖書 / エゼキエル書"]
  },
  {
    "question": "【エゼキエル書29章-1】エゼキエル書29章は、主にどの国に対する預言か？",
    "choices": ["エジプト", "ティルス", "バビロン", "アッシリア"],
    "answer": "エジプト",
    "explanation": "29章は、エジプトに対する神の裁きの預言として展開されています。参考：新解約2017版 エゼキエル書29章",
    "sources": [
      "エゼキエル書 29章"
    ],
    "tags": ["旧約聖書 / エゼキエル書"]
  },
  {
    "question": "【エゼキエル書29章-2】エゼキエル書29章において、エジプトに対する裁きは、何を強調しているか？",
    "choices": ["神の全能な怒り", "経済の繁栄", "宗教の更新", "文化の復興"],
    "answer": "神の全能な怒り",
    "explanation": "裁きは、エジプトの高慢さや反抗に対して、神の全能な怒りが下されることを強調しています。参考：新解約2017版 エゼキエル書29章",
    "sources": [
      "エゼキエル書 29章"
    ],
    "tags": ["旧約聖書 / エゼキエル書"]
  },
  {
    "question": "【エゼキエル書29章-3】エゼキエル書29章は、エジプトのどの側面を問題視しているか？",
    "choices": ["誇り高い態度", "農業の不作", "軍事の弱さ", "芸術の退廃"],
    "answer": "誇り高い態度",
    "explanation": "エジプトはその誇り高い態度ゆえに、神の裁きを受ける対象として非難されています。参考：新解約2017版 エゼキエル書29章",
    "sources": [
      "エゼキエル書 29章"
    ],
    "tags": ["旧約聖書 / エゼキエル書"]
  },
  {
    "question": "【エゼキエル書29章-4】エゼキエル書29章の預言では、エジプトの将来はどのように描かれているか？",
    "choices": ["荒廃と虚無", "繁栄と栄光", "政治の安定", "宗教の隆盛"],
    "answer": "荒廃と虚無",
    "explanation": "預言は、エジプトが最終的に荒廃し、虚無に陥る運命であることを告げています。参考：新解約2017版 エゼキエル書29章",
    "sources": [
      "エゼキエル書 29章"
    ],
    "tags": ["旧約聖書 / エゼキエル書"]
  },
  {
    "question": "【エゼキエル書29章-5】エゼキエル書29章におけるエジプトへの罰は、何を象徴しているか？",
    "choices": ["神の裁きと警告", "新たな同盟", "経済的な繁栄", "文化的交流"],
    "answer": "神の裁きと警告",
    "explanation": "罰は、エジプトの偉大な反抗行為に対する神の厳しい裁きであり、同時に警告としての意味を持ちます。参考：新解約2017版 エゼキエル書29章",
    "sources": [
      "エゼキエル書 29章"
    ],
    "tags": ["旧約聖書 / エゼキエル書"]
  },
  {
    "question": "【エゼキエル書29章-6】エゼキエル書29章は、エジプトが裁かれる原因として何を挙げているか？",
    "choices": ["傲慢な心", "謙虚な精神", "文化の尊重", "経済の発展"],
    "answer": "傲慢な心",
    "explanation": "エジプトはその傲慢な態度のために裁かれるとされ、神の怒りを買ったと預言されています。参考：新解約2017版 エゼキエル書29章",
    "sources": [
      "エゼキエル書 29章"
    ],
    "tags": ["旧約聖書 / エゼキエル書"]
  },
  {
    "question": "【エゼキエル書29章-7】エゼキエル書29章で語られるエジプトの結末は、どのような印象を与えるか？",
    "choices": ["失望と荒廃", "喜びと祝祭", "豊かな実り", "国際的な栄誉"],
    "answer": "失望と荒廃",
    "explanation": "預言は、エジプトが最終的に失望と荒廃に終わる様子を描いています。参考：新解約2017版 エゼキエル書29章",
    "sources": [
      "エゼキエル書 29章"
    ],
    "tags": ["旧約聖書 / エゼキエル書"]
  },
  {
    "question": "【エゼキエル書29章-8】エゼキエル書29章は、エジプトに対して何を警告しているか？",
    "choices": ["神の永続的な裁き", "繁栄の永続", "文化の昇華", "政治の革新"],
    "answer": "神の永続的な裁き",
    "explanation": "預言は、エジプトが今後も神の裁きを受け続けるという警告を強調しています。参考：新解約2017版 エゼキエル書29章",
    "sources": [
      "エゼキエル書 29章"
    ],
    "tags": ["旧約聖書 / エゼキエル書"]
  }
  ,
  {
    "question": "【総合問題】エゼキエル書全体を通じて、預言者エゼキエルの主なメッセージは何か？",
    "choices": ["神の裁きと救済の約束", "経済の繁栄のみ", "政治的中立", "異邦国への同盟"],
    "answer": "神の裁きと救済の約束",
    "explanation": "エゼキエル書は、神の厳しい裁きと共に、悔い改めた者に対する救済の約束を伝えています。参考：新解約2017版 エゼキエル書",
    "sources": [
      "エゼキエル書 全章"
    ],
    "tags": ["旧約聖書 / エゼキエル書"]
  }
]