[
  {
    "question": "黙示録に登場する七つの教会の中で最初に書簡が送られたのはどの教会か？",
    "choices": ["エフェソ", "スミルナ", "ペルガモ", "ラオディキア"],
    "answer": "エフェソ",
    "explanation": "黙示録2章で、エフェソの教会へ最初の書簡が送られています。",
    "sources": [
      "黙示録 2:1-7"
    ],
    "tags": ["新約聖書 / 黙示録"]
  },
  {
    "question": "黙示録に記されている第二の教会はどこですか？",
    "choices": ["エフェソ", "スミルナ", "ペルガモ", "フィラデルフィア"],
    "answer": "スミルナ",
    "explanation": "黙示録2章にはスミルナの教会への書簡が記されています。",
    "sources": [
      "黙示録 2:8-11"
    ],
    "tags": ["新約聖書 / 黙示録"]
  },
  {
    "question": "黙示録の第三の教会はどこにありますか？",
    "choices": ["スミルナ", "ペルガモ", "ティアティラ", "ラオディキア"],
    "answer": "ペルガモ",
    "explanation": "ペルガモの教会には黙示録2章で書簡が送られています。",
    "sources": [
      "黙示録 2:12-17"
    ],
    "tags": ["新約聖書 / 黙示録"]
  },
  {
    "question": "黙示録における第四の教会はどこですか？",
    "choices": ["エフェソ", "スミルナ", "ティアティラ", "サルデス"],
    "answer": "ティアティラ",
    "explanation": "黙示録2章に、ティアティラの教会への書簡が記されています。",
    "sources": [
      "黙示録 2:18-29"
    ],
    "tags": ["新約聖書 / 黙示録"]
  },
  {
    "question": "黙示録における第五の教会はどこですか？",
    "choices": ["サルデス", "フィラデルフィア", "ラオディキア", "エフェソ"],
    "answer": "サルデス",
    "explanation": "サルデスの教会は、黙示録3章に記されています。",
    "sources": [
      "黙示録 3:1-6"
    ],
    "tags": ["新約聖書 / 黙示録"]
  },
  {
    "question": "黙示録における第六の教会はどこですか？",
    "choices": ["フィラデルフィア", "ペルガモ", "スミルナ", "ティアティラ"],
    "answer": "フィラデルフィア",
    "explanation": "フィラデルフィアの教会は、黙示録3章において称賛されています。",
    "sources": [
      "黙示録 3:7-13"
    ],
    "tags": ["新約聖書 / 黙示録"]
  },
  {
    "question": "黙示録における第七の教会はどこですか？",
    "choices": ["ラオディキア", "エフェソ", "スミルナ", "サルデス"],
    "answer": "ラオディキア",
    "explanation": "ラオディキアの教会は、黙示録3章において書簡が送られています。",
    "sources": [
      "黙示録 3:14-22"
    ],
    "tags": ["新約聖書 / 黙示録"]
  },
  {
    "question": "黙示録で最初の封印が開かれた時、現れた騎士はどのような色の馬に乗っていましたか？",
    "choices": ["白", "赤", "黒", "青白"],
    "answer": "白",
    "explanation": "第一の封印では、白い馬に乗っている騎士が登場します（黙示録6:2）。",
    "sources": [
      "黙示録 6:1-2"
    ],
    "tags": ["新約聖書 / 黙示録"]
  },
  {
    "question": "黙示録で第二の封印が示す騎士は何を象徴していますか？",
    "choices": ["戦争", "飢饉", "征服", "死"],
    "answer": "戦争",
    "explanation": "第二の封印では、赤い馬に乗る騎士が戦争や争いを象徴しています（黙示録6:3-4）。",
    "sources": [
      "黙示録 6:3-4"
    ],
    "tags": ["新約聖書 / 黙示録"]
  },
  {
    "question": "黙示録で第三の封印に乗る騎士が象徴する災いは何ですか？",
    "choices": ["飢饉", "戦争", "疫病", "自然災害"],
    "answer": "飢饉",
    "explanation": "第三の封印では、黒い馬に乗る騎士が飢饉を象徴しています（黙示録6:5-6）。",
    "sources": [
      "黙示録 6:5-6"
    ],
    "tags": ["新約聖書 / 黙示録"]
  },
  {
    "question": "黙示録において、第四の封印で現れた騎士が乗った馬の色は？",
    "choices": ["白", "赤", "黒", "青白"],
    "answer": "青白",
    "explanation": "第四の封印では、青白の馬に乗る騎士が死を象徴しています（黙示録6:7-8）。",
    "sources": [
      "黙示録 6:7-8"
    ],
    "tags": ["新約聖書 / 黙示録"]
  },
  {
    "question": "黙示録の第五の封印で、祭壇の下にいる魂は何を象徴していますか？",
    "choices": ["預言者", "殉教者", "天使", "聖人"],
    "answer": "殉教者",
    "explanation": "第五の封印では、神のために殺された殉教者の魂が描かれています（黙示録6:9-10）。",
    "sources": [
      "黙示録 6:9-10"
    ],
    "tags": ["新約聖書 / 黙示録"]
  },
  {
    "question": "黙示録の第六の封印が開かれたとき、どのような現象が起こりましたか？",
    "choices": ["地震と災害", "新たな天使の出現", "七つのトランペットの音", "七つの碗の災い"],
    "answer": "地震と災害",
    "explanation": "第六の封印では、大規模な天変地異が起こると記されています（黙示録6:12-17）。",
    "sources": [
      "黙示録 6:12-17"
    ],
    "tags": ["新約聖書 / 黙示録"]
  },
  {
    "question": "黙示録において、第七の封印が開かれた後、どのような出来事が続きますか？",
    "choices": ["七つのトランペットが鳴る", "大患難が始まる", "獣が現れる", "新エルサレムが降臨"],
    "answer": "七つのトランペットが鳴る",
    "explanation": "第七の封印の開放後、七人の天使に七つのトランペットが与えられます（黙示録8:1）。",
    "sources": [
      "黙示録 8:1"
    ],
    "tags": ["新約聖書 / 黙示録"]
  },
  {
    "question": "黙示録の第一のトランペットが鳴らされたときに降ったものは何ですか？",
    "choices": ["火と血", "雹と火", "石と砂", "水と血"],
    "answer": "雹と火",
    "explanation": "第一のトランペットでは、雹と火が血混じりで降る災いがもたらされます（黙示録8:7）。",
    "sources": [
      "黙示録 8:7"
    ],
    "tags": ["新約聖書 / 黙示録"]
  },
  {
    "question": "黙示録の第二のトランペットでは、何が大地の一部を焼き尽くしましたか？",
    "choices": ["火山", "燃える山", "隕石", "流星"],
    "answer": "燃える山",
    "explanation": "第二のトランペットで、大きな燃える山が海に投げ込まれる災いが描かれています（黙示録8:8-9）。",
    "sources": [
      "黙示録 8:8-9"
    ],
    "tags": ["新約聖書 / 黙示録"]
  },
  {
    "question": "黙示録の第三のトランペットで、どの天体が墜ち、苦い水となりましたか？",
    "choices": ["太陽", "月", "惑星", "星"],
    "answer": "星",
    "explanation": "第三のトランペットでは、大星が墜ち、その水が毒となって人々に苦しみをもたらします（黙示録8:10-11）。",
    "sources": [
      "黙示録 8:10-11"
    ],
    "tags": ["新約聖書 / 黙示録"]
  },
  {
    "question": "黙示録の第四のトランペットが鳴ると、何が暗くなりましたか？",
    "choices": ["太陽、月、星", "地球", "海", "大気"],
    "answer": "太陽、月、星",
    "explanation": "第四のトランペットでは、太陽、月、星の一部が打たれて暗くなります（黙示録8:12）。",
    "sources": [
      "黙示録 8:12"
    ],
    "tags": ["新約聖書 / 黙示録"]
  },
  {
    "question": "黙示録の第五のトランペット（第一の声）では、何が放たれましたか？",
    "choices": ["毒のバッタ", "炎の剣", "暗黒の霧", "硫黄の煙"],
    "answer": "毒のバッタ",
    "explanation": "第五のトランペットでは、悪魔のような姿のバッタが現れ、人々を苦しめます（黙示録9:1-2）。",
    "sources": [
      "黙示録 9:1-2"
    ],
    "tags": ["新約聖書 / 黙示録"]
  },
  {
    "question": "黙示録の第六のトランペット（第二の声）で放たれた災いの対象は？",
    "choices": ["大河", "海の生物", "四人の天使", "大陸"],
    "answer": "四人の天使",
    "explanation": "第六のトランペットで、四人の天使が捕えられた人々に災いを与えます（黙示録9:13-21）。",
    "sources": [
      "黙示録 9:13-21"
    ],
    "tags": ["新約聖書 / 黙示録"]
  },
  {
    "question": "黙示録において、次に鳴るのはどの審判の象徴ですか？",
    "choices": ["七つの碗", "七つの封印", "七つのトランペット", "七つの教会"],
    "answer": "七つの碗",
    "explanation": "トランペットの後、七人の天使に七つの碗が与えられ順に災いがもたらされます（黙示録16章）。",
    "sources": [
      "黙示録 16:1"
    ],
    "tags": ["新約聖書 / 黙示録"]
  },
  {
    "question": "黙示録の第一の碗によってもたらされた災いは何ですか？",
    "choices": ["瘡（そう）", "血の海", "暗闇", "唾液"],
    "answer": "瘡（そう）",
    "explanation": "第一の碗では、神の怒りが現われ、人々に痛ましい瘡が下ります（黙示録16:2）。",
    "sources": [
      "黙示録 16:2"
    ],
    "tags": ["新約聖書 / 黙示録"]
  },
  {
    "question": "黙示録の第二の碗で滝のように注がれたものは何ですか？",
    "choices": ["血", "硫黄", "水", "油"],
    "answer": "血",
    "explanation": "第二の碗では、血が滝のように流れ、多くの人がその災いに苦しみます（黙示録16:3）。",
    "sources": [
      "黙示録 16:3"
    ],
    "tags": ["新約聖書 / 黙示録"]
  },
  {
    "question": "黙示録の第三の碗では、何が人々に降り注ぎますか？",
    "choices": ["硫黄", "火", "蝗虫", "氷"],
    "answer": "硫黄",
    "explanation": "第三の碗では、硫黄を含む火が降り注ぎ、人々に激しい痛みをもたらします（黙示録16:4）。",
    "sources": [
      "黙示録 16:4"
    ],
    "tags": ["新約聖書 / 黙示録"]
  },
  {
    "question": "黙示録の第四の碗で起こる災いは何ですか？",
    "choices": ["暗黒の中に落ちる", "大河が血に変わる", "太陽が激しく焼く", "海が沸騰する"],
    "answer": "太陽が激しく焼く",
    "explanation": "第四の碗では、太陽の熱が増し、地上の人々に大きな苦しみを与えます（黙示録16:8-9）。",
    "sources": [
      "黙示録 16:8-9"
    ],
    "tags": ["新約聖書 / 黙示録"]
  },
  {
    "question": "黙示録の第五の碗の災いにより、どこで闇が起こりますか？",
    "choices": ["エルサレム", "大河", "王宮", "王の国"],
    "answer": "王の国",
    "explanation": "第五の碗では、獣の王国に深い闇が臨み、人々が苦しみます（黙示録16:10-11）。",
    "sources": [
      "黙示録 16:10-11"
    ],
    "tags": ["新約聖書 / 黙示録"]
  },
  {
    "question": "黙示録の第六の碗で流された血の量はどれほどですか？",
    "choices": ["小さじ1杯", "海全体", "川一本分", "大いなる泉"],
    "answer": "大いなる泉",
    "explanation": "第六の碗では、巨大的な災いとして大量の血が流されると記されています（黙示録16:12）。",
    "sources": [
      "黙示録 16:12"
    ],
    "tags": ["新約聖書 / 黙示録"]
  },
  {
    "question": "黙示録の第七の碗で語られる主要な出来事は何ですか？",
    "choices": ["新しい天と地", "大地の震動", "全ての悪の敗北", "バビロンの滅亡"],
    "answer": "新しい天と地",
    "explanation": "第七の碗では、神の全面的な審判が現れ、新しい創造の幕開けが予告されます（黙示録16:17-21）。",
    "sources": [
      "黙示録 16:17-21"
    ],
    "tags": ["新約聖書 / 黙示録"]
  },
  {
    "question": "黙示録に登場する獣はどこから現れますか？",
    "choices": ["海から", "地上から", "空から", "地下から"],
    "answer": "海から",
    "explanation": "獣は海から現れると記され、力と権威を持つ存在として描かれています（黙示録13:1-2）。",
    "sources": [
      "黙示録 13:1-2"
    ],
    "tags": ["新約聖書 / 黙示録"]
  },
  {
    "question": "黙示録の獣の特徴として正しいものはどれですか？",
    "choices": ["七つの頭と十の角", "五つの目と三つの牙", "六つの翼を持つ", "四つの顔を持つ"],
    "answer": "七つの頭と十の角",
    "explanation": "獣は七つの頭と十の角を持つと描かれ、その象徴的な力を示しています（黙示録13:1）。",
    "sources": [
      "黙示録 13:1"
    ],
    "tags": ["新約聖書 / 黙示録"]
  },
  {
    "question": "黙示録で獣に与えられた権威の期間はどれくらいとされていますか？",
    "choices": ["42ヶ月", "7年", "3年半", "1260日"],
    "answer": "1260日",
    "explanation": "獣の権威は、黙示録13章で1260日と記されています。",
    "sources": [
      "黙示録 13:5"
    ],
    "tags": ["新約聖書 / 黙示録"]
  },
  {
    "question": "黙示録に登場する第二の獣は何と呼ばれていますか？",
    "choices": ["偽預言者", "偽救世主", "大いなる敵", "反キリスト"],
    "answer": "偽預言者",
    "explanation": "第二の獣は、獣の側近として偽預言者の役割を果たし、偶像崇拝を扇動します（黙示録13:11）。",
    "sources": [
      "黙示録 13:11-12"
    ],
    "tags": ["新約聖書 / 黙示録"]
  },
  {
    "question": "黙示録において、獣に対抗するものとして描かれるものは何ですか？",
    "choices": ["子羊", "大天使", "聖なる使い", "正義の戦士"],
    "answer": "子羊",
    "explanation": "子羊（イエス・キリスト）は、獣と対立する救済の象徴として描かれています（黙示録12章）。",
    "sources": [
      "黙示録 12:10"
    ],
    "tags": ["新約聖書 / 黙示録"]
  },
  {
    "question": "黙示録に登場する「獣の刻印」は何の象徴として描かれていますか？",
    "choices": ["所有権", "忠誠心", "罪と反抗", "神の恵み"],
    "answer": "罪と反抗",
    "explanation": "獣の刻印は、信仰に反する者たちの象徴とされています（黙示録13:16-18）。",
    "sources": [
      "黙示録 13:16-18"
    ],
    "tags": ["新約聖書 / 黙示録"]
  },
  {
    "question": "黙示録で「バビロン大淫婦」とは何を象徴していますか？",
    "choices": ["堕落した大都市", "反逆者の集団", "神の代理人", "未来の理想都市"],
    "answer": "堕落した大都市",
    "explanation": "バビロン大淫婦は、堕落と偶像崇拝の象徴として描かれています（黙示録17章）。",
    "sources": [
      "黙示録 17:1-6"
    ],
    "tags": ["新約聖書 / 黙示録"]
  },
  {
    "question": "黙示録において、バビロン大淫婦はどのような形で描かれていますか？",
    "choices": ["美しい女性", "猛獣", "巨大な像", "焼けた森"],
    "answer": "美しい女性",
    "explanation": "バビロン大淫婦は、美しいが堕落した女性の姿で象徴的に描かれています（黙示録17章）。",
    "sources": [
      "黙示録 17:1-2"
    ],
    "tags": ["新約聖書 / 黙示録"]
  },
  {
    "question": "黙示録に登場する『大いなるしるし』は何を示していますか？",
    "choices": ["神の怒り", "救済の希望", "終末の到来", "再生の時"],
    "answer": "終末の到来",
    "explanation": "『大いなるしるし』は、黙示録における終末の印として描かれています（黙示録1章）。",
    "sources": [
      "黙示録 1:12-16"
    ],
    "tags": ["新約聖書 / 黙示録"]
  },
  {
    "question": "黙示録の最初のビジョンで見られるイエスの姿はどのように表現されていますか？",
    "choices": ["輝く目と剣を持つ", "弱々しい老人", "普通の人間", "無表情な像"],
    "answer": "輝く目と剣を持つ",
    "explanation": "黙示録1章では、イエスが輝く目と剣を持って現れる姿が描かれています。",
    "sources": [
      "黙示録 1:12-16"
    ],
    "tags": ["新約聖書 / 黙示録"]
  },
  {
    "question": "黙示録における女性と竜の戦いは、何を象徴していると解釈されますか？",
    "choices": ["信仰と悪の戦い", "自然の摂理", "経済と政治", "科学と宗教"],
    "answer": "信仰と悪の戦い",
    "explanation": "女性と竜の戦いは、神の民と悪の勢力との対立を象徴しています（黙示録12章）。",
    "sources": [
      "黙示録 12:7-9"
    ],
    "tags": ["新約聖書 / 黙示録"]
  },
  {
    "question": "黙示録における大いなる異兆の時は、どのような出来事が含まれますか？",
    "choices": ["宇宙の混沌", "平和な時代", "豊かな実り", "祝福の雨"],
    "answer": "宇宙の混沌",
    "explanation": "大いなる異兆は、宇宙規模での変動や混沌を示しています（黙示録6章、8章）。",
    "sources": [
      "黙示録 6:12-17",
      "黙示録 8:12"
    ],
    "tags": ["新約聖書 / 黙示録"]
  },
  {
    "question": "黙示録でイエスが示す『再臨』のビジョンはどこにありますか？",
    "choices": ["1章", "3章", "7章", "10章"],
    "answer": "1章",
    "explanation": "黙示録1章でイエスの再臨の象徴的な姿が描かれています。",
    "sources": [
      "黙示録 1:12-16"
    ],
    "tags": ["新約聖書 / 黙示録"]
  },
  {
    "question": "黙示録に登場する『巻物』は何を象徴しているとされていますか？",
    "choices": ["救いの計画", "過去の歴史", "未来の予言", "現在の状況"],
    "answer": "未来の予言",
    "explanation": "巻物は、神の未来の計画と審判を象徴しています（黙示録5章）。",
    "sources": [
      "黙示録 5:1-5"
    ],
    "tags": ["新約聖書 / 黙示録"]
  },
  {
    "question": "黙示録において、子羊が巻物を受け取るシーンは何を意味していますか？",
    "choices": ["全面的な救済", "祝祭の開始", "戦争の始まり", "古い秩序の終わり"],
    "answer": "全面的な救済",
    "explanation": "子羊が巻物を受け取ることにより、救済の完成と新しい時代の到来が示されます（黙示録5:6-10）。",
    "sources": [
      "黙示録 5:6-10"
    ],
    "tags": ["新約聖書 / 黙示録"]
  },
  {
    "question": "黙示録において神の玉座がある場所はどのように表現されていますか？",
    "choices": ["雲の上", "荒野", "海の中", "天の上"],
    "answer": "雲の上",
    "explanation": "神の玉座は、天において雲の上に位置すると描かれています（黙示録4章）。",
    "sources": [
      "黙示録 4:2-3"
    ],
    "tags": ["新約聖書 / 黙示録"]
  },
  {
    "question": "黙示録に描かれる24人の長老は何を象徴していますか？",
    "choices": ["天使の階級", "聖なる会議", "旧約の部族", "使徒たち"],
    "answer": "聖なる会議",
    "explanation": "24人の長老は、天における神の聖なる会議を象徴しています（黙示録4:4）。",
    "sources": [
      "黙示録 4:4"
    ],
    "tags": ["新約聖書 / 黙示録"]
  },
  {
    "question": "黙示録における『賛美の歌』は誰によって歌われていますか？",
    "choices": ["24人の長老", "七人の天使", "獣", "召された者"],
    "answer": "24人の長老",
    "explanation": "24人の長老は、神の玉座の前で絶えず賛美の歌を歌っています（黙示録4:8）。",
    "sources": [
      "黙示録 4:8"
    ],
    "tags": ["新約聖書 / 黙示録"]
  },
  {
    "question": "黙示録で口にされる『新しい歌』はどの場面で登場しますか？",
    "choices": ["子羊の巻物取得時", "大患難の始まり", "最後の審判", "新エルサレムの到来"],
    "answer": "子羊の巻物取得時",
    "explanation": "新しい歌は、子羊が巻物を受ける際に、多くの聖者によって歌われます（黙示録5:9）。",
    "sources": [
      "黙示録 5:9"
    ],
    "tags": ["新約聖書 / 黙示録"]
  },
  {
    "question": "黙示録における『七つの封印』は何の過程を象徴していますか？",
    "choices": ["救済の段階", "神の叱責", "教会の誕生", "信仰の試練"],
    "answer": "救済の段階",
    "explanation": "七つの封印は、救済の啓示と神の計画が段階的に明らかにされる過程を象徴しています。",
    "sources": [
      "黙示録 6章",
      "黙示録 8章"
    ],
    "tags": ["新約聖書 / 黙示録"]
  },
  {
    "question": "黙示録における『七つのトランペット』は、何を予告するものですか？",
    "choices": ["審判の災い", "教会への祝福", "預言の成就", "復活の兆し"],
    "answer": "審判の災い",
    "explanation": "七つのトランペットは、神の審判が次第に明らかにされる災いの連鎖を示します。",
    "sources": [
      "黙示録 8章",
      "黙示録 9章"
    ],
    "tags": ["新約聖書 / 黙示録"]
  },
  {
    "question": "黙示録に記された災いの連鎖の中で、どのシンボルが特に『終末の印』として扱われますか？",
    "choices": ["獣の刻印", "長老の冠", "子羊の羔", "巻物の印"],
    "answer": "獣の刻印",
    "explanation": "獣の刻印は、終末の時に背く者たちの証として重要なシンボルとされています。",
    "sources": [
      "黙示録 13:16-18"
    ],
    "tags": ["新約聖書 / 黙示録"]
  },
  {
    "question": "黙示録にみられる『大患難』の期間は一般的に何日と解釈されていますか？",
    "choices": ["7日", "42日", "1260日", "40年"],
    "answer": "1260日",
    "explanation": "大患難の期間は、黙示録13章などで1260日と象徴的に表現されています。",
    "sources": [
      "黙示録 13:5"
    ],
    "tags": ["新約聖書 / 黙示録"]
  },
  {
    "question": "黙示録に登場する『小羊』は主に何を象徴していますか？",
    "choices": ["犠牲", "真実", "愛", "賛美"],
    "answer": "犠牲",
    "explanation": "小羊は、イエス・キリストの犠牲を象徴しており、救済の中心となっています（黙示録5章）。",
    "sources": [
      "黙示録 5:6-10"
    ],
    "tags": ["新約聖書 / 黙示録"]
  },
  {
    "question": "黙示録で語られる『新エルサレム』はどこから降りてくると描かれていますか？",
    "choices": ["天から", "海から", "大地から", "火の中から"],
    "answer": "天から",
    "explanation": "新エルサレムは、神の住む天から降りてくると記されています（黙示録21章）。",
    "sources": [
      "黙示錄 21:2"
    ],
    "tags": ["新約聖書 / 黙示録"]
  },
  {
    "question": "黙示録の新エルサレムはどのように描写されていますか？",
    "choices": ["黄金の都", "石の要塞", "霧に包まれた街", "血の都"],
    "answer": "黄金の都",
    "explanation": "新エルサレムは、美しい黄金の都として描かれ、神の臨在の象徴となっています（黙示録21章）。",
    "sources": [
      "黙示録 21:10-11"
    ],
    "tags": ["新約聖書 / 黙示録"]
  },
  {
    "question": "黙示録において、『命の水』が与えられると記されている場所はどこですか？",
    "choices": ["新エルサレム", "旧エルサレム", "楽園", "バビロン"],
    "answer": "新エルサレム",
    "explanation": "新エルサレムには、命の水の川が与えられるという約束が記されています（黙示録21章）。",
    "sources": [
      "黙示録 21:6"
    ],
    "tags": ["新約聖書 / 黙示録"]
  },
  {
    "question": "黙示録21章において、神は『涙を一切の川から拭い取る』と約束していますが、これは何を象徴していますか？",
    "choices": ["永遠の平和", "苦悩の終わり", "力の行使", "裁きの始まり"],
    "answer": "苦悩の終わり",
    "explanation": "涙が拭われる約束は、苦しみと悲しみの終わりを象徴しています（黙示録21:4）。",
    "sources": [
      "黙示録 21:4"
    ],
    "tags": ["新約聖書 / 黙示録"]
  },
  {
    "question": "黙示録における『終わりなき夜』に関する記述はどの章に見られますか？",
    "choices": ["21章", "20章", "19章", "18章"],
    "answer": "20章",
    "explanation": "黙示録20章では、サタンの束縛とその後の最終審判が語られ、永遠の闇が示唆されます。",
    "sources": [
      "黙示録 20章"
    ],
    "tags": ["新約聖書 / 黙示録"]
  },
  {
    "question": "黙示録において、最後の審判は誰によって行われるとされていますか？",
    "choices": ["子羊", "大天使", "長老たち", "獣"],
    "answer": "子羊",
    "explanation": "最後の審判は、イエス・キリスト（子羊）によって行われると描かれています（黙示録20:11-15）。",
    "sources": [
      "黙示録 20:11-15"
    ],
    "tags": ["新約聖書 / 黙示録"]
  },
  {
    "question": "黙示録において、サタンは最終的にどのように処理されますか？",
    "choices": ["永遠に放逐される", "燃え尽きる", "また一度自由になる", "縛られる"],
    "answer": "縛られる",
    "explanation": "サタンは最終審判の前に千年の間縛られ、その後最終的に火に投げ込まれます（黙示録20:1-3, 10）。",
    "sources": [
      "黙示録 20:1-3,10"
    ],
    "tags": ["新約聖書 / 黙示録"]
  },
  {
    "question": "黙示録において、『白い馬に乗る者』は何を象徴していますか？",
    "choices": ["正義", "戦争", "平和", "征服"],
    "answer": "正義",
    "explanation": "白い馬に乗る者は、勝利と正義の象徴として描かれています（黙示録19:11-16）。",
    "sources": [
      "黙示録 19:11-16"
    ],
    "tags": ["新約聖書 / 黙示録"]
  },
  {
    "question": "黙示録19章で、子羊の勝利の象徴として与えられる冠は何と呼ばれていますか？",
    "choices": ["栄光の冠", "生命の冠", "勝利の冠", "永遠の冠"],
    "answer": "栄光の冠",
    "explanation": "子羊に与えられる冠は、栄光と勝利の象徴とされています（黙示録19:12）。",
    "sources": [
      "黙示録 19:12"
    ],
    "tags": ["新約聖書 / 黙示録"]
  },
  {
    "question": "黙示録にて『婚姻の夕食』として描かれる場面は、何を象徴していますか？",
    "choices": ["神と信者の交わり", "終末の裁き", "戦争の饗宴", "堕落の宴"],
    "answer": "神と信者の交わり",
    "explanation": "婚姻の夕食は、神とその民との親密な交わりと祝宴を象徴しています（黙示録19:7-9）。",
    "sources": [
      "黙示録 19:7-9"
    ],
    "tags": ["新約聖書 / 黙示録"]
  },
  {
    "question": "黙示録における『七つのステッパー』の概念は何を指すか？",
    "choices": ["完全な契約", "神の計画の完成", "不完全な救済", "人間の自由意志"],
    "answer": "神の計画の完成",
    "explanation": "『七つのステッパー』は、神の計画が完全に実現する段階を象徴しているとされます（解釈例）。",
    "sources": [
      "黙示録 全体の文脈"
    ],
    "tags": ["新約聖書 / 黙示録"]
  },
  {
    "question": "黙示録において用いられる数『7』は象徴的に何を意味しますか？",
    "choices": ["完全さ", "不完全さ", "偶然", "不滅"],
    "answer": "完全さ",
    "explanation": "聖書では7は神聖な完全さや完成を象徴する数として用いられます。",
    "sources": [
      "黙示録 全体の文脈"
    ],
    "tags": ["新約聖書 / 黙示録"]
  },
  {
    "question": "黙示録に登場する『宝石の城壁』はどこに見られますか？",
    "choices": ["エルサレム", "新エルサレム", "バビロン", "パレスチナ"],
    "answer": "新エルサレム",
    "explanation": "新エルサレムは、宝石で飾られた城壁を持つ美しい都として描かれています（黙示録21:18-21）。",
    "sources": [
      "黙示録 21:18-21"
    ],
    "tags": ["新約聖書 / 黙示録"]
  },
  {
    "question": "黙示録で語られる『命の書』は何に関するものですか？",
    "choices": ["救いを受ける者の記録", "神の創造記録", "過去の歴史", "未来の予知"],
    "answer": "救いを受ける者の記録",
    "explanation": "命の書は、救いの遺産として、信者の名前が記されるものとされています（黙示録3:5など）。",
    "sources": [
      "黙示録 3:5"
    ],
    "tags": ["新約聖書 / 黙示録"]
  },
  {
    "question": "黙示録において、『真実な証人』として描かれているのは誰ですか？",
    "choices": ["イエス・キリスト", "使徒ヨハネ", "子羊", "天使"],
    "answer": "イエス・キリスト",
    "explanation": "イエス・キリストは、真実の証人として、全ての啓示を成就する存在とされています（黙示録1章）。",
    "sources": [
      "黙示録 1章"
    ],
    "tags": ["新約聖書 / 黙示録"]
  },
  {
    "question": "黙示録に描かれる『災いの叫び』はどのようなものとされていますか？",
    "choices": ["天変地異", "人々の嘆き", "エンジェルの叫び", "戦士の咆哮"],
    "answer": "天変地異",
    "explanation": "災いの叫びは、天変地異とともに、神の怒りが現れる際の象徴とされています（黙示録6章）。",
    "sources": [
      "黙示録 6:12-17"
    ],
    "tags": ["新約聖書 / 黙示録"]
  },
  {
    "question": "黙示録に出てくる『封印された巻物』の開封は誰によって行われるとされていますか？",
    "choices": ["子羊", "人間", "大天使", "預言者"],
    "answer": "子羊",
    "explanation": "子羊が巻物の封印を解くことで、神の救済計画が明らかになるとされます（黙示録5章）。",
    "sources": [
      "黙示録 5:1-5"
    ],
    "tags": ["新約聖書 / 黙示録"]
  },
  {
    "question": "黙示録のビジョンで使われる『火』は、主に何を象徴していますか？",
    "choices": ["浄化と審判", "祝福", "生命", "再生"],
    "answer": "浄化と審判",
    "explanation": "火は、神の清めと審判の象徴として、しばしば使用されます（黙示録8章、16章）。",
    "sources": [
      "黙示録 8章",
      "黙示録 16章"
    ],
    "tags": ["新約聖書 / 黙示録"]
  },
  {
    "question": "黙示録における『七つの碗の災い』は、どのような順序で現れますか？",
    "choices": ["段階的な神の怒り", "一斉に起こる", "交互に現れる", "ランダム"],
    "answer": "段階的な神の怒り",
    "explanation": "鉢の災いは、段階的に与えられる神の怒りを示すものです（黙示録16章）。",
    "sources": [
      "黙示録 16章"
    ],
    "tags": ["新約聖書 / 黙示録"]
  },
  {
    "question": "黙示録に登場する『二つの大いなる戦い』は、一つ目が何ですか？",
    "choices": ["天使と竜の戦い", "教会内の争い", "獣と小羊の戦い", "人間同士の戦い"],
    "answer": "天使と竜の戦い",
    "explanation": "最初の大いなる戦いは、天使と竜（サタン）との戦いとして描かれています（黙示録12:7-9）。",
    "sources": [
      "黙示録 12:7-9"
    ],
    "tags": ["新約聖書 / 黙示録"]
  },
  {
    "question": "黙示録で描かれる『黄金の杯』は何の象徴と解釈されることが多いですか？",
    "choices": ["神の恵み", "憎悪", "裁き", "富"],
    "answer": "裁き",
    "explanation": "黄金の杯は、神の怒りと裁きを象徴することがあります（黙示録16章のイメージ）。",
    "sources": [
      "黙示録 16章"
    ],
    "tags": ["新約聖書 / 黙示録"]
  },
  {
    "question": "黙示録にて、『永遠の福』が約束される場面はどこに描かれていますか？",
    "choices": ["新エルサレム", "バビロン", "出エジプト", "楽園"],
    "answer": "新エルサレム",
    "explanation": "新エルサレムは、永遠の福と神の臨在が実現する場所として描かれています（黙示録21章）。",
    "sources": [
      "黙示録 21章"
    ],
    "tags": ["新約聖書 / 黙示録"]
  },
  {
    "question": "黙示録で『地の震え』が起こるシーンは主にどの封印または災いに関連していますか？",
    "choices": ["第六の封印", "第一の封印", "第三の碗", "第一のトランペット"],
    "answer": "第六の封印",
    "explanation": "地震やその他の天変地異は、第六の封印が開かれた時に起こるとされています（黙示録6:12-17）。",
    "sources": [
      "黙示録 6:12-17"
    ],
    "tags": ["新約聖書 / 黙示録"]
  },
  {
    "question": "黙示録に記された『七つの星』は何を象徴していますか？",
    "choices": ["七つの教会", "七つの大罪", "七つの天使", "七つの預言"],
    "answer": "七つの教会",
    "explanation": "七つの星は、各教会の天使（守護霊）を象徴していると解釈されます（黙示録1:20）。",
    "sources": [
      "黙示録 1:20"
    ],
    "tags": ["新約聖書 / 黙示録"]
  },
  {
    "question": "黙示録における『透明な水晶の玉座』は何を象徴していますか？",
    "choices": ["神の公正", "人間の弱さ", "虚無", "救い"],
    "answer": "神の公正",
    "explanation": "透明な水晶の玉座は、神の正義と公正を象徴しているとされます（黙示録4章）。",
    "sources": [
      "黙示録 4:2-3"
    ],
    "tags": ["新約聖書 / 黙示録"]
  },
  {
    "question": "黙示録において、『荒野』はしばしば何を象徴する場面に用いられますか？",
    "choices": ["試練", "安息", "豊穣", "静寂"],
    "answer": "試練",
    "explanation": "荒野は、信仰の試練と神の試みの場として描かれることがあります。",
    "sources": [
      "黙示録 全体の文脈"
    ],
    "tags": ["新約聖書 / 黙示録"]
  },
  {
    "question": "黙示録に登場する『大いなる声』は通常誰の声と解釈されますか？",
    "choices": ["神の声", "人々の抗議", "天使の声", "獣の声"],
    "answer": "神の声",
    "explanation": "大いなる声は、神の意志や裁きを伝えるために用いられる表現です。",
    "sources": [
      "黙示録 8章"
    ],
    "tags": ["新約聖書 / 黙示録"]
  },
  {
    "question": "黙示録の中で、『羊と共に帆を上げる者』はどの象徴に関連していますか？",
    "choices": ["信仰の旅", "戦い", "浄化", "失楽"],
    "answer": "信仰の旅",
    "explanation": "羊と共に帆を上げる表現は、信仰の旅路や神への帰依を象徴することがあります。",
    "sources": [
      "黙示録 全体の解釈"
    ],
    "tags": ["新約聖書 / 黙示録"]
  },
  {
    "question": "黙示録における『獣の海』の象徴は何を示すとされていますか？",
    "choices": ["権力の乱用", "豊かな実り", "神の御心", "平和な時代"],
    "answer": "権力の乱用",
    "explanation": "獣の登場は、悪と権力の乱用を象徴するものであり、海から現れるとされています（黙示録13章）。",
    "sources": [
      "黙示録 13:1-2"
    ],
    "tags": ["新約聖書 / 黙示録"]
  },
  {
    "question": "黙示録において、『天に描かれた書』は何を記録しているとされていますか？",
    "choices": ["人々の罪", "天使の階級", "神の計画", "人間の未来"],
    "answer": "神の計画",
    "explanation": "天に描かれた書は、神の全体的な計画と救済の歴史が記されている象徴と考えられます。",
    "sources": [
      "黙示録 全体の文脈"
    ],
    "tags": ["新約聖書 / 黙示録"]
  },
  {
    "question": "黙示録で語られる『白い衣』を着た者たちは、何を受けた象徴ですか？",
    "choices": ["救い", "罰", "知識", "権力"],
    "answer": "救い",
    "explanation": "白い衣は、信仰による清めと救いの証として与えられると描かれています（黙示録7章）。",
    "sources": [
      "黙示録 7:9-14"
    ],
    "tags": ["新約聖書 / 黙示録"]
  },
  {
    "question": "黙示録における『祭司としての役割』について述べられているのは、誰に関する言及ですか？",
    "choices": ["信者全体", "特定の長老", "預言者だけ", "使徒のみ"],
    "answer": "信者全体",
    "explanation": "祭司としての役割は、救いを受けた信者一人ひとりに与えられる召命とされています（黙示録7章）。",
    "sources": [
      "黙示録 7:15-17"
    ],
    "tags": ["新約聖書 / 黙示録"]
  },
  {
    "question": "黙示録に描かれる『川』は、何を象徴していますか？",
    "choices": ["命の与え", "涙", "悲しみ", "力"],
    "answer": "命の与え",
    "explanation": "川は、命と恵みの象徴として、神の均衡と赦しを示しています（黙示録22章）。",
    "sources": [
      "黙示録 22:1-2"
    ],
    "tags": ["新約聖書 / 黙示録"]
  },
  {
    "question": "黙示録における『光』は象徴的に何を示していますか？",
    "choices": ["神の存在", "知識", "無知", "混沌"],
    "answer": "神の存在",
    "explanation": "光は神の栄光と臨在を表すシンボルとして、聖書全体で用いられます。",
    "sources": [
      "黙示録 全体の象徴表現"
    ],
    "tags": ["新約聖書 / 黙示録"]
  },
  {
    "question": "黙示録において、『地の王たち』はどのように扱われますか？",
    "choices": ["神の前で裁かれる", "祝福される", "永遠の命を与えられる", "無視される"],
    "answer": "神の前で裁かれる",
    "explanation": "地の王たちは、最終審判において神の前に引き出されるとされています（黙示録20章）。",
    "sources": [
      "黙示録 20:11-15"
    ],
    "tags": ["新約聖書 / 黙示録"]
  },
  {
    "question": "黙示録に描かれる『真実な証』は何を基準に判断されるとされていますか？",
    "choices": ["書かれた言葉", "心の状態", "行い", "信仰"],
    "answer": "信仰",
    "explanation": "真実な証は、信仰と神への従順さに基づいて評価されます。",
    "sources": [
      "黙示録 全体のテーマ"
    ],
    "tags": ["新約聖書 / 黙示録"]
  },
  {
    "question": "黙示録における『祭壇の周り』には何が集まると記されていますか？",
    "choices": ["殉教者の霊", "戦士の霊", "反逆者", "天使"],
    "answer": "殉教者の霊",
    "explanation": "祭壇の周りに現れるものは、神のために命を賭した殉教者の霊とされています（黙示録6:9-10）。",
    "sources": [
      "黙示録 6:9-10"
    ],
    "tags": ["新約聖書 / 黙示録"]
  },
  {
    "question": "黙示録に記された『恵みの雲』は何を表す象徴でしょうか？",
    "choices": ["神の隠れた臨在", "隠された知識", "人間の希望", "失われた力"],
    "answer": "神の隠れた臨在",
    "explanation": "恵みの雲は、神の臨在とその隠された救いの力を象徴しています。",
    "sources": [
      "黙示録 全体の象徴"
    ],
    "tags": ["新約聖書 / 黙示録"]
  },
  {
    "question": "黙示録において『封印された教書』は何を表していますか？",
    "choices": ["未来の計画", "過去の栄光", "現在の混乱", "歴史の終焉"],
    "answer": "未来の計画",
    "explanation": "封印された教書は、神の秘密の計画と未来の啓示を象徴しています。",
    "sources": [
      "黙示録 5章"
    ],
    "tags": ["新約聖書 / 黙示録"]
  },
  {
    "question": "黙示録に登場する『硫黄の山』は何を意味することが多いですか？",
    "choices": ["大きな災い", "繁栄", "平和", "再生"],
    "answer": "大きな災い",
    "explanation": "硫黄は、破壊と炎の象徴であり、硫黄の山は大いなる災いを示唆します（黙示録8:8-9）。",
    "sources": [
      "黙示録 8:8-9"
    ],
    "tags": ["新約聖書 / 黙示録"]
  },
  {
    "question": "黙示録において、『大いなる叫び』はどのような状況で響くとされていますか？",
    "choices": ["終末の審判時", "平穏な日々", "祝祭の時", "世の再建時"],
    "answer": "終末の審判時",
    "explanation": "大いなる叫びは、終末の審判や神の怒りが表現されるシーンで聞かれるとされています。",
    "sources": [
      "黙示録 全体の描写"
    ],
    "tags": ["新約聖書 / 黙示録"]
  },
  {
    "question": "黙示録に記された『異人たちの叫び声』は何を予示すると解釈されますか？",
    "choices": ["最後の反逆", "新しい時代の到来", "神の赦し", "繁栄の兆し"],
    "answer": "最後の反逆",
    "explanation": "異人たちの叫び声は、最終的な反逆や失望を象徴するとされています（黙示録10章）。",
    "sources": [
      "黙示録 10章"
    ],
    "tags": ["新約聖書 / 黙示録"]
  },
  {
    "question": "黙示録で『翼のある生物』が賛美する対象は誰ですか？",
    "choices": ["神", "サタン", "地の王", "人類"],
    "answer": "神",
    "explanation": "翼のある生物は、神の栄光と聖性を讃えるために存在すると描かれています（黙示録4章）。",
    "sources": [
      "黙示録 4:6-8"
    ],
    "tags": ["新約聖書 / 黙示録"]
  },
  {
    "question": "黙示録における『燃え盛る火』は、最終審判の象徴として何を意味していますか？",
    "choices": ["浄化と罰", "新生", "避難所", "喜び"],
    "answer": "浄化と罰",
    "explanation": "燃え盛る火は、神の厳しい浄化と罰のシンボルとされています（黙示録20章）。",
    "sources": [
      "黙示録 20章"
    ],
    "tags": ["新約聖書 / 黙示録"]
  },
  {
    "question": "黙示録で『暗黒の霧』は、どの災いの一部として現れますか？",
    "choices": ["第一のトランペット", "第一の碗", "第六の封印", "第四のトランペット"],
    "answer": "第一のトランペット",
    "explanation": "寒冷な暗黒や霧の中に敗北をもたらす災いは、第一のトランペットの描写に類似します。",
    "sources": [
      "黙示録 8章"
    ],
    "tags": ["新約聖書 / 黙示録"]
  },
  {
    "question": "黙示録において、『聖なる都』に関する記述はどの章に多く見られますか？",
    "choices": ["21章", "5章", "12章", "16章"],
    "answer": "21章",
    "explanation": "聖なる都、すなわち新エルサレムに関する記述は、黙示録21章に豊富にあります。",
    "sources": [
      "黙示録 21章"
    ],
    "tags": ["新約聖書 / 黙示録"]
  },
  {
    "question": "黙示録に描かれる『永遠の命』は、どのような手段で与えられるとされていますか？",
    "choices": ["神の恵みと救い", "富と権力", "知識と知恵", "勇気と戦い"],
    "answer": "神の恵みと救い",
    "explanation": "永遠の命は、神の恵みと救いによって信者に与えられるとされています（黙示録21章）。",
    "sources": [
      "黙示録 21章"
    ],
    "tags": ["新約聖書 / 黙示録"]
  },
  {
    "question": "黙示録にて『倒れた大いなる者』とは誰のことを指しているのでしょうか？",
    "choices": ["サタン", "偽預言者", "獣", "バビロン"],
    "answer": "サタン",
    "explanation": "『倒れた大いなる者』は、堕天使としてのサタンを指すと一般的に解釈されます（黙示録12章）。",
    "sources": [
      "黙示録 12:9"
    ],
    "tags": ["新約聖書 / 黙示録"]
  },
  {
    "question": "黙示録において、『目覚めの時』とは、主に何を指すのでしょうか？",
    "choices": ["信仰の再生", "人間の目覚め", "平和な時代", "科学の発展"],
    "answer": "信仰の再生",
    "explanation": "目覚めの時は、信者や世界が霊的に新たに目覚める瞬間を象徴します（解釈例）。",
    "sources": [
      "黙示録 解釈例"
    ],
    "tags": ["新約聖書 / 黙示録"]
  },
  {
    "question": "黙示録において、『時の終わり』が描かれる際、最も強調されるテーマは何ですか？",
    "choices": ["神の正義と裁き", "人類の進歩", "科学の革命", "芸術の栄光"],
    "answer": "神の正義と裁き",
    "explanation": "時の終わりは、神の正義と最終的な裁きが顕現する時として描かれます（黙示録20章）。",
    "sources": [
      "黙示録 20章"
    ],
    "tags": ["新約聖書 / 黙示録"]
  },
  {
    "question": "黙示録における『生ける水』は、何を象徴していると考えられますか？",
    "choices": ["霊的な生命", "暴力", "絶望", "混沌"],
    "answer": "霊的な生命",
    "explanation": "生ける水は、信者に与えられる霊的な生命と再生の象徴です（黙示録22章）。",
    "sources": [
      "黙示録 22:1-2"
    ],
    "tags": ["新約聖書 / 黙示録"]
  },
  {
    "question": "黙示録において、『滅びゆく者』に対して神はどのような結末を約束していますか？",
    "choices": ["永遠の刑罰", "再生の機会", "無記名の消滅", "祝福"],
    "answer": "永遠の刑罰",
    "explanation": "神は堕落した者たちに対し、最終的な永遠の刑罰を約束すると記されています（黙示録20章）。",
    "sources": [
      "黙示録 20:10-15"
    ],
    "tags": ["新約聖書 / 黙示録"]
  },
  {
    "question": "黙示録で『聖者』と呼ばれる者たちは、最終的にどこに住むと記されていますか？",
    "choices": ["新エルサレム", "地上", "地下", "天国の一部"],
    "answer": "新エルサレム",
    "explanation": "聖者は新エルサレムに住むという約束を受け、永遠の命を得るとされています（黙示録21章）。",
    "sources": [
      "黙示録 21章"
    ],
    "tags": ["新約聖書 / 黙示録"]
  },
  {
    "question": "黙示録において、『神の献身』が最もよく示される場面はどれですか？",
    "choices": ["子羊が巻物の封印を解く場面", "獣が現れる場面", "教会への書簡", "預言者の苦難"],
    "answer": "子羊が巻物の封印を解く場面",
    "explanation": "子羊による巻物の封印の解除は、神の救済計画と献身が示された象徴的な場面です（黙示録5章）。",
    "sources": [
      "黙示録 5章"
    ],
    "tags": ["新約聖書 / 黙示録"]
  },
  {
    "question": "黙示録に記された『新たに創られるもの』とは何を指していますか？",
    "choices": ["新しい天と地", "新しい教会", "新しい律法", "新しい国家"],
    "answer": "新しい天と地",
    "explanation": "新しい天と地の創造は、神の完全な救済と新しい始まりを意味します（黙示録21章）。",
    "sources": [
      "黙示録 21:1"
    ],
    "tags": ["新約聖書 / 黙示録"]
  },
  {
    "question": "黙示録における全体のメッセージは、主にどのように要約されるでしょうか？",
    "choices": ["神の最終勝利と新たな創造", "人間の滅亡と無秩序", "科学の発展と調和", "歴史の反復"],
    "answer": "神の最終勝利と新たな創造",
    "explanation": "黙示録は、神の最終勝利、悪の敗北、そして新たな創造の到来を描く預言書です。",
    "sources": [
      "黙示録 全体"
    ],
    "tags": ["新約聖書 / 黙示録"]
  },
  {
    "question": "黙示録に登場する『目覚めの時』とは、主に何を指すのでしょうか？",
    "choices": ["信仰の再生", "人間の目覚め", "平和な時代", "科学の発展"],
    "answer": "信仰の再生",
    "explanation": "目覚めの時は、信者や世界が霊的に新たに目覚める瞬間を象徴します（黙示録 解釈例）。",
    "sources": [
      "黙示録 解釈例"
    ],
    "tags": ["新約聖書 / 黙示録"]
  },
  {
    "question": "黙示録において、『時の終わり』が描かれる際、最も強調されるテーマは何ですか？",
    "choices": ["神の正義と裁き", "人類の進歩", "科学の革命", "芸術の栄光"],
    "answer": "神の正義と裁き",
    "explanation": "時の終わりは、神の正義と最終的な裁きが顕現する時として描かれます（黙示録20章）。",
    "sources": [
      "黙示録 20章"
    ],
    "tags": ["新約聖書 / 黙示録"]
  },
  {
    "question": "黙示録において、『生ける水』は、何を象徴していると考えられますか？",
    "choices": ["霊的な生命", "暴力", "絶望", "混沌"],
    "answer": "霊的な生命",
    "explanation": "生ける水は、信者に与えられる霊的な生命と再生の象徴です（黙示録22章）。",
    "sources": [
      "黙示録 22:1-2"
    ],
    "tags": ["新約聖書 / 黙示録"]
  },
  {
    "question": "黙示録において、『滅びゆく者』に対して神はどのような結末を約束していますか？",
    "choices": ["永遠の刑罰", "再生の機会", "無記名の消滅", "祝福"],
    "answer": "永遠の刑罰",
    "explanation": "神は堕落した者たちに対し、最終的な永遠の刑罰を約束すると記されています（黙示録20章）。",
    "sources": [
      "黙示録 20:10-15"
    ],
    "tags": ["新約聖書 / 黙示録"]
  },
  {
    "question": "黙示録で『聖者』と呼ばれる者たちは、最終的にどこに住むと記されていますか？",
    "choices": ["新エルサレム", "地上", "地下", "天国の一部"],
    "answer": "新エルサレム",
    "explanation": "聖者は新エルサレムに住むという約束を受け、永遠の命を得るとされています（黙示録21章）。",
    "sources": [
      "黙示録 21章"
    ],
    "tags": ["新約聖書 / 黙示録"]
  },
  {
    "question": "黙示録において、『神の献身』が最もよく示される場面はどれですか？",
    "choices": ["子羊が巻物の封印を解く場面", "獣が現れる場面", "教会への書簡", "預言者の苦難"],
    "answer": "子羊が巻物の封印を解く場面",
    "explanation": "子羊による巻物の封印の解除は、神の救済計画と献身が示された象徴的な場面です（黙示録5章）。",
    "sources": [
      "黙示録 5章"
    ],
    "tags": ["新約聖書 / 黙示録"]
  },
  {
    "question": "黙示録に記された『新たに創られるもの』とは何を指していますか？",
    "choices": ["新しい天と地", "新しい教会", "新しい律法", "新しい国家"],
    "answer": "新しい天と地",
    "explanation": "新しい天と地の創造は、神の完全な救済と新しい始まりを意味します（黙示録21章）。",
    "sources": [
      "黙示録 21:1"
    ],
    "tags": ["新約聖書 / 黙示録"]
  },
  {
    "question": "黙示録における全体のメッセージは、主にどのように要約されるでしょうか？",
    "choices": ["神の最終勝利と新たな創造", "人間の滅亡と無秩序", "科学の発展と調和", "歴史の反復"],
    "answer": "神の最終勝利と新たな創造",
    "explanation": "黙示録は、神の最終勝利、悪の敗北、そして新たな創造の到来を描く預言書です。",
    "sources": [
      "黙示録 全体"
    ],
    "tags": ["新約聖書 / 黙示録"]
  }
]